Workbook

Sheet cbm_aug_2022
B1: Number of Announced Closures
A2: =IF(EDATE(DATE(2022,6,1), row(A2))<TODAY(), EDATE(DATE(2022,6,1), Row(A2)), "") -> 44774 | B2: =IF(A2="","",COUNTIFS(All_closures!$J$2:$J$1005, ">="& EDATE(DATE(2022,6,1), row(B2)),All_closures!$J$2:$J$1005, "<"& EDATE(DATE(2022,7,1), row(B2)))) -> 2
A3: =IF(EDATE(DATE(2022,6,1), row(A3))<TODAY(), EDATE(DATE(2022,6,1), Row(A3)), "") -> 44805 | B3: =IF(A3="","",COUNTIFS(All_closures!$J$2:$J$1005, ">="& EDATE(DATE(2022,6,1), row(B3)),All_closures!$J$2:$J$1005, "<"& EDATE(DATE(2022,7,1), row(B3)))) -> 0
A4: =IF(EDATE(DATE(2022,6,1), row(A4))<TODAY(), EDATE(DATE(2022,6,1), Row(A4)), "") -> 44835 | B4: =IF(A4="","",COUNTIFS(All_closures!$J$2:$J$1005, ">="& EDATE(DATE(2022,6,1), row(B4)),All_closures!$J$2:$J$1005, "<"& EDATE(DATE(2022,7,1), row(B4)))) -> 1
A5: =IF(EDATE(DATE(2022,6,1), row(A5))<TODAY(), EDATE(DATE(2022,6,1), Row(A5)), "") -> 44866 | B5: =IF(A5="","",COUNTIFS(All_closures!$J$2:$J$1005, ">="& EDATE(DATE(2022,6,1), row(B5)),All_closures!$J$2:$J$1005, "<"& EDATE(DATE(2022,7,1), row(B5)))) -> 1
A6: =IF(EDATE(DATE(2022,6,1), row(A6))<TODAY(), EDATE(DATE(2022,6,1), Row(A6)), "") -> 44896 | B6: =IF(A6="","",COUNTIFS(All_closures!$J$2:$J$1005, ">="& EDATE(DATE(2022,6,1), row(B6)),All_closures!$J$2:$J$1005, "<"& EDATE(DATE(2022,7,1), row(B6)))) -> 0
A7: =IF(EDATE(DATE(2022,6,1), row(A7))<TODAY(), EDATE(DATE(2022,6,1), Row(A7)), "") -> 44927 | B7: =IF(A7="","",COUNTIFS(All_closures!$J$2:$J$1005, ">="& EDATE(DATE(2022,6,1), row(B7)),All_closures!$J$2:$J$1005, "<"& EDATE(DATE(2022,7,1), row(B7)))) -> 8
A8: =IF(EDATE(DATE(2022,6,1), row(A8))<TODAY(), EDATE(DATE(2022,6,1), Row(A8)), "") -> 44958 | B8: =IF(A8="","",COUNTIFS(All_closures!$J$2:$J$1005, ">="& EDATE(DATE(2022,6,1), row(B8)),All_closures!$J$2:$J$1005, "<"& EDATE(DATE(2022,7,1), row(B8)))) -> 20
A9: =IF(EDATE(DATE(2022,6,1), row(A9))<TODAY(), EDATE(DATE(2022,6,1), Row(A9)), "") -> 44986 | B9: =IF(A9="","",COUNTIFS(All_closures!$J$2:$J$1005, ">="& EDATE(DATE(2022,6,1), row(B9)),All_closures!$J$2:$J$1005, "<"& EDATE(DATE(2022,7,1), row(B9)))) -> 5
A10: =IF(EDATE(DATE(2022,6,1), row(A10))<TODAY(), EDATE(DATE(2022,6,1), Row(A10)), "") -> 45017 | B10: =IF(A10="","",COUNTIFS(All_closures!$J$2:$J$1005, ">="& EDATE(DATE(2022,6,1), row(B10)),All_closures!$J$2:$J$1005, "<"& EDATE(DATE(2022,7,1), row(B10)))) -> 6
A11: =IF(EDATE(DATE(2022,6,1), row(A11))<TODAY(), EDATE(DATE(2022,6,1), Row(A11)), "") -> 45047 | B11: =IF(A11="","",COUNTIFS(All_closures!$J$2:$J$1005, ">="& EDATE(DATE(2022,6,1), row(B11)),All_closures!$J$2:$J$1005, "<"& EDATE(DATE(2022,7,1), row(B11)))) -> 5
A12: =IF(EDATE(DATE(2022,6,1), row(A12))<TODAY(), EDATE(DATE(2022,6,1), Row(A12)), "") -> 45078 | B12: =IF(A12="","",COUNTIFS(All_closures!$J$2:$J$1005, ">="& EDATE(DATE(2022,6,1), row(B12)),All_closures!$J$2:$J$1005, "<"& EDATE(DATE(2022,7,1), row(B12)))) -> 3
A13: =IF(EDATE(DATE(2022,6,1), row(A13))<TODAY(), EDATE(DATE(2022,6,1), Row(A13)), "") -> 45108 | B13: =IF(A13="","",COUNTIFS(All_closures!$J$2:$J$1005, ">="& EDATE(DATE(2022,6,1), row(B13)),All_closures!$J$2:$J$1005, "<"& EDATE(DATE(2022,7,1), row(B13)))) -> 3 | C13: =SUM(B2:B13) -> 54
A14: =IF(EDATE(DATE(2022,6,1), row(A14))<TODAY(), EDATE(DATE(2022,6,1), Row(A14)), "") -> 45139 | B14: =IF(A14="","",COUNTIFS(All_closures!$J$2:$J$1005, ">="& EDATE(DATE(2022,6,1), row(B14)),All_closures!$J$2:$J$1005, "<"& EDATE(DATE(2022,7,1), row(B14)))) -> 2
A15: =IF(EDATE(DATE(2022,6,1), row(A15))<TODAY(), EDATE(DATE(2022,6,1), Row(A15)), "") -> 45170 | B15: =IF(A15="","",COUNTIFS(All_closures!$J$2:$J$1005, ">="& EDATE(DATE(2022,6,1), row(B15)),All_closures!$J$2:$J$1005, "<"& EDATE(DATE(2022,7,1), row(B15)))) -> 2
A16: =IF(EDATE(DATE(2022,6,1), row(A16))<TODAY(), EDATE(DATE(2022,6,1), Row(A16)), "") -> 45200 | B16: =IF(A16="","",COUNTIFS(All_closures!$J$2:$J$1005, ">="& EDATE(DATE(2022,6,1), row(B16)),All_closures!$J$2:$J$1005, "<"& EDATE(DATE(2022,7,1), row(B16)))) -> 5
A17: =IF(EDATE(DATE(2022,6,1), row(A17))<TODAY(), EDATE(DATE(2022,6,1), Row(A17)), "") -> 45231 | B17: =IF(A17="","",COUNTIFS(All_closures!$J$2:$J$1005, ">="& EDATE(DATE(2022,6,1), row(B17)),All_closures!$J$2:$J$1005, "<"& EDATE(DATE(2022,7,1), row(B17)))) -> 1
A18: =IF(EDATE(DATE(2022,6,1), row(A18))<TODAY(), EDATE(DATE(2022,6,1), Row(A18)), "") -> 45261 | B18: =IF(A18="","",COUNTIFS(All_closures!$J$2:$J$1005, ">="& EDATE(DATE(2022,6,1), row(B18)),All_closures!$J$2:$J$1005, "<"& EDATE(DATE(2022,7,1), row(B18)))) -> 3
A19: =IF(EDATE(DATE(2022,6,1), row(A19))<TODAY(), EDATE(DATE(2022,6,1), Row(A19)), "") -> 45292 | B19: =IF(A19="","",COUNTIFS(All_closures!$J$2:$J$1005, ">="& EDATE(DATE(2022,6,1), row(B19)),All_closures!$J$2:$J$1005, "<"& EDATE(DATE(2022,7,1), row(B19)))) -> 6
A20: =IF(EDATE(DATE(2022,6,1), row(A20))<TODAY(), EDATE(DATE(2022,6,1), Row(A20)), "") -> 45323 | B20: =IF(A20="","",COUNTIFS(All_closures!$J$2:$J$1005, ">="& EDATE(DATE(2022,6,1), row(B20)),All_closures!$J$2:$J$1005, "<"& EDATE(DATE(2022,7,1), row(B20)))) -> 6
A21: =IF(EDATE(DATE(2022,6,1), row(A21))<TODAY(), EDATE(DATE(2022,6,1), Row(A21)), "") -> 45352 | B21: =IF(A21="","",COUNTIFS(All_closures!$J$2:$J$1005, ">="& EDATE(DATE(2022,6,1), row(B21)),All_closures!$J$2:$J$1005, "<"& EDATE(DATE(2022,7,1), row(B21)))) -> 7
A22: =IF(EDATE(DATE(2022,6,1), row(A22))<TODAY(), EDATE(DATE(2022,6,1), Row(A22)), "") -> 45383 | B22: =IF(A22="","",COUNTIFS(All_closures!$J$2:$J$1005, ">="& EDATE(DATE(2022,6,1), row(B22)),All_closures!$J$2:$J$1005, "<"& EDATE(DATE(2022,7,1), row(B22)))) -> 10
A23: =IF(EDATE(DATE(2022,6,1), row(A23))<TODAY(), EDATE(DATE(2022,6,1), Row(A23)), "") -> 45413 | B23: =IF(A23="","",COUNTIFS(All_closures!$J$2:$J$1005, ">="& EDATE(DATE(2022,6,1), row(B23)),All_closures!$J$2:$J$1005, "<"& EDATE(DATE(2022,7,1), row(B23)))) -> 11
A24: =IF(EDATE(DATE(2022,6,1), row(A24))<TODAY(), EDATE(DATE(2022,6,1), Row(A24)), "") -> 45444 | B24: =IF(A24="","",COUNTIFS(All_closures!$J$2:$J$1005, ">="& EDATE(DATE(2022,6,1), row(B24)),All_closures!$J$2:$J$1005, "<"& EDATE(DATE(2022,7,1), row(B24)))) -> 4
A25: =IF(EDATE(DATE(2022,6,1), row(A25))<TODAY(), EDATE(DATE(2022,6,1), Row(A25)), "") -> 45474 | B25: =IF(A25="","",COUNTIFS(All_closures!$J$2:$J$1005, ">="& EDATE(DATE(2022,6,1), row(B25)),All_closures!$J$2:$J$1005, "<"& EDATE(DATE(2022,7,1), row(B25)))) -> 3 | C25: =SUM(B14:B25) -> 60
A26: =IF(EDATE(DATE(2022,6,1), row(A26))<TODAY(), EDATE(DATE(2022,6,1), Row(A26)), "") -> 45505 | B26: =IF(A26="","",COUNTIFS(All_closures!$J$2:$J$1005, ">="& EDATE(DATE(2022,6,1), row(B26)),All_closures!$J$2:$J$1005, "<"& EDATE(DATE(2022,7,1), row(B26)))) -> 2
A27: =IF(EDATE(DATE(2022,6,1), row(A27))<TODAY(), EDATE(DATE(2022,6,1), Row(A27)), "") -> 45536 | B27: =IF(A27="","",COUNTIFS(All_closures!$J$2:$J$1005, ">="& EDATE(DATE(2022,6,1), row(B27)),All_closures!$J$2:$J$1005, "<"& EDATE(DATE(2022,7,1), row(B27)))) -> 4
A28: =IF(EDATE(DATE(2022,6,1), row(A28))<TODAY(), EDATE(DATE(2022,6,1), Row(A28)), "") -> 45566 | B28: =IF(A28="","",COUNTIFS(All_closures!$J$2:$J$1005, ">="& EDATE(DATE(2022,6,1), row(B28)),All_closures!$J$2:$J$1005, "<"& EDATE(DATE(2022,7,1), row(B28)))) -> 1
A29: =IF(EDATE(DATE(2022,6,1), row(A29))<TODAY(), EDATE(DATE(2022,6,1), Row(A29)), "") -> 45597 | B29: =IF(A29="","",COUNTIFS(All_closures!$J$2:$J$1005, ">="& EDATE(DATE(2022,6,1), row(B29)),All_closures!$J$2:$J$1005, "<"& EDATE(DATE(2022,7,1), row(B29)))) -> 1
A30: =IF(EDATE(DATE(2022,6,1), row(A30))<TODAY(), EDATE(DATE(2022,6,1), Row(A30)), "") -> 45627 | B30: =IF(A30="","",COUNTIFS(All_closures!$J$2:$J$1005, ">="& EDATE(DATE(2022,6,1), row(B30)),All_closures!$J$2:$J$1005, "<"& EDATE(DATE(2022,7,1), row(B30)))) -> 5
A31: =IF(EDATE(DATE(2022,6,1), row(A31))<TODAY(), EDATE(DATE(2022,6,1), Row(A31)), "") -> 45658 | B31: =IF(A31="","",COUNTIFS(All_closures!$J$2:$J$1005, ">="& EDATE(DATE(2022,6,1), row(B31)),All_closures!$J$2:$J$1005, "<"& EDATE(DATE(2022,7,1), row(B31)))) -> 9
A32: =IF(EDATE(DATE(2022,6,1), row(A32))<TODAY(), EDATE(DATE(2022,6,1), Row(A32)), "") -> 45689 | B32: =IF(A32="","",COUNTIFS(All_closures!$J$2:$J$1005, ">="& EDATE(DATE(2022,6,1), row(B32)),All_closures!$J$2:$J$1005, "<"& EDATE(DATE(2022,7,1), row(B32)))) -> 10
A33: =IF(EDATE(DATE(2022,6,1), row(A33))<TODAY(), EDATE(DATE(2022,6,1), Row(A33)), "") -> 45717 | B33: =IF(A33="","",COUNTIFS(All_closures!$J$2:$J$1005, ">="& EDATE(DATE(2022,6,1), row(B33)),All_closures!$J$2:$J$1005, "<"& EDATE(DATE(2022,7,1), row(B33)))) -> 6
A34: =IF(EDATE(DATE(2022,6,1), row(A34))<TODAY(), EDATE(DATE(2022,6,1), Row(A34)), "") -> 45748 | B34: =IF(A34="","",COUNTIFS(All_closures!$J$2:$J$1005, ">="& EDATE(DATE(2022,6,1), row(B34)),All_closures!$J$2:$J$1005, "<"& EDATE(DATE(2022,7,1), row(B34)))) -> 5
A35: =IF(EDATE(DATE(2022,6,1), row(A35))<TODAY(), EDATE(DATE(2022,6,1), Row(A35)), "") -> 45778 | B35: =IF(A35="","",COUNTIFS(All_closures!$J$2:$J$1005, ">="& EDATE(DATE(2022,6,1), row(B35)),All_closures!$J$2:$J$1005, "<"& EDATE(DATE(2022,7,1), row(B35)))) -> 4
A36: =IF(EDATE(DATE(2022,6,1), row(A36))<TODAY(), EDATE(DATE(2022,6,1), Row(A36)), "") -> 45809 | B36: =IF(A36="","",COUNTIFS(All_closures!$J$2:$J$1005, ">="& EDATE(DATE(2022,6,1), row(B36)),All_closures!$J$2:$J$1005, "<"& EDATE(DATE(2022,7,1), row(B36)))) -> 4
A37: =IF(EDATE(DATE(2022,6,1), row(A37))<TODAY(), EDATE(DATE(2022,6,1), Row(A37)), "") -> 45839 | B37: =IF(A37="","",COUNTIFS(All_closures!$J$2:$J$1005, ">="& EDATE(DATE(2022,6,1), row(B37)),All_closures!$J$2:$J$1005, "<"& EDATE(DATE(2022,7,1), row(B37)))) -> 1
... A50: =IF(EDATE(DATE(2022,6,1), row(A50))<TODAY(), EDATE(DATE(2022,6,1), Row(A50)), "") | B50: =IF(A50="","",COUNTIFS(All_closures!$J$2:$J$1005, ">="& EDATE(DATE(2022,6,1), row(B50)),All_closures!$J$2:$J$1005, "<"& EDATE(DATE(2022,7,1), row(B50))))

Sheet cbm_aug_2023
B1: Number of Announced Closures
A2: =IF(EDATE(DATE(2023,6,1), row(A2))<TODAY(), EDATE(DATE(2023,6,1), Row(A2)), "") -> 45139 | B2: =IF(A2="","",COUNTIFS(All_closures!$J$2:$J$1005, ">="& EDATE(DATE(2023,6,1), row(B2)),All_closures!$J$2:$J$1005, "<"& EDATE(DATE(2023,7,1), row(B2)))) -> 2
A3: =IF(EDATE(DATE(2023,6,1), row(A3))<TODAY(), EDATE(DATE(2023,6,1), Row(A3)), "") -> 45170 | B3: =IF(A3="","",COUNTIFS(All_closures!$J$2:$J$1005, ">="& EDATE(DATE(2023,6,1), row(B3)),All_closures!$J$2:$J$1005, "<"& EDATE(DATE(2023,7,1), row(B3)))) -> 2
A4: =IF(EDATE(DATE(2023,6,1), row(A4))<TODAY(), EDATE(DATE(2023,6,1), Row(A4)), "") -> 45200 | B4: =IF(A4="","",COUNTIFS(All_closures!$J$2:$J$1005, ">="& EDATE(DATE(2023,6,1), row(B4)),All_closures!$J$2:$J$1005, "<"& EDATE(DATE(2023,7,1), row(B4)))) -> 5
A5: =IF(EDATE(DATE(2023,6,1), row(A5))<TODAY(), EDATE(DATE(2023,6,1), Row(A5)), "") -> 45231 | B5: =IF(A5="","",COUNTIFS(All_closures!$J$2:$J$1005, ">="& EDATE(DATE(2023,6,1), row(B5)),All_closures!$J$2:$J$1005, "<"& EDATE(DATE(2023,7,1), row(B5)))) -> 1
A6: =IF(EDATE(DATE(2023,6,1), row(A6))<TODAY(), EDATE(DATE(2023,6,1), Row(A6)), "") -> 45261 | B6: =IF(A6="","",COUNTIFS(All_closures!$J$2:$J$1005, ">="& EDATE(DATE(2023,6,1), row(B6)),All_closures!$J$2:$J$1005, "<"& EDATE(DATE(2023,7,1), row(B6)))) -> 3
A7: =IF(EDATE(DATE(2023,6,1), row(A7))<TODAY(), EDATE(DATE(2023,6,1), Row(A7)), "") -> 45292 | B7: =IF(A7="","",COUNTIFS(All_closures!$J$2:$J$1005, ">="& EDATE(DATE(2023,6,1), row(B7)),All_closures!$J$2:$J$1005, "<"& EDATE(DATE(2023,7,1), row(B7)))) -> 6
A8: =IF(EDATE(DATE(2023,6,1), row(A8))<TODAY(), EDATE(DATE(2023,6,1), Row(A8)), "") -> 45323 | B8: =IF(A8="","",COUNTIFS(All_closures!$J$2:$J$1005, ">="& EDATE(DATE(2023,6,1), row(B8)),All_closures!$J$2:$J$1005, "<"& EDATE(DATE(2023,7,1), row(B8)))) -> 6
A9: =IF(EDATE(DATE(2023,6,1), row(A9))<TODAY(), EDATE(DATE(2023,6,1), Row(A9)), "") -> 45352 | B9: =IF(A9="","",COUNTIFS(All_closures!$J$2:$J$1005, ">="& EDATE(DATE(2023,6,1), row(B9)),All_closures!$J$2:$J$1005, "<"& EDATE(DATE(2023,7,1), row(B9)))) -> 7
A10: =IF(EDATE(DATE(2023,6,1), row(A10))<TODAY(), EDATE(DATE(2023,6,1), Row(A10)), "") -> 45383 | B10: =IF(A10="","",COUNTIFS(All_closures!$J$2:$J$1005, ">="& EDATE(DATE(2023,6,1), row(B10)),All_closures!$J$2:$J$1005, "<"& EDATE(DATE(2023,7,1), row(B10)))) -> 10
A11: =IF(EDATE(DATE(2023,6,1), row(A11))<TODAY(), EDATE(DATE(2023,6,1), Row(A11)), "") -> 45413 | B11: =IF(A11="","",COUNTIFS(All_closures!$J$2:$J$1005, ">="& EDATE(DATE(2023,6,1), row(B11)),All_closures!$J$2:$J$1005, "<"& EDATE(DATE(2023,7,1), row(B11)))) -> 11
A12: =IF(EDATE(DATE(2023,6,1), row(A12))<TODAY(), EDATE(DATE(2023,6,1), Row(A12)), "") -> 45444 | B12: =IF(A12="","",COUNTIFS(All_closures!$J$2:$J$1005, ">="& EDATE(DATE(2023,6,1), row(B12)),All_closures!$J$2:$J$1005, "<"& EDATE(DATE(2023,7,1), row(B12)))) -> 4
A13: =IF(EDATE(DATE(2023,6,1), row(A13))<TODAY(), EDATE(DATE(2023,6,1), Row(A13)), "") -> 45474 | B13: =IF(A13="","",COUNTIFS(All_closures!$J$2:$J$1005, ">="& EDATE(DATE(2023,6,1), row(B13)),All_closures!$J$2:$J$1005, "<"& EDATE(DATE(2023,7,1), row(B13)))) -> 3
A35: =IF(EDATE(DATE(2023,6,1), row(A35))<TODAY(), EDATE(DATE(2023,6,1), Row(A35)), "") -> 46143
A36: =IF(EDATE(DATE(2023,6,1), row(A36))<TODAY(), EDATE(DATE(2023,6,1), Row(A36)), "") -> 46174
A37: =IF(EDATE(DATE(2023,6,1), row(A37))<TODAY(), EDATE(DATE(2023,6,1), Row(A37)), "") -> 46204
A38: =IF(EDATE(DATE(2023,6,1), row(A38))<TODAY(), EDATE(DATE(2023,6,1), Row(A38)), "")
A39: =IF(EDATE(DATE(2023,6,1), row(A39))<TODAY(), EDATE(DATE(2023,6,1), Row(A39)), "")
A40: =IF(EDATE(DATE(2023,6,1), row(A40))<TODAY(), EDATE(DATE(2023,6,1), Row(A40)), "")
A41: =IF(EDATE(DATE(2023,6,1), row(A41))<TODAY(), EDATE(DATE(2023,6,1), Row(A41)), "") | B41: =IF(A41="","",COUNTIFS(All_closures!$J$2:$J$1005, ">="& EDATE(DATE(2023,6,1), row(B41)),All_closures!$J$2:$J$1005, "<"& EDATE(DATE(2023,7,1), row(B41))))
A42: =IF(EDATE(DATE(2023,6,1), row(A42))<TODAY(), EDATE(DATE(2023,6,1), Row(A42)), "") | B42: =IF(A42="","",COUNTIFS(All_closures!$J$2:$J$1005, ">="& EDATE(DATE(2023,6,1), row(B42)),All_closures!$J$2:$J$1005, "<"& EDATE(DATE(2023,7,1), row(B42))))
A43: =IF(EDATE(DATE(2023,6,1), row(A43))<TODAY(), EDATE(DATE(2023,6,1), Row(A43)), "") | B43: =IF(A43="","",COUNTIFS(All_closures!$J$2:$J$1005, ">="& EDATE(DATE(2023,6,1), row(B43)),All_closures!$J$2:$J$1005, "<"& EDATE(DATE(2023,7,1), row(B43))))
A44: =IF(EDATE(DATE(2023,6,1), row(A44))<TODAY(), EDATE(DATE(2023,6,1), Row(A44)), "") | B44: =IF(A44="","",COUNTIFS(All_closures!$J$2:$J$1005, ">="& EDATE(DATE(2023,6,1), row(B44)),All_closures!$J$2:$J$1005, "<"& EDATE(DATE(2023,7,1), row(B44))))
A45: =IF(EDATE(DATE(2023,6,1), row(A45))<TODAY(), EDATE(DATE(2023,6,1), Row(A45)), "") | B45: =IF(A45="","",COUNTIFS(All_closures!$J$2:$J$1005, ">="& EDATE(DATE(2023,6,1), row(B45)),All_closures!$J$2:$J$1005, "<"& EDATE(DATE(2023,7,1), row(B45))))
A46: =IF(EDATE(DATE(2023,6,1), row(A46))<TODAY(), EDATE(DATE(2023,6,1), Row(A46)), "") | B46: =IF(A46="","",COUNTIFS(All_closures!$J$2:$J$1005, ">="& EDATE(DATE(2023,6,1), row(B46)),All_closures!$J$2:$J$1005, "<"& EDATE(DATE(2023,7,1), row(B46))))
A47: =IF(EDATE(DATE(2023,6,1), row(A47))<TODAY(), EDATE(DATE(2023,6,1), Row(A47)), "") | B47: =IF(A47="","",COUNTIFS(All_closures!$J$2:$J$1005, ">="& EDATE(DATE(2023,6,1), row(B47)),All_closures!$J$2:$J$1005, "<"& EDATE(DATE(2023,7,1), row(B47))))
A48: =IF(EDATE(DATE(2023,6,1), row(A48))<TODAY(), EDATE(DATE(2023,6,1), Row(A48)), "") | B48: =IF(A48="","",COUNTIFS(All_closures!$J$2:$J$1005, ">="& EDATE(DATE(2023,6,1), row(B48)),All_closures!$J$2:$J$1005, "<"& EDATE(DATE(2023,7,1), row(B48))))
A49: =IF(EDATE(DATE(2023,6,1), row(A49))<TODAY(), EDATE(DATE(2023,6,1), Row(A49)), "") | B49: =IF(A49="","",COUNTIFS(All_closures!$J$2:$J$1005, ">="& EDATE(DATE(2023,6,1), row(B49)),All_closures!$J$2:$J$1005, "<"& EDATE(DATE(2023,7,1), row(B49))))
A50: =IF(EDATE(DATE(2023,6,1), row(A50))<TODAY(), EDATE(DATE(2023,6,1), Row(A50)), "") | B50: =IF(A50="","",COUNTIFS(All_closures!$J$2:$J$1005, ">="& EDATE(DATE(2023,6,1), row(B50)),All_closures!$J$2:$J$1005, "<"& EDATE(DATE(2023,7,1), row(B50))))
A51: =IF(EDATE(DATE(2023,6,1), row(A51))<TODAY(), EDATE(DATE(2023,6,1), Row(A51)), "") | B51: =IF(A51="","",COUNTIFS(All_closures!$J$2:$J$1005, ">="& EDATE(DATE(2023,6,1), row(B51)),All_closures!$J$2:$J$1005, "<"& EDATE(DATE(2023,7,1), row(B51))))
A52: =IF(EDATE(DATE(2023,6,1), row(A52))<TODAY(), EDATE(DATE(2023,6,1), Row(A52)), "") | B52: =IF(A52="","",COUNTIFS(All_closures!$J$2:$J$1005, ">="& EDATE(DATE(2023,6,1), row(B52)),All_closures!$J$2:$J$1005, "<"& EDATE(DATE(2023,7,1), row(B52))))
... A61: =IF(EDATE(DATE(2023,6,1), row(A61))<TODAY(), EDATE(DATE(2023,6,1), Row(A61)), "") | B61: =IF(A61="","",COUNTIFS(All_closures!$J$2:$J$1005, ">="& EDATE(DATE(2023,6,1), row(B61)),All_closures!$J$2:$J$1005, "<"& EDATE(DATE(2023,7,1), row(B61))))

Sheet cbm_aug_2024
B1: Number of Announced Closures
A2: =IF(EDATE(DATE(2024,6,1), row(A2))<TODAY(), EDATE(DATE(2024,6,1), Row(A2)), "") -> 45505 | B2: =IF(A2="","",COUNTIFS(All_closures!$J$2:$J$1005, ">="& EDATE(DATE(2024,6,1), row(B2)),All_closures!$J$2:$J$1005, "<"& EDATE(DATE(2024,7,1), row(B2)))) -> 2
A3: =IF(EDATE(DATE(2024,6,1), row(A3))<TODAY(), EDATE(DATE(2024,6,1), Row(A3)), "") -> 45536 | B3: =IF(A3="","",COUNTIFS(All_closures!$J$2:$J$1005, ">="& EDATE(DATE(2024,6,1), row(B3)),All_closures!$J$2:$J$1005, "<"& EDATE(DATE(2024,7,1), row(B3)))) -> 4
A4: =IF(EDATE(DATE(2024,6,1), row(A4))<TODAY(), EDATE(DATE(2024,6,1), Row(A4)), "") -> 45566 | B4: =IF(A4="","",COUNTIFS(All_closures!$J$2:$J$1005, ">="& EDATE(DATE(2024,6,1), row(B4)),All_closures!$J$2:$J$1005, "<"& EDATE(DATE(2024,7,1), row(B4)))) -> 1
A5: =IF(EDATE(DATE(2024,6,1), row(A5))<TODAY(), EDATE(DATE(2024,6,1), Row(A5)), "") -> 45597 | B5: =IF(A5="","",COUNTIFS(All_closures!$J$2:$J$1005, ">="& EDATE(DATE(2024,6,1), row(B5)),All_closures!$J$2:$J$1005, "<"& EDATE(DATE(2024,7,1), row(B5)))) -> 1
A6: =IF(EDATE(DATE(2024,6,1), row(A6))<TODAY(), EDATE(DATE(2024,6,1), Row(A6)), "") -> 45627 | B6: =IF(A6="","",COUNTIFS(All_closures!$J$2:$J$1005, ">="& EDATE(DATE(2024,6,1), row(B6)),All_closures!$J$2:$J$1005, "<"& EDATE(DATE(2024,7,1), row(B6)))) -> 5
A7: =IF(EDATE(DATE(2024,6,1), row(A7))<TODAY(), EDATE(DATE(2024,6,1), Row(A7)), "") -> 45658 | B7: =IF(A7="","",COUNTIFS(All_closures!$J$2:$J$1005, ">="& EDATE(DATE(2024,6,1), row(B7)),All_closures!$J$2:$J$1005, "<"& EDATE(DATE(2024,7,1), row(B7)))) -> 9
A8: =IF(EDATE(DATE(2024,6,1), row(A8))<TODAY(), EDATE(DATE(2024,6,1), Row(A8)), "") -> 45689 | B8: =IF(A8="","",COUNTIFS(All_closures!$J$2:$J$1005, ">="& EDATE(DATE(2024,6,1), row(B8)),All_closures!$J$2:$J$1005, "<"& EDATE(DATE(2024,7,1), row(B8)))) -> 10
A9: =IF(EDATE(DATE(2024,6,1), row(A9))<TODAY(), EDATE(DATE(2024,6,1), Row(A9)), "") -> 45717 | B9: =IF(A9="","",COUNTIFS(All_closures!$J$2:$J$1005, ">="& EDATE(DATE(2024,6,1), row(B9)),All_closures!$J$2:$J$1005, "<"& EDATE(DATE(2024,7,1), row(B9)))) -> 6
A10: =IF(EDATE(DATE(2024,6,1), row(A10))<TODAY(), EDATE(DATE(2024,6,1), Row(A10)), "") -> 45748 | B10: =IF(A10="","",COUNTIFS(All_closures!$J$2:$J$1005, ">="& EDATE(DATE(2024,6,1), row(B10)),All_closures!$J$2:$J$1005, "<"& EDATE(DATE(2024,7,1), row(B10)))) -> 5
A11: =IF(EDATE(DATE(2024,6,1), row(A11))<TODAY(), EDATE(DATE(2024,6,1), Row(A11)), "") -> 45778 | B11: =IF(A11="","",COUNTIFS(All_closures!$J$2:$J$1005, ">="& EDATE(DATE(2024,6,1), row(B11)),All_closures!$J$2:$J$1005, "<"& EDATE(DATE(2024,7,1), row(B11)))) -> 4
A12: =IF(EDATE(DATE(2024,6,1), row(A12))<TODAY(), EDATE(DATE(2024,6,1), Row(A12)), "") -> 45809 | B12: =IF(A12="","",COUNTIFS(All_closures!$J$2:$J$1005, ">="& EDATE(DATE(2024,6,1), row(B12)),All_closures!$J$2:$J$1005, "<"& EDATE(DATE(2024,7,1), row(B12)))) -> 4
A13: =IF(EDATE(DATE(2024,6,1), row(A13))<TODAY(), EDATE(DATE(2024,6,1), Row(A13)), "") -> 45839 | B13: =IF(A13="","",COUNTIFS(All_closures!$J$2:$J$1005, ">="& EDATE(DATE(2024,6,1), row(B13)),All_closures!$J$2:$J$1005, "<"& EDATE(DATE(2024,7,1), row(B13)))) -> 1
A14: =IF(EDATE(DATE(2024,6,1), row(A14))<TODAY(), EDATE(DATE(2024,6,1), Row(A14)), "") -> 45870 | B14: =IF(A14="","",COUNTIFS(All_closures!$J$2:$J$1005, ">="& EDATE(DATE(2024,6,1), row(B14)),All_closures!$J$2:$J$1005, "<"& EDATE(DATE(2024,7,1), row(B14)))) -> 0
A15: =IF(EDATE(DATE(2024,6,1), row(A15))<TODAY(), EDATE(DATE(2024,6,1), Row(A15)), "") -> 45901
A16: =IF(EDATE(DATE(2024,6,1), row(A16))<TODAY(), EDATE(DATE(2024,6,1), Row(A16)), "") -> 45931 | B16: =IF(A16="","",COUNTIFS(All_closures!$J$2:$J$1005, ">="& EDATE(DATE(2024,6,1), row(B16)),All_closures!$J$2:$J$1005, "<"& EDATE(DATE(2024,7,1), row(B16)))) -> 2
A17: =IF(EDATE(DATE(2024,6,1), row(A17))<TODAY(), EDATE(DATE(2024,6,1), Row(A17)), "") -> 45962 | B17: =IF(A17="","",COUNTIFS(All_closures!$J$2:$J$1005, ">="& EDATE(DATE(2024,6,1), row(B17)),All_closures!$J$2:$J$1005, "<"& EDATE(DATE(2024,7,1), row(B17)))) -> 2
A18: =IF(EDATE(DATE(2024,6,1), row(A18))<TODAY(), EDATE(DATE(2024,6,1), Row(A18)), "") -> 45992 | B18: =IF(A18="","",COUNTIFS(All_closures!$J$2:$J$1005, ">="& EDATE(DATE(2024,6,1), row(B18)),All_closures!$J$2:$J$1005, "<"& EDATE(DATE(2024,7,1), row(B18)))) -> 2
A19: =IF(EDATE(DATE(2024,6,1), row(A19))<TODAY(), EDATE(DATE(2024,6,1), Row(A19)), "") -> 46023 | B19: =IF(A19="","",COUNTIFS(All_closures!$J$2:$J$1005, ">="& EDATE(DATE(2024,6,1), row(B19)),All_closures!$J$2:$J$1005, "<"& EDATE(DATE(2024,7,1), row(B19)))) -> 11
A20: =IF(EDATE(DATE(2024,6,1), row(A20))<TODAY(), EDATE(DATE(2024,6,1), Row(A20)), "") -> 46054 | B20: =IF(A20="","",COUNTIFS(All_closures!$J$2:$J$1005, ">="& EDATE(DATE(2024,6,1), row(B20)),All_closures!$J$2:$J$1005, "<"& EDATE(DATE(2024,7,1), row(B20)))) -> 12
A21: =IF(EDATE(DATE(2024,6,1), row(A21))<TODAY(), EDATE(DATE(2024,6,1), Row(A21)), "") -> 46082 | B21: =IF(A21="","",COUNTIFS(All_closures!$J$2:$J$1005, ">="& EDATE(DATE(2024,6,1), row(B21)),All_closures!$J$2:$J$1005, "<"& EDATE(DATE(2024,7,1), row(B21)))) -> 13
A22: =IF(EDATE(DATE(2024,6,1), row(A22))<TODAY(), EDATE(DATE(2024,6,1), Row(A22)), "") -> 46113 | B22: =IF(A22="","",COUNTIFS(All_closures!$J$2:$J$1005, ">="& EDATE(DATE(2024,6,1), row(B22)),All_closures!$J$2:$J$1005, "<"& EDATE(DATE(2024,7,1), row(B22)))) -> 1
A23: =IF(EDATE(DATE(2024,6,1), row(A23))<TODAY(), EDATE(DATE(2024,6,1), Row(A23)), "") -> 46143 | B23: =IF(A23="","",COUNTIFS(All_closures!$J$2:$J$1005, ">="& EDATE(DATE(2024,6,1), row(B23)),All_closures!$J$2:$J$1005, "<"& EDATE(DATE(2024,7,1), row(B23)))) -> 6
A24: =IF(EDATE(DATE(2024,6,1), row(A24))<TODAY(), EDATE(DATE(2024,6,1), Row(A24)), "") -> 46174 | B24: =IF(A24="","",COUNTIFS(All_closures!$J$2:$J$1005, ">="& EDATE(DATE(2024,6,1), row(B24)),All_closures!$J$2:$J$1005, "<"& EDATE(DATE(2024,7,1), row(B24)))) -> 13
A25: =IF(EDATE(DATE(2024,6,1), row(A25))<TODAY(), EDATE(DATE(2024,6,1), Row(A25)), "") -> 46204 | B25: =IF(A25="","",COUNTIFS(All_closures!$J$2:$J$1005, ">="& EDATE(DATE(2024,6,1), row(B25)),All_closures!$J$2:$J$1005, "<"& EDATE(DATE(2024,7,1), row(B25)))) -> 4
A26: =IF(EDATE(DATE(2024,6,1), row(A26))<TODAY(), EDATE(DATE(2024,6,1), Row(A26)), "") | B26: =IF(A26="","",COUNTIFS(All_closures!$J$2:$J$1005, ">="& EDATE(DATE(2024,6,1), row(B26)),All_closures!$J$2:$J$1005, "<"& EDATE(DATE(2024,7,1), row(B26))))
A27: =IF(EDATE(DATE(2024,6,1), row(A27))<TODAY(), EDATE(DATE(2024,6,1), Row(A27)), "") | B27: =IF(A27="","",COUNTIFS(All_closures!$J$2:$J$1005, ">="& EDATE(DATE(2023,6,1), row(B27)),All_closures!$J$2:$J$1005, "<"& EDATE(DATE(2023,7,1), row(B27))))
A28: =IF(EDATE(DATE(2023,6,1), row(A28))<TODAY(), EDATE(DATE(2023,6,1), Row(A28)), "") -> 45931 | B28: =IF(A28="","",COUNTIFS(All_closures!$J$2:$J$1005, ">="& EDATE(DATE(2023,6,1), row(B28)),All_closures!$J$2:$J$1005, "<"& EDATE(DATE(2023,7,1), row(B28)))) -> 2
A29: =IF(EDATE(DATE(2023,6,1), row(A29))<TODAY(), EDATE(DATE(2023,6,1), Row(A29)), "") -> 45962 | B29: =IF(A29="","",COUNTIFS(All_closures!$J$2:$J$1005, ">="& EDATE(DATE(2023,6,1), row(B29)),All_closures!$J$2:$J$1005, "<"& EDATE(DATE(2023,7,1), row(B29)))) -> 2
A30: =IF(EDATE(DATE(2023,6,1), row(A30))<TODAY(), EDATE(DATE(2023,6,1), Row(A30)), "") -> 45992 | B30: =IF(A30="","",COUNTIFS(All_closures!$J$2:$J$1005, ">="& EDATE(DATE(2023,6,1), row(B30)),All_closures!$J$2:$J$1005, "<"& EDATE(DATE(2023,7,1), row(B30)))) -> 2
A31: =IF(EDATE(DATE(2023,6,1), row(A31))<TODAY(), EDATE(DATE(2023,6,1), Row(A31)), "") -> 46023 | B31: =IF(A31="","",COUNTIFS(All_closures!$J$2:$J$1005, ">="& EDATE(DATE(2023,6,1), row(B31)),All_closures!$J$2:$J$1005, "<"& EDATE(DATE(2023,7,1), row(B31)))) -> 11
A32: =IF(EDATE(DATE(2023,6,1), row(A32))<TODAY(), EDATE(DATE(2023,6,1), Row(A32)), "") -> 46054 | B32: =IF(A32="","",COUNTIFS(All_closures!$J$2:$J$1005, ">="& EDATE(DATE(2023,6,1), row(B32)),All_closures!$J$2:$J$1005, "<"& EDATE(DATE(2023,7,1), row(B32)))) -> 12
A33: =IF(EDATE(DATE(2023,6,1), row(A33))<TODAY(), EDATE(DATE(2023,6,1), Row(A33)), "") -> 46082 | B33: =IF(A33="","",COUNTIFS(All_closures!$J$2:$J$1005, ">="& EDATE(DATE(2023,6,1), row(B33)),All_closures!$J$2:$J$1005, "<"& EDATE(DATE(2023,7,1), row(B33)))) -> 13
A34: =IF(EDATE(DATE(2023,6,1), row(A34))<TODAY(), EDATE(DATE(2023,6,1), Row(A34)), "") -> 46113 | B34: =IF(A34="","",COUNTIFS(All_closures!$J$2:$J$1005, ">="& EDATE(DATE(2023,6,1), row(B34)),All_closures!$J$2:$J$1005, "<"& EDATE(DATE(2023,7,1), row(B34)))) -> 1
A35: =IF(EDATE(DATE(2023,6,1), row(A35))<TODAY(), EDATE(DATE(2023,6,1), Row(A35)), "") -> 46143 | B35: =IF(A35="","",COUNTIFS(All_closures!$J$2:$J$1005, ">="& EDATE(DATE(2023,6,1), row(B35)),All_closures!$J$2:$J$1005, "<"& EDATE(DATE(2023,7,1), row(B35)))) -> 6
A36: =IF(EDATE(DATE(2023,6,1), row(A36))<TODAY(), EDATE(DATE(2023,6,1), Row(A36)), "") -> 46174 | B36: =IF(A36="","",COUNTIFS(All_closures!$J$2:$J$1005, ">="& EDATE(DATE(2023,6,1), row(B36)),All_closures!$J$2:$J$1005, "<"& EDATE(DATE(2023,7,1), row(B36)))) -> 13
A37: =IF(EDATE(DATE(2023,6,1), row(A37))<TODAY(), EDATE(DATE(2023,6,1), Row(A37)), "") -> 46204 | B37: =IF(A37="","",COUNTIFS(All_closures!$J$2:$J$1005, ">="& EDATE(DATE(2023,6,1), row(B37)),All_closures!$J$2:$J$1005, "<"& EDATE(DATE(2023,7,1), row(B37)))) -> 4
A38: =IF(EDATE(DATE(2023,6,1), row(A38))<TODAY(), EDATE(DATE(2023,6,1), Row(A38)), "") | B38: =IF(A38="","",COUNTIFS(All_closures!$J$2:$J$1005, ">="& EDATE(DATE(2023,6,1), row(B38)),All_closures!$J$2:$J$1005, "<"& EDATE(DATE(2023,7,1), row(B38))))
A39: =IF(EDATE(DATE(2023,6,1), row(A39))<TODAY(), EDATE(DATE(2023,6,1), Row(A39)), "") | B39: =IF(A39="","",COUNTIFS(All_closures!$J$2:$J$1005, ">="& EDATE(DATE(2023,6,1), row(B39)),All_closures!$J$2:$J$1005, "<"& EDATE(DATE(2023,7,1), row(B39))))
... A61: =IF(EDATE(DATE(2023,6,1), row(A61))<TODAY(), EDATE(DATE(2023,6,1), Row(A61)), "") | B61: =IF(A61="","",COUNTIFS(All_closures!$J$2:$J$1005, ">="& EDATE(DATE(2023,6,1), row(B61)),All_closures!$J$2:$J$1005, "<"& EDATE(DATE(2023,7,1), row(B61))))

Sheet All_openings
B1: Name | C1: Link | D1: Town | E1: State | F1: Region | G1: Type | H1: Date Reported | I1: Expected Opening Date | J1: Expected Enrollment | K1: Source/Links | L1: Notes | M1: Annual Tuition | N1: Tuition Notes | O1: Link | P1: Full Address | Q1: Estimated Tract Median Family Income | R1: Data Year | S1: Microschool?
A2: =row()-1 -> 1 | B2: Avenues Sillicon Valley | C2: https://www.asumag.com/facilities-management/business-finance/article/21238677/private-school-based-in-new-york-city-buys-property-in-san-jose-calif-plans-prek12-campus | D2: San Jose | E2: CA | F2: West | G2: Independent | H2: 43556 | I2: Fall 2022 | K2: https://www.sanjoseinside.com/news/exclusive-private-school-to-open-silicon-valley-campus/ | M2: 57500 | O2: https://www.avenues.org/sv/tuition-financial-aid | P2: 570 Meridian Ave San Jose, CA 95126 | Q2: 107689 | R2: 2021
A3: =row()-1 -> 2 | B3: Christo Rey Research Triangle High School | C3: https://dioceseofraleigh.org/news/cristo-rey-rtp-announces-jesuit-affiliation-planned-high-school | D3: Raleigh | E3: NC | F3: South | G3: Roman Catholic | H3: 43900 | I3: Fall 2021 | J3: 100 | K3: https://www.cristoreyrt.org/ | M3: 700 | N3: 70/month for 10 months. Sliding scale and work contributions | O3: https://www.cristoreyrt.org/apps/pages/index.jsp?uREC_ID=2126760&type=d&pREC_ID=2156787 | P3: 334 Blackwell Street, Durham, NC 27701 | Q3: 100474 | R3: 2020
A4: =row()-1 -> 3 | B4: All Saints Catholic Academy | C4: https://patch.com/connecticut/naugatuck/new-catholic-school-open-new-haven | D4: New Haven | E4: CT | F4: Northeast | G4: Roman Catholic | H4: 43959 | I4: Fall 2021 | K4: https://allsaintsnewhaven.org/ | L4: Formed from merging three New Haven Catholic elementary schools | M4: 4350 | N4: Catholic + Non Catholic Average | O4: https://allsaintsnewhaven.org/admissions/tuition | P4: 423 Ferry Street New Haven, CT 06513 | Q4: 91800 | R4: 2020
A5: =row()-1 -> 4 | B5: Chesterton Academy of Notre Dame | C5: https://www.spokesman.com/stories/2020/may/12/new-catholic-high-school-to-open-in-downtown-spoka/ | D5: Spokane | E5: WA | F5: West | G5: Roman Catholic | H5: 43963 | I5: Fall 2020 | J5: 160 | K5: https://chestertonacademyofnotredame.org/ | M5: 7500 | O5: https://chestertonacademyofnotredame.org/admissions | P5: 2706 E Queen Ave, Spokane, WA 99217 | Q5: 48986 | R5: 2020
A6: =row()-1 -> 5 | B6: Fairmont San Juan Capistrano | C6: https://www.prnewswire.com/news-releases/fairmont-schools-to-open-new-san-juan-capistrano-campus-301059547.html | D6: San Juan Capistrano | E6: CA | F6: West | G6: Independent | H6: 43965 | I6: Fall 2020 | J6: 850 | K6: https://www.fairmontschools.com/campuses/san-juan-capistrano-campus/ | M6: 22470 | O6: https://cdn.brandfolder.io/4N7CPF37/as/q05m7c-g0aw48-4bthtw/P12_Tuition__Fee_Information.pdf | P6: 26333 Oso Rd, San Juan Capistrano, CA 92675 | Q6: 52839 | R6: 2020
A7: =row()-1 -> 6 | B7: Gloria Deo Academy | C7: https://www.koamnewsnow.com/new-school-opening-in-joplin-provides-unique-combination-of-private-and-homeschool-education/ | D7: Joplin | E7: MO | F7: Midwest | G7: Christian | H7: 43970 | I7: Fall 2020 | K7: https://gloriadeoacademy.org/ | M7: 2880 | N7: 288 average/month for 10 months | O7: https://gloriadeoacademy.org/tuition-fees/ | P7: 600 E 50th St, Joplin, MO 64804 | Q7: 71238 | R7: 2020
A8: =row()-1 -> 7 | B8: Avenues Studio Hampton | C8: https://www.businessinsider.com/nyc-private-school-opening-hamptons-avenues-2020-5 | D8: New York City | E8: NY | F8: Northeast | G8: Independent | H8: 43979 | I8: Fall 2020 | J8: 150 | K8: https://www.avenues.org/ht/ | L8: Most classes online but some events in person | M8: 48000 | O8: https://www.businessinsider.com/nyc-private-school-opening-hamptons-avenues-2020-5 | P8: 11 Madison Square North New York, NY 10010-1420 | Q8: 268819
A9: =row()-1 -> 8 | B9: Fusion Academy | C9: https://www.wickedlocal.com/story/hingham-journal/2020/06/17/new-private-school-opens-in-hingham/42940191/ | D9: Hingham | E9: MA | F9: Northeast | G9: Independent | H9: 43999 | I9: Fall 2020 | J9: 60 | K9: https://www.fusionacademy.com/campuses/hingham/ | M9: 54150 | N9: 4512 average per middle school and high school class, 6 classes per term, two terms in a year | O9: https://www.fusionacademy.com/campuses/hingham/tuition/ | P9: 99 Derby Street Suite 103 Hingham, MA 02043 | Q9: 181357 | R9: 2020
A10: =row()-1 -> 9 | B10: Saint John Neumann Catholic School | C10: https://www.fox43.com/article/news/local/lancaster-county/saint-john-neumann-catholic-school-will-open-in-lancaster-this-fall-replacing-saint-anne-catholic/521-49beec85-2f6b-408c-9787-e5d7d11f7c3d | D10: Lancaster | E10: PA | F10: Northeast | G10: Roman Catholic | H10: 43999 | I10: Fall 2020 | K10: https://sjncslancaster.org/ | L10: replacing Saint Anne, which closed this year | M10: 4945 | N10: 4445 Catholic, 5445 non catholic | O10: https://sjncslancaster.org/admissions | P10: 601 E. Delp Road, Lancaster, PA 17601 | Q10: 88277 | R10: 2020
A11: =row()-1 -> 10 | B11: St. Joseph Academy | C11: https://www.stjosephacademy.com/ | D11: Hammonton | E11: NJ | F11: Northeast | G11: Roman Catholic | H11: 44089 | I11: Fall 2020 | J11: 150 | K11: https://www.nj.com/news/2020/09/shuttered-nj-catholic-school-revived-as-private-academy-by-alumni-supporters.html | L11: Opening as independent high school after St. Joseph Catholic High School was closed by diocese. | M11: 11000 | P11: 328 Vine Street Hammonton, New Jersey 08037 | Q11: 119663 | R11: 2020
A12: =row()-1 -> 11 | B12: Acton Academy Lincoln | C12: https://www.1011now.com/2020/09/22/new-school-opening-in-lincoln/ | D12: Lincoln | E12: NE | F12: Midwest | G12: Independent | H12: 44095 | I12: Fall 2020 | J12: 12 | K12: https://www.actonacademylincoln.com/ | M12: 7900 | N12: $500 discount if all paid upfront | O12: https://www.actonacademylincoln.com/faq.html | P12: 8400 Cody Drive ​Lincoln, NE 68512 | Q12: 97776 | R12: 2020
A13: =row()-1 -> 12 | B13: Brompton Community Center | C13: https://fredericksburg.com/news/local/fredericksburg-approves-new-private-school-at-braehead-manor/article_b01bac14-f92a-500e-82c9-3a6fb35861dc.html | D13: Fredericksburg | E13: VA | F13: South | G13: Independent | H13: 44209 | I13: Fall 2021 | K13: https://bromptoncommunityschool.org/ | M13: 12500 | O13: https://bromptoncommunityschool.org/admissions-tuition/ | P13: 123 Lee Dr, Fredericksburg, VA 22401 | Q13: 75291 | R13: 2020
A14: =row()-1 -> 13 | B14: Renaissance School | C14: https://communityimpact.com/dallas-fort-worth/mckinney/impacts/2021/01/26/new-mckinney-private-school-wont-require-algebra-or-calculus/ | D14: McKinney | E14: TX | F14: South | G14: Independent | H14: 44222 | I14: Fall 2022 | K14: https://therschool.org/ | L14: No address yet | M14: 12000 | O14: https://communityimpact.com/dallas-fort-worth/mckinney/impacts/2021/01/26/new-mckinney-private-school-wont-require-algebra-or-calculus/
A15: =row()-1 -> 14 | B15: Bear Town Academy | C15: https://www.witn.com/2021/03/10/new-elementary-school-to-open-in-new-bern/ | D15: New Bern | E15: NC | F15: South | G15: Independent | H15: 44265 | I15: Fall 2021 | K15: https://beartownacademy.com/ | P15: 1909 (B&C) S. Glenburnie Rd. New Bern, NC | Q15: 73582 | R15: 2020
A16: =row()-1 -> 15 | B16: Chesterton Academy of St. Mary's | C16: https://www.thebaynet.com/articles/0321/a-new-catholic-high-school-coming-to-st-marys-county.html | D16: Charlotte Hall | E16: MD | F16: South | G16: Roman Catholic | H16: 44271 | I16: Fall 2021 | J16: 25 | K16: https://www.chestertonstmarys.org/ | M16: 8500 | O16: https://www.chestertonstmarys.org/ | P16: 29530 Charlotte Hall Road, Charlotte Hall, MD 20622 | Q16: 105672 | R16: 2020
A17: =row()-1 -> 16 | B17: Stratford School | C17: https://www.pleasantonweekly.com/news/2021/03/29/new-middle-school-to-open-in-pleasanton-this-fall | D17: Pleasanton | E17: CA | F17: West | H17: 44284 | I17: Fall 2021
A18: =row()-1 -> 17 | B18: Acton Academy Sioux Falls | C18: https://www.keloland.com/news/education/new-acton-academy-private-school-opening-up-in-sioux-falls/ | D18: Sioux Falls | E18: SD | F18: Midwest | G18: Independent | H18: 44291 | I18: Fall 2021 | K18: https://www.actonacademysiouxfalls.org/ | M18: 7700 | N18: $700/month for 11 months | O18: https://www.actonacademysiouxfalls.org/faq | P18: 3628 S Southeastern Ave, Sioux Falls, SD 57103 | Q18: 91665 | R18: 2020
A19: =row()-1 -> 18 | B19: Thales Academy Flowers Plantation | C19: https://www.facebook.com/FlowersPlantationNC/posts/its-official-thales-academy-is-coming-to-flowers-plantation-slated-to-open-july-/4191352904216730/ | D19: Clayton | E19: NC | F19: South | G19: Independent | H19: 44291 | I19: Fall 2022 | K19: https://www.cbs17.com/news/local-news/thales-academy-to-open-1-new-campus-a-year-earlier-than-expected-heres-where/ | L19: Opened one year ahead of schedule | M19: 5400 | N19: Average of K-5 and 6-8 | O19: https://www.thalesacademy.org/admissions/tuition-information | P19: 65 Flowers Parkway Clayton, NC 27527 | Q19: 97566 | R19: 2021
A20: =row()-1 -> 19 | B20: The Linder Academy | C20: https://alexandrialivingmagazine.com/private-school-the-linder-academy-to-open-in-old-town/ | D20: Alexandria | E20: VA | F20: South | G20: Independent | H20: 44292 | I20: Fall 2021 | K20: https://www.thelinderacademy.com/ | M20: 28500 | O20: https://www.thelinderacademy.com/faqs | P20: Old Town location: 607 S Washington St, Alexandria, VA 22314 | Q20: Old Town: $264,867 | R20: 2020
A21: =row()-1 -> 20 | B21: Capstone Christian Academy | C21: https://www.reviewjournal.com/local/education/christian-school-plans-ivy-league-flavor-campus-in-southeast-valley-2326430/ | D21: Las Vegas | E21: NV | F21: West | G21: Christian | H21: 44296 | I21: Fall 2021 | J21: 144 | K21: https://www.capstonechristian.com/ | O21: https://www.capstonechristian.com/requesttuition | P21: 985 E Serene Ave, Las Vegas, NV 89123 | Q21: 72237 | R21: 2020
A22: =row()-1 -> 21 | B22: Thales Academy Greenville | C22: https://greenvillejournal.com/education/thales-academy-to-open-greenville-location-in-hartness-community/ | D22: Greenville | E22: NC | F22: South | G22: Independent | H22: 44314 | I22: Fall 2023 | K22: https://www.thalesacademy.org/ | L22: Applications open Sep. 2022 (No expected enrollment or campus address yet) | M22: 6000 | O22: https://www.thalesacademy.org/
A23: =row()-1 -> 22 | B23: Village School of South Orange | C23: https://www.tapinto.net/towns/soma/sections/education/articles/parents-to-launch-south-orange-maplewood-s-first-independent-elementary-school | D23: South Orange | E23: NJ | F23: Northeast | G23: Independent | H23: 44320 | I23: Fall 2021 | J23: Aiming for 30 the first few years, then to grow to over 100 | K23: https://villageschoolsouthorange.org/ | M23: 19500 | O23: https://villageschoolsouthorange.org/admission | P23: 111 Irvington Ave South Orange, NJ 07079 | Q23: 152395 | R23: 2020
A24: =row()-1 -> 23 | B24: Mother of Mercy Academy | C24: https://motherofmercyacademy.org/ | D24: Pittsburgh | E24: PA | F24: Northeast | G24: Roman Catholic | H24: 44335 | I24: Fall 2021 | K24: https://diopitt.org/news/new-names-announced-for-newly-merged-catholic-schools | P24: 5200 Greenridge Drive Pittsburgh, PA 15236 | Q24: 93081 | R24: 2020
A25: =row()-1 -> 24 | B25: Lazy H Ranch | C25: https://www.hmbreview.com/news/lazy-h-ranch-opens-new-private-school/article_02feb0ec-be38-11eb-9aa0-c32a40f6cf51.html | D25: Half Moon Bay | E25: CA | F25: West | G25: Independent | H25: 44342 | I25: Fall 2021 | J25: 16 | K25: https://www.littlehelementary.com/ | M25: 16000 | N25: $1600 month for 10 months | O25: https://www.littlehelementary.com/schedule-and-tuition | P25: 3100 Miramontes Point Road Half Moon Bay, Ca 94019 | Q25: 156963 | R25: 2020
A26: =row()-1 -> 25 | B26: FaithPrep Indiana | C26: https://in.chalkbeat.org/2021/6/1/22463572/vouchers-virtual-private-schools-indiana | D26: Virtual | E26: IN | F26: Midwest | G26: Christian | H26: 44348 | J26: 500 students expected for the first year, intends to expand to 2,500 over next 5 years | K26: https://in.chalkbeat.org/2021/6/1/22463572/vouchers-virtual-private-schools-indiana; https://www.in.gov/sboe/files/faithprep-indiana-seeking-accreditation-summary.pdf; https://www.faithprep.com/ | M26: 6750 | N26: $6,250 for elementary students/$7,250 for middle and high schoolers | O26: https://in.chalkbeat.org/2021/6/1/22463572/vouchers-virtual-private-schools-indiana
A27: =row()-1 -> 26 | B27: Geo Focus Academy | C27: https://in.chalkbeat.org/2021/6/1/22463572/vouchers-virtual-private-schools-indiana | D27: Virtual | E27: IN | F27: Midwest | G27: Independent | H27: 44348 | J27: Initially can enroll up to 700 students, intends to expand to 1,000 students over time | K27: https://www.in.gov/sboe/files/geo-focus-academy-seeking-accreditation-summary.docx.pdf; https://geoacademies.org/focus-academy/ | M27: 7000 | P27: 3145 N. Meridian St. Indianapolis, IN 46208 | Q27: 25313 | R27: 2020
A28: =row()-1 -> 27 | B28: Lumen Verum Academy | C28: https://www.patriotledger.com/story/news/2021/06/01/first-all-new-catholic-secondary-school-half-century-open/5287812001/ | D28: Boston | E28: MA | F28: Northeast | G28: Roman Catholic | H28: 44348 | I28: Fall 2021 | J28: 25 enrolled initially | K28: https://lumenverumacademy.org/ | M28: 14750 | P28: 66 Brooks Dr, Braintree, MA 02184 | Q28: 123020 | R28: 2020
A29: =row()-1 -> 28 | B29: Jean Charles Academy | C29: https://lynnjournal.com/2021/06/02/jean-charles-academy-an-accessible-dual-language-private-school-to-open-in-lynn/ | D29: Lynn | E29: MA | F29: Northeast | G29: Independent | H29: 44349 | I29: Fall 2021 | J29: Up to 40 first year, continuing to expand yearly until can offer a full K-12 program | K29: https://www.jeancharlesacademy.org/faqs | N29: JCA tuition is based on a shared economy structure. Families can choose to pay all of the tuition or contribute half of the cost via cash and the other half by sharing their time and/or talent with the school." | O29: https://www.jeancharlesacademy.org/faqs | P29: 498 Essex St Lynn, MA 01902 | Q29: 41723 | R29: 2020
A30: =row()-1 -> 29 | B30: Northeast Christian High School | C30: https://ktvo.com/news/local/new-christian-high-school-in-kirksville-hopes-for-big-changes-in-its-future | D30: Kirksville | E30: MO | F30: Midwest | G30: Christian | H30: 44354 | I30: Fall 2021 | N30: No tuition information available yet | O30: https://www.northeastchs.com/admissions-standards/tuition-fees | P30: 1702 N Elson St, Kirksville, MO 63501 | Q30: 41083 | R30: 2020
A31: =row()-1 -> 30 | B31: Yellowhab Norfolk | C31: https://www.pilotonline.com/news/education/vp-nw-pharrell-williams-yellowhab-school-20210607-hhyzrj6cmjg7pae4s77tqdl3ye-story.html | D31: Norfolk | E31: VA | F31: South | G31: Independent | H31: 44354 | I31: Fall 2021 | L31: School started by Pharell Williams' nonprofit; Cannot find address? | M31: 0 | N31: Tuition-free for at least the first year | O31: https://teamyellow.org/yellowhab
A32: =row()-1 -> 31 | B32: Evergreen Christian High School | C32: https://loudounnow.com/2021/06/10/evergreen-christian-high-school-eyes-fall-opening/ | D32: Leesburg | E32: VA | F32: South | G32: Christian | H32: 44357 | I32: Fall 2021 | M32: 17000 | P32: 21336 Evergreen Mills Rd, Leesburg, VA 20175 | Q32: 209779 | R32: 2020
A33: =row()-1 -> 32 | B33: Cedar School | C33: https://www.greenwichtime.com/local/article/Cedar-School-to-join-educational-landscape-in-16241434.php | D33: Greenwich | E33: CT | F33: Northeast | G33: Special needs | H33: 44358 | I33: Fall 2021 | J33: 25 students first year, maxiumum enrollment of 100 for following years | K33: https://www.thecedarschool.org/ | L33: School is for dyslexic/language-based learning difference students | M33: 47000 | O33: https://www.thecedarschool.org/admissions/tuition-and-fees.cfm | P33: 200 Pemberwick Rd Greenwich, CT 06831 | Q33: 122440 | R33: 2020
A34: =row()-1 -> 33 | B34: Shawnee Nazarene Academy | C34: https://shawneemissionpost.com/2021/06/28/shawnee-nazarene-academy-126016/ | D34: Shawnee | E34: KS | F34: Midwest | G34: Christian | H34: 44358 | I34: Fall 2021 | J34: Capacity is 50 students for now | K34: https://shawneenaz.org/shawnee-naz-academy | M34: 6630 | O34: https://umuhh8.nucleus.church/download/a18e823af076e1dd6516f4e26b3c3896298e3a48.pdf | P34: 5539 Quivira Rd Shawnee, KS 66203 | Q34: 58103 | R34: 2020
A35: =row()-1 -> 34 | B35: Arbor Academy | C35: https://communityimpact.com/austin/georgetown/education/2021/06/15/project-based-private-school-in-georgetown-now-enrolling-for-august-opening/ | D35: Georgetown | E35: TX | F35: South | G35: Independent | H35: 44362 | I35: Fall 2021 | K35: https://www.arboracademy.org/ | M35: 8700 | O35: https://www.arboracademy.org/enroll | P35: 412 E 19th St Georgetown, TX 78626 | Q35: 84688 | R35: 2020
A36: =row()-1 -> 35 | B36: Challenge Prepatory Academy | C36: https://www.wjbf.com/cyber/cyber-education-prep-school-opening-in-harrisburg-this-fall/ | D36: Augusta | E36: GA | F36: South | G36: Independent | H36: 44369 | I36: Fall 2021 | K36: https://www.challengeprepacademy.org/ | M36: 7500 | O36: https://www.challengeprepacademy.org/tuition | P36: 1948 Ellis St Augusta, GA 30904 | Q36: 27447 | R36: 2020
A37: =row()-1 -> 36 | B37: Catskill Wheelhouse Community | C37: https://www.hudsonvalley360.com/news/greenecounty/private-elementary-school-to-open-in-fall/article_8a0c7d79-6eec-500f-a668-fd3a543abe76.html | D37: Cairo | E37: NY | F37: Northeast | G37: Independent | H37: 44370 | I37: Fall 2021 | J37: 36 | K37: http://www.catskillwheelhouse.org/ | M37: 9000 | N37: Sliding scale based on need; ranges from 0 to 18,000 | O37: http://www.catskillwheelhouse.org/forest-school; http://www.catskillwheelhouse.org/community-school | P37: 665 Main St Cairo, NY 12413 | Q37: 70264 | R37: 2020
A38: =row()-1 -> 37 | B38: St. Catherine of Siena Academy | C38: https://www.wwnytv.com/2021/06/23/canton-sees-return-catholic-elementary-education/ | D38: Canton | E38: NY | F38: Northeast | G38: Roman Catholic | H38: 44370 | I38: Fall 2021 | K38: https://www.sienaacademy.org/ | M38: 4000 | O38: https://www.sienaacademy.org/faqs | P38: 2 Powers St, Canton, NY 13617 | Q38: 83093 | R38: 2020
A39: =row()-1 -> 38 | B39: Prairie Song Academy | C39: https://www.kirksvilledailyexpress.com/story/news/2021/07/07/prairie-song-academy-montessori-based-school-opening-kirksville-year/7842192002/ | D39: Kirksville | E39: MO | F39: Midwest | G39: Independent | H39: 44384 | I39: Fall 2021 | K39: https://prairiesongacademy.com/ | M39: 1406 | N39: Sliding tuition scale, average of 703.13/semester, two semesters in a year | O39: https://prairiesongacademy.com/enrollment/tuition/ | P39: 1301 E PATTERSON STREET KIRKSVILLE MO 63501 | Q39: 68446 | R39: 2020
A40: =row()-1 -> 39 | B40: Scenic City Montessori | C40: https://www.timesfreepress.com/news/local/story/2021/jul/25/two-new-montessori-schools-open-chattanoogare/550975/ | D40: Chattanooga | E40: TN | F40: South | G40: Independent | H40: 44402 | I40: Fall 2021 | J40: <30 | K40: https://www.themontessorischool.net/ | M40: 9125 | N40: 8801 K-5, 9449 6-8 | O40: https://www.themontessorischool.net/tuition-terms/ | P40: 6310 Dayton Blvd Hixson, TN 37343 | Q40: 78190 | R40: 2020
A41: =row()-1 -> 40 | B41: Polaris Village Academy | C41: https://www.stardem.com/news/tuition-free-private-school-opening-in-easton/article_c7d28f7f-b185-53e1-a416-fa3b051519b8.html | D41: Easton | E41: MD | F41: South | G41: Independent | H41: 44404 | I41: Fall 2021 | K41: https://polarisvillageacademy.org/ | M41: 0 | N41: Tuition free | O41: https://polarisvillageacademy.org/ | P41: 31 Jowite St, Easton, MD 21601 | Q41: 47757 | R41: 2020
A42: =row()-1 -> 41 | B42: Mother Mary Lange Catholic School | C42: https://www.ncregister.com/cna/new-catholic-school-in-baltimore-holds-blessing-ceremony | D42: Baltimore | E42: MD | F42: South | G42: Roman Catholic | H42: 44415 | I42: Fall 2021 | J42: >400 | K42: https://mmlcs.org/ | M42: 6000 | O42: https://mmlcs.org/admissions/tuition | P42: 200 N Martin Luther King Jr Blvd, Baltimore, MD 21201 | Q42: 18793 | R42: 2020
A43: =row()-1 -> 42 | B43: New Mexico Trinity Prep | C43: https://www.santafenewmexican.com/news/education/new-private-online-high-school-to-be-offered-in-new-mexico/article_31593ba2-f09b-11eb-8778-f700e9e28bd4.html | E43: NM | F43: West | G43: Independent | H43: 44416 | I43: Fall 2021 | K43: https://www.nmtrinityprep.school/index.php | L43: Online school | M43: 1990 | N43: 199/month for min. 10 months | O43: https://www.nmtrinityprep.school/index.php/nmtp-enroll-now
A44: =row()-1 -> 43 | B44: Star Academy | C44: https://theswellesleyreport.com/2021/08/wellesley-business-buzz-star-academy-eyes-fall-opening-dont-let-the-scaffolding-scare-ya-beer-wine-delivered/ | D44: Wellesley | E44: MA | F44: Northeast | G44: Independent | H44: 44419 | I44: Fall 2021 | K44: https://staracademyboston.com/ | M44: 19800 | O44: https://staracademyboston.com/general-info | P44: 10 ATWOOD STREET WELLESLEY, MA 02482 | Q44: 225397 | R44: 2020
A45: =row()-1 -> 44 | B45: Chesterton Academy of Our Lady of Walsingham | C45: https://olwclassical.org/ | D45: Colorado Springs | E45: CO | F45: West | G45: Roman Catholic | H45: 44428 | I45: Fall 2021 | J45: 26 | K45: https://olwclassical.org/ | M45: 7400 | O45: https://olwclassical.org/admissions/#tuition-and-aid | P45: 8755 Scarborough Dr. Colorado Springs, CO 80920 | Q45: 152101 | R45: 2020
A46: =row()-1 -> 45 | B46: Acton Midwest | C46: https://www.news8000.com/ribbon-cutting-ceremony-marks-opening-of-acton-academy/ | D46: Onalaska | E46: WI | F46: Midwest | G46: Independent | H46: 44433 | I46: Fall 2021 | J46: 17-20 | K46: https://www.actonmidwest.org/home | M46: 7500 | O46: https://www.actonmidwest.org/about-acton-midwest/faq | P46: 923 12th Avenue South, Onalaska, WI 54650 | Q46: 64236 | R46: 2020
A47: =row()-1 -> 46 | B47: BASIS Independent Manhattan | C47: https://www.wfmz.com/news/pr_newswire/pr_newswire_business/spring-education-group-celebrates-new-school-openings-in-2021/article_7f3caae8-66c5-5d7b-b9a7-555f6e308f58.html | D47: New York City | E47: NY | F47: Northeast | G47: Independent | H47: 44438 | I47: Fall 2021 | K47: https://manhattan.basisindependent.com/ | M47: 38833 | N47: K-10 average | O47: https://manhattan.basisindependent.com/admissions/tuition-fees/ | P47: 795 Columbus Ave, New York, NY 10025 | Q47: 181833 | R47: 2020
A48: =row()-1 -> 47 | B48: Stratford Almaden Preschool | C48: https://www.wfmz.com/news/pr_newswire/pr_newswire_business/spring-education-group-celebrates-new-school-openings-in-2021/article_7f3caae8-66c5-5d7b-b9a7-555f6e308f58.html | D48: San Jose | E48: CA | F48: West | G48: Independent | H48: 44438 | I48: Fall 2021 | K48: https://www.stratfordschools.com/schools/northern-california/south-bay/san-jose-almaden/ | M48: 19542 | N48: 10 month price, 12 month: $23,272 | O48: https://www.stratfordschools.com/schools/northern-california/south-bay/san-jose-almaden/admissions/tuition/ | P48: 5200 Dent Ave San Jose, CA 95118 | Q48: 115810 | R48: 2020
A49: =row()-1 -> 48 | B49: Stratford Milpitas Corning Elementary School | C49: https://www.wfmz.com/news/pr_newswire/pr_newswire_business/spring-education-group-celebrates-new-school-openings-in-2021/article_7f3caae8-66c5-5d7b-b9a7-555f6e308f58.html | D49: Milpitas | E49: CA | F49: West | G49: Independent | H49: 44438 | I49: Fall 2021 | K49: https://www.stratfordschools.com/schools/northern-california/south-bay/milpitas-corning/ | M49: 22634 | N49: K-8 average | O49: https://www.stratfordschools.com/schools/northern-california/south-bay/milpitas-corning/admissions/tuition/ | P49: 25 Corning Ave, Milpitas, CA 95035 | Q49: 143854 | R49: 2020
A50: =row()-1 -> 49 | B50: Stratford Online Academy | C50: https://www.wfmz.com/news/pr_newswire/pr_newswire_business/spring-education-group-celebrates-new-school-openings-in-2021/article_7f3caae8-66c5-5d7b-b9a7-555f6e308f58.html | E50: CA | F50: West | G50: Independent | H50: 44438 | I50: Fall 2021 | K50: https://www.stratfordschools.com/stratford-blog/announcing-the-second-year-of-stratford-schools-online-academy/ | L50: Online school | M50: 20878 | N50: K-5 average | O50: https://www.stratfordschools.com/our-programs/online-academy/
A51: =row()-1 -> 50 | B51: Stratford Pleasanton Middle School | C51: https://www.wfmz.com/news/pr_newswire/pr_newswire_business/spring-education-group-celebrates-new-school-openings-in-2021/article_7f3caae8-66c5-5d7b-b9a7-555f6e308f58.html | D51: Pleasanton | E51: CA | F51: West | G51: Independent | H51: 44438 | I51: Fall 2021 | K51: https://www.stratfordschools.com/schools/northern-california/east-bay/pleasanton-middle-school/ | M51: 25501 | O51: https://www.stratfordschools.com/schools/northern-california/east-bay/pleasanton-middle-school/admissions/tuition/ | P51: 3800 Stoneridge Drive, Pleasanton, CA 94588 | Q51: 235849 | R51: 2020
A52: =row()-1 -> 51 | B52: BridgeWay Prepatory Christian School | C52: https://www.dailyadvance.com/news/local/christian-private-school-set-to-open-in-moyock/article_8a5176ce-c708-578e-bd8a-e39fcca2252f.html | D52: Moyock | E52: NC | F52: South | G52: Christian | H52: 44440 | I52: Fall 2021 | K52: https://www.bwpcskids.org/ | M52: 6000 | O52: https://www.bwpcskids.org/admissions | P52: 243 Caratoke Hwy Moyock, NC 27958 | Q52: 92968 | R52: 2020
A53: =row()-1 -> 52 | B53: Carlsbad Prep Academy | C53: https://www.currentargus.com/story/news/education/2021/09/08/faith-based-private-school-opening-carlsbad/5695769001/ | D53: Carlsbad | E53: NM | F53: West | G53: Christian | H53: 44447 | I53: Fall 2022 | K53: https://www.carlsbadprepacademy.com/ | M53: 4500 | N53: $500/month x 9 months | O53: https://www.carlsbadprepacademy.com/ | P53: 805 Walter St Carlsbad, NM 88220 | Q53: 79978 | R53: 2020
A54: =row()-1 -> 53 | B54: BASIS Bellevue | C54: https://www.bellevuereporter.com/news/bellevue-to-have-new-private-school-by-2022-school-year/ | D54: Bellevue | E54: WA | F54: West | G54: Independent | H54: 44449 | I54: Fall 2022 | J54: 100 then 450 | K54: https://bellevue.basisindependent.com/ | M54: 27150 | N54: 2-7 average | O54: https://bellevue.basisindependent.com/admissions/tuition-fees/ | P54: 15749 NE 4th St. Bellevue, WA 98008 | Q54: 76308 | R54: 2020
A55: =row()-1 -> 54 | B55: BASIS Brooklyn | C55: https://patch.com/new-york/brooklyn/classifieds/announcements/258982/basis-independent-schools-to-open-brooklyn-lower-school-campus | D55: Brooklyn | E55: NY | F55: Northeast | G55: Independent | H55: 44456 | I55: Fall 2021 | K55: https://blog.basisindependent.com/bklyn/lowerschoolcampusdesign | M55: 36200 | O55: https://brooklyn.basisindependent.com/admissions/tuition-fees/ | P55: 405 Gold St, Brooklyn, NY 11201 | Q55: 109342 | R55: 2020
A56: =row()-1 -> 55 | B56: Kanye West Donda Academy | C56: https://www.simivalleyacorn.com/articles/kanye-west-reportedly-looking-to-open-school-between-simi-moorpark/ | D56: Simi Valley | E56: CA | F56: West | G56: Independent | H56: 44460 | J56: 60 | K56: https://donda.world/ | M56: 0 | N56: No Tuition | P56: 1625 Tierra Rejada Rd, Simi Valley, CA 93065 | Q56: 154025 | R56: 2020
A57: =row()-1 -> 56 | B57: BASIS Sunnyvale Lower School Campus | C57: https://www.prnewswire.com/news-releases/top-private-school-basis-independent-silicon-valley-to-open-new-lower-campus-fall-2022-301386394.html | D57: Sunnyvale | E57: CA | F57: West | G57: Independent | H57: 44467 | I57: Fall 2022 | P57: 1500 Partridge Ave Sunnyvale, CA 94087 | Q57: 190589 | R57: 2020
A58: =row()-1 -> 57 | B58: Kaleidoscope Heights Academy | C58: https://www.wlbt.com/2021/10/01/kaleidoscope-heights-opens-fill-void-special-needs-students/ | D58: Jackson | E58: MS | F58: South | G58: Independent | H58: 44470 | I58: Fall 2021 | J58: 78 | K58: https://www.kaleidoscopeheights.org/ | N58: sliding scale | O58: https://www.kaleidoscopeheights.org/tuition-and-fees | P58: 411 Briarwood Drive Building 400 Jackson, MS 39206 | Q58: 34832 | R58: 2020
A59: =row()-1 -> 58 | B59: Saint John Paul the Great | C59: https://denvercatholic.org/st-john-paul-the-great-introducing-denvers-newest-catholic-classical-high-school-open-house-oct-30/ | D59: Denver | E59: CO | F59: West | G59: Roman Catholic | H59: 44484 | I59: Fall 2022 | J59: 440 capacity | K59: https://www.jpthegreatdenver.org/ | O59: https://www.jpthegreatdenver.org/soon | P59: 2256 S Logan St. Denver, CO 80210 | Q59: 111700 | R59: 2020
A60: =row()-1 -> 59 | B60: Trilogy STEM Academy | C60: https://www.hometownsource.com/press_and_news/news/local/trilogy-stem-academy-roger-s-first-private-high-school/article_0a5436b6-3762-11ec-9b10-5738d2db8a1d.html | D60: Rogers | E60: MN | F60: Midwest | G60: Independent | H60: 44497 | I60: Fall 2022 | J60: 40 to start (20 for 2 9th grade classes) | K60: https://www.trilogystemacademy.org/ | M60: 14875 | O60: https://www.trilogystemacademy.org/affordability | P60: 14020 Northdale Boulevard Rogers, MN 55374 | Q60: 133749 | R60: 2020
A61: =row()-1 -> 60 | B61: Chesterton Academy of St. George | C61: https://www.mlive.com/news/jackson/2021/11/new-private-high-school-in-jackson-finds-home-in-wing-of-adult-care-facility.html | D61: Jackson | E61: MS | F61: South | G61: Roman Catholic | H61: 44502 | I61: Fall 2022 | K61: https://www.castgeorge.com/ | M61: 6200 | O61: https://www.castgeorge.com/admissions/#tuition-and-aid | P61: 1000 E Porter St Jackson, MS 39201 | Q61: 36001 | R61: 2020
A62: =row()-1 -> 61 | B62: Ascend Academy | C62: https://www.spokanepublicradio.org/post/new-school-serve-autistic-students-spokane#stream/0 | D62: Spokane | E62: WA | F62: West | G62: Special needs | H62: 44529 | I62: Spring 2022 | J62: 20 | K62: http://ascendacademy.org/ | M62: 0 | N62: Free tuition, funded by donations as a nonprofit | O62: http://ascendacademy.org/free-private-school/ | P62: 1117 E Westview Ct. Spokane WA 99218 | Q62: 56536 | R62: 2020
A63: =row()-1 -> 62 | B63: Chesterton Academy of St. Patrick | C63: https://www.kvmr.org/kvmr-event/chesterton-academy-information-night/ | D63: Grass Valley | E63: CA | F63: West | G63: Roman Catholic | H63: 44536 | I63: Fall 2022 | K63: https://caofstpatrick.org/ | P63: 423 Dalton Street, Grass Valley, CA 95945 | Q63: 58738 | R63: 2020
A64: =row()-1 -> 63 | B64: Cristo Rey | C64: https://communitynewspapers.com/biscayne-bay/cristo-rey-miami-high-school-to-open-its-doors-july-2022/ | D64: North Miami | E64: FL | F64: South | G64: Roman Catholic | H64: 44536 | I64: Summer 2022 | J64: 100 | K64: https://www.cristoreymiami.org/about/fast-facts | L64: Hope to grow to 400 by 2025 | M64: 625 | N64: "average annual of $500-$750 per year) work study + step up scholarships factored in | O64: https://www.cristoreymiami.org/about/fast-facts | P64: 125 NE 119th Street North Miami, FL 33161 | Q64: 63971 | R64: 2021
A65: =row()-1 -> 64 | B65: Bright Start Learning Center | C65: https://www.alxnow.com/2021/12/09/new-incredibly-small-private-school-coming-to-cameron-station/ | D65: Alexandria | E65: VA | F65: South | G65: Independent | H65: 44539 | J65: 15 | K65: https://www.brightstartva.com/ | L65: The child care program will be separate from classes for 3-12 year olds | P65: 4917 Brenman Park Dr, Alexandria, VA 22304 | Q65: 203523 | R65: 2020
A66: =row()-1 -> 65 | B66: Aegis Institute | C66: https://www.gainesville.com/story/news/education/2021/12/29/married-couple-seeks-start-new-private-school-modernize-curriculum/9037024002/ | D66: Gainesville | E66: FL | F66: South | G66: Independent | H66: 44559 | I66: Fall 2022 | J66: 10 | K66: https://www.theaegisinstitute.com/ | P66: 3809 NW 40th St., Gainesville, FL 32606 | Q66: 102270 | R66: 2020
A67: =row()-1 -> 66 | B67: Righteous Warrior Academy | C67: https://www.polkio.com/news/dallas-couple-takes-leap-of-faith-opening-new-christian-private-school/article_b94351d0-6e7f-11ec-82a6-b750e0924f8f.html | D67: Dallas | E67: OR | F67: West | G67: Christian | H67: 44566 | I67: Spring 2022 | K67: https://righteouswarrioracademy.com/ | L67: Want class sizes of 10-20, unclear how many classes | M67: 6000 | N67: 500 monthly x 12 months | O67: https://righteouswarrioracademy.com/pre-register%2Ftuition | P67: 289 East Ellendale Avenue Suite 403, Dallas, OR 97338 | Q67: 61163 | R67: 2021
A68: =row()-1 -> 67 | B68: Kingdom United Education | C68: https://dailyjournalonline.com/news/local/education/plans-afoot-to-open-new-school/article_c6693e85-7b46-5adf-b1e0-1a86436a4300.html | D68: Bonne Terre | E68: MO | F68: Midwest | G68: Independent | H68: 44568 | I68: Fall 2022 | K68: https://www.kingdomunitededu.com/
A69: =row()-1 -> 68 | B69: Dream Center Academy | C69: https://www.wlky.com/article/west-louisville-christian-school-opens-looks-to-expand/38793624 | D69: Louisville | E69: KY | F69: Midwest | G69: Christian | H69: 44578 | I69: 44562 | J69: 11 | K69: https://www.wlky.com/article/west-louisville-christian-school-opens-looks-to-expand/38793624 | L69: Hoping to expand | M69: 6000 | N69: Average of donation amounts that cover high school/elementary tuition | O69: https://ndky.org/dreamcenteracademychristianschool/ | P69: 1190 S 40th St, Louisville, KY 40211 | Q69: 39773 | R69: 2021
A70: =row()-1 -> 69 | B70: Capstone Classical Academy | C70: https://www.inforum.com/news/fargo/new-private-school-set-to-open-in-fargo-this-fall | D70: Fargo | E70: ND | F70: Midwest | G70: Christian | H70: 44581 | I70: Fall 2022 | J70: 560 | K70: https://capstoneclassical.com/ | L70: Hoping to reach 560, has 17 applications first week | M70: 8950 | O70: https://capstoneclassical.com/tuition/ | P70: 3910 25th St. S, Fargo, ND 58104 | Q70: 167353 | R70: 2021
A71: =row()-1 -> 70 | B71: Cornerstone Christian Academy | C71: https://loudounnow.com/2022/02/07/cornerstone-chapel-plans-school-at-middleburg-academy-site/ | D71: Middleburg | E71: VA | F71: South | G71: Christian | H71: 44599 | I71: Fall 2023 | K71: https://cornerstonechapel.net/cca | L71: They purchased the campus that used to be Middleburg Academy (closed June 2020) | N71: Still finalizing numbers | O71: https://cornerstonechapel.net/cca | P71: 35321 Notre Dame Ln, Middleburg, VA 20117 | Q71: 170867 | R71: 2021
A72: =row()-1 -> 71 | B72: Veritas Collegiate Academy | C72: https://www.arlnow.com/2022/02/09/new-private-school-set-to-open-this-fall-in-aurora-highlands-church/ | D72: Arlington | E72: VA | F72: South | G72: Christian | H72: 44601 | I72: Fall 2022 | K72: https://www.veritasacademydc.com/crystal-city | P72: 935 23rd St S. Arlington, VA 22202 | Q72: 206557 | R72: 2021
A73: =row()-1 -> 72 | B73: Santa Fe Christian | C73: https://www.santafenewmexican.com/news/local_news/residents-concerned-about-traffic-from-planned-private-school-on-old-pecos-trail/article_fe228638-8859-11ec-84d5-831bb7ee0b73.html | D73: Santa Fe | E73: NM | F73: West | G73: Christian | H73: 44601 | I73: Fall 2022 | J73: 122 | K73: https://www.santafenewmexican.com/news/local_news/residents-concerned-about-traffic-from-planned-private-school-on-old-pecos-trail/article_fe228638-8859-11ec-84d5-831bb7ee0b73.html | O73: https://santafechristian.org/ | P73: 3201 Zafarano Drive, Suite C, #263 Santa Fe, NM 87507 | Q73: 35909 | R73: 2021
A74: =row()-1 -> 73 | B74: Discovery Learners' Academy | C74: https://www.chattanoogan.com/2022/2/10/443206/Discovery-Learners-Academy-Offers.aspx | D74: Chattanooga | E74: TN | F74: South | G74: Independent | H74: 44602 | I74: Fall 2022 | K74: https://discoverylearnersacademy.org/ | M74: 6000 | O74: https://discoverylearnersacademy.org/about | P74: 3933 S Mission Oaks Dr Chattanooga, TN 37412 | Q74: 62316 | R74: 2021
A75: =row()-1 -> 74 | B75: Trinity Lutheran Classical High School | C75: https://www.jsonline.com/story/communities/southwest/news/west-allis/2022/02/22/trinity-lutheran-church-west-allis-plans-open-new-high-school/6879919001/ | D75: West Allis | E75: WI | F75: Midwest | G75: Lutheran | H75: 44614 | I75: Fall 2023 | K75: https://www.trinitywa.org/classical-school.html | P75: 2500 S 68th St, Milwaukee, WI 53219 | Q75: 74019 | R75: 2021
A76: =row()-1 -> 75 | B76: E.A. Young Academy | C76: https://communityimpact.com/dallas-fort-worth/keller-roanoke-northeast-fort-worth/education/2022/02/22/k-12-gifted-talented-and-high-ability-private-school-planning-to-open-in-roanoke/ | D76: Roanoke | E76: TX | F76: South | G76: Independent | H76: 44614 | L76: https://www.eayoungacademy.com/ (website for a different branch) | P76: 608 Henrietta Creek Rd. Roanoke, TX 76262 | Q76: 97597 | R76: 2021
A77: =row()-1 -> 76 | B77: Limestone School | C77: https://lawrencekstimes.com/2022/03/03/limestone-school-reimagining-edu/ | D77: Lawrence | E77: KS | F77: Midwest | G77: Independent | H77: 44623 | I77: Fall 2022 | J77: 36 | K77: https://limestoneschool.com/ | L77: K max 12, 1st and 2nd mixed with a 24 max | P77: 1915 Rhode Island St, Lawrence KS 66046 | Q77: 77402 | R77: 2021
A78: =row()-1 -> 77 | B78: Fusion Academy Palm Beach Gardens | C78: https://www.prnewswire.com/news-releases/fusion-academy-opening-four-new-schools-this-spring-301502154.html | D78: Palm Beach Gardens | E78: FL | F78: South | G78: Independent | H78: 44634 | I78: Spring 2022 | K78: https://www.fusionacademy.com/campuses/palm-beach-gardens/ | M78: 49920 | N78: 4160 average per middle school and high school class, 6 classes per term, two terms in a year | O78: https://www.fusionacademy.com/campuses/palm-beach-gardens/tuition/ | P78: 11300 Legacy Avenue, Palm Beach Gardens, FL 33410 | Q78: 94018 | R78: 2021
A79: =row()-1 -> 78 | B79: Fusion Academy Santa Barbara | C79: https://www.prnewswire.com/news-releases/fusion-academy-opening-four-new-schools-this-spring-301502154.html | D79: Santa Barbara | E79: CA | F79: West | G79: Independent | H79: 44634 | I79: Spring 2022 | K79: https://www.fusionacademy.com/campuses/santa-barbara/ | M79: 47700 | N79: 3975 average per middle school and high school class, 6 classes per semester, two semesters in a year | O79: https://www.fusionacademy.com/campuses/santa-barbara/tuition/ | P79: 510 State Street, Santa Barbara, CA 93101 | Q79: 50393 | R79: 2021
A80: =row()-1 -> 79 | B80: Fusion Academy Franklin | C80: https://www.prnewswire.com/news-releases/fusion-academy-opening-four-new-schools-this-spring-301502154.html | D80: Franklin | E80: TN | F80: South | G80: Independent | H80: 44634 | I80: Summer 2022 | K80: https://www.fusionacademy.com/campuses/franklin/ | M80: 53100 | N80: 4425 average per middle school and high school class, 6 classes per term, two terms in a year | O80: https://www.fusionacademy.com/campuses/franklin/tuition/ | P80: 2550 Meridian Boulevard, Franklin, TN 37067 | Q80: 170906 | R80: 2021
A81: =row()-1 -> 80 | B81: Fusion Academy Boulder County | C81: https://www.prnewswire.com/news-releases/fusion-academy-opening-four-new-schools-this-spring-301502154.html | D81: Boulder | E81: CO | F81: West | G81: Independent | H81: 44634 | I81: Summer 2022 | K81: https://www.fusionacademy.com/campuses/boulder-county/ | M81: 48756 | N81: 4063 average per middle school and high school class, 6 classes per term, two terms in a year | O81: https://www.fusionacademy.com/campuses/boulder-county/tuition/ | P81: 168 Centennial Parkway, Louisville, CO 80027 | Q81: 168394 | R81: 2021
A82: =row()-1 -> 81 | B82: Grace Christian Academy | C82: https://swvatoday.com/community/article_25d7c574-a48b-11ec-ac56-c3358c5cd3c9.html | D82: Atkins | E82: VA | F82: South | G82: Christian | H82: 44635 | I82: Fall 2022 | J82: 12 | K82: https://swvatoday.com/community/article_25d7c574-a48b-11ec-ac56-c3358c5cd3c9.html | P82: 442 Freedom Tabernacle Ln, Atkins, VA 24311 | Q82: 59571 | R82: 2021
A83: =row()-1 -> 82 | B83: Marian University Preparatory School | C83: https://www.businesswire.com/news/home/20220322005224/en/Marian-University-Launches-New-K-12-Private-School-Offers-Flexible-Faith-Based-Learning-Across-Indiana | D83: Indianapolis | E83: IN | F83: Midwest | G83: Roman Catholic | H83: 44642 | I83: Fall 2022 | K83: https://muprep.k12.com/ | M83: 7500 | O83: https://muprep.k12.com/resources/general-faqs.html | P83: 2916 30th Street Indianapolis, IN 46222 | Q83: 49542 | R83: 2021
A84: =row()-1 -> 83 | B84: Chrysostom Academy | C84: https://www.wfmz.com/news/area/lehighvalley/st-john-chrysostom-orthodox-school-to-open-this-fall-at-monocacy-manor-in-bethlehem/article_1d9254d8-aac6-11ec-a176-d3b54451e79d.html | D84: Bethlehem | E84: PA | F84: Northeast | G84: Orthodox | H84: 44643 | I84: Fall 2022 | L84: The new school will offer first through ninth grade education when it opens this fall but says in its statement that its plan it to have classes through 12th grade. | M84: 8250 | N84: average. grades 1-4=$6,250; 5-8=$7,500; 9-12=$11,000 | O84: https://chrysostomacademy.org/admission/tuition-fee-schedule/ | P84: 395 Bridle Path Rd, Bethlehem, PA 18017 | Q84: 111642 | R84: 2022
A85: =row()-1 -> 84 | B85: Basilica High School of St. Mary Star of the Sea | C85: https://basilicaschoolkeywest.com/2022/03/the-basilica-school-to-expand-to-high-school/ | D85: Key West | E85: FL | F85: South | G85: Roman Catholic | H85: 44646 | I85: Fall 2023 | J85: 180 | K85: https://basilicaschoolkeywest.com/2022/03/the-basilica-school-to-expand-to-high-school/ | L85: 180 number in 3 years | P85: 700 Truman Avenue Key West, Florida 33040 | Q85: 64154 | R85: 2021
A86: =row()-1 -> 85 | B86: Individualized Intellect Institute | C86: https://www.localmemphis.com/article/news/education/memphis-tennessee-academy-health-sciences-i3-charter-school/522-2dd90604-b503-4b77-ba6b-eacbadb6514a | D86: Memphis | E86: TN | F86: South | G86: Independent | H86: 44659 | I86: Fall 2022 | J86: 350 | K86: https://www.localmemphis.com/article/news/education/memphis-tennessee-academy-health-sciences-i3-charter-school/522-2dd90604-b503-4b77-ba6b-eacbadb6514a | L86: 350 in person, 300 online | M86: 0 | N86: Tuition Free | O86: https://www.i3memphis.com/enrollment | P86: 1299 E. McLemore Ave Memphis, TN 38106 | Q86: 28433 | R86: 2021
A87: =row()-1 -> 86 | B87: Natural Connections Academy | C87: https://cdapress.com/news/2022/apr/15/new-private-school-opens-enrollment/ | D87: Worley | E87: ID | F87: West | G87: Independent | H87: 44666 | I87: Fall 2022 | M87: 5000 | O87: https://www.naturalconnectionsacademy.net/ | P87: 5827 W Conkling Rd, Worley, ID 83876 | Q87: 63371 | R87: 2021
A88: =row()-1 -> 87 | B88: New Montgomery Prepatory Academy | C88: https://www.montgomery-herald.com/news/august-opening-eyed-for-montgomery-preparatory-academy/article_9ebd043e-be78-11ec-ace9-0f89269a0e36.html | D88: Montgomery | E88: WV | F88: South | G88: Independent | H88: 44668 | I88: Fall 2022 | J88: 50 | K88: https://www.montgomery-herald.com/news/august-opening-eyed-for-montgomery-preparatory-academy/article_9ebd043e-be78-11ec-ace9-0f89269a0e36.html | L88: hoping to reach 150 | M88: 4298 | O88: https://mlmpipa.org/montgomerypa/ | P88: (address unknown)
A89: =row()-1 -> 88 | B89: Lufkin Christian Academy | C89: https://kfox95.com/new-christian-private-school-coming-this-fall-in-lufkin-texas/ | D89: Lufkin | E89: Texas | F89: South | G89: Christian | H89: 44670 | I89: Fall 2022 | J89: 50 | K89: https://www.kltv.com/2022/05/04/lufkin-christian-academy-set-open-fall-2022/ | L89: 50 for first year, plan to grow | M89: 4000 | O89: https://www.facebook.com/lcalufkintexas/photos/a.106878485141515/156001843562512/ | P89: 5101 S Chestnut St Lufkin, TX 75901 | Q89: 79410 | R89: 2021
A90: =row()-1 -> 89 | B90: Freedom Prepatory | C90: https://www.ksn.com/news/local/independent-christian-school-opening-in-august/ | D90: Wichita | E90: Kansas | F90: Midwest | G90: Christian | H90: 44671 | I90: Fall 2022 | J90: 150 | K90: https://www.ksn.com/news/local/independent-christian-school-opening-in-august/ | L90: 60 enrolled, expect 100-150 for future | N90: "Enrollment fees and tuition will be set once enrollment is filled." | O90: https://freedomprep.wixsite.com/website/admissions | P90: 3724 N. Pepper Ridge St Wichita, KS 67205 | Q90: 113343 | R90: 2021
A91: =row()-1 -> 90 | B91: Louisville Urban Classical Academy | C91: https://www.whas11.com/video/news/local/new-private-school-opens-in-west-louisville/417-818f1727-9eee-4576-9188-8d81f76db71b | D91: Louisville | E91: KY | F91: South | G91: Christian | H91: 44697 | I91: Fall 2022 | M91: 0 | N91: tuition free | O91: https://www.lucaky.org/about | P91: 1606 W. Chestnut Louisville, KY 40203 | Q91: 37116 | R91: 2021
A92: =row()-1 -> 91 | B92: Coastside Leadership Academy | C92: https://www.hmbreview.com/news/2-new-schools-opening-on-coastside/article_895ee5fe-d632-11ec-bb50-77ee85942359.html | D92: Moss Beach | E92: CA | F92: West | G92: Independent | H92: 44698 | I92: Fall 2022 | M92: 15000 | O92: https://coastsideleadershipacademy.com/join-us | P92: (address unknown) | R92: 2021
A93: =row()-1 -> 92 | B93: Hemisphere School | C93: https://www.hmbreview.com/news/2-new-schools-opening-on-coastside/article_895ee5fe-d632-11ec-bb50-77ee85942359.html | D93: Half Moon Bay | E93: CA | F93: West | G93: Independent | H93: 44698 | I93: Fall 2022 | M93: 34800 | N93: 2,900 x 12 | O93: http://www.hemisphereschool.org/cost | P93: (address unknown) | R93: 2021
A94: =row()-1 -> 93 | B94: Chesterton Academy of Wichita Falls | C94: https://www.timesrecordnews.com/story/news/2022/06/10/new-catholic-high-school-slated-open-2023-wichita-falls-chesterton-academy/7490147001/ | D94: Wichita Falls | E94: TX | F94: West | G94: Roman Catholic | H94: 44722 | I94: Fall 2023 | O94: https://www.chestertonacademywf.org/ | P94: (address unknown) | R94: 2021
A95: =row()-1 -> 94 | B95: Seton Academy | C95: https://www.fosters.com/story/news/education/2022/07/14/seton-academy-rochester-nh/10028995002/ | D95: Rochester | E95: NH | F95: Northeast | G95: Roman Catholic | H95: 44756 | I95: Fall 2022 | J95: 50 | K95: https://www.fosters.com/story/news/education/2022/07/14/seton-academy-rochester-nh/10028995002/ | L95: 40-60 expected | M95: 6000 | O95: https://seton.academy/admissions | P95: 189 N Main St. Rochester, NH 03867 | Q95: 59956 | R95: 2021
A96: =row()-1 -> 95 | B96: Oak Grove Christian Academy | C96: https://www.dailyadvance.com/chowan/features/school_news/oak-grove-christian-academy-will-open-this-fall/article_a2d5ed11-990c-5840-a80f-2404553341a1.html | D96: Edenton | E96: NC | F96: South | G96: Christian | H96: 44758 | I96: Fall 2022 | M96: 2700 | N96: $2450 for K-4, $2950 for 5-8 | O96: https://www.oakgroveedenton.com/blank-page | P96: 131 Morristown Road Edenton, NC 27932 | Q96: 61151 | R96: 2021
A97: =row()-1 -> 96 | B97: Heart Dream Christian Academy | C97: https://www.marshallnewsmessenger.com/news/new-christian-private-school-in-marshall-to-start-classes-in-august/article_4e26f7c6-e855-11ec-91b3-a787f2185cc8.html | D97: Marshall | E97: TX | F97: South | G97: Christian | H97: 44722 | I97: Fall 2022 | P97: 1315 Calloway St, Marshall, TX 75670 | Q97: 36857 | R97: 2021
A98: =row()-1 -> 97 | B98: Alpha School - Brownsville | C98: https://alpha.school/brownsville/ | D98: Brownsville | E98: TX | F98: South | G98: Independent | I98: 2022 | J98: N/A | K98: N/A | L98: PreK-8 | M98: 10000 | P98: 591 N. Central Ave, Brownsville, TX 78521 | Q98: 60476 | R98: 2022
A99: =row()-1 -> 98 | B99: Fusion Academy Folsom | C99: https://www.bizjournals.com/sacramento/news/2022/07/31/fusion-academy-campus-folsom-palladio.html | D99: Folsom | E99: CA | F99: West | G99: Independent | H99: 44773 | I99: Spring 2023 | P99: 420 Palladio Pkwy, Folsom, CA 95630 | Q99: 125078 | R99: 2021
A100: =row()-1 -> 99 | B100: Southside Academy | C100: https://www.rockymounttelegram.com/features/school_news/new-private-school-welcomes-students/article_20e2a9c7-01d5-5b2b-b238-a199275af21e.html | D100: Rocky Mount | E100: NC | F100: South | G100: Christian | H100: 44760 | I100: Fall 2022 | M100: 7000 | N100: Parents pay $35/month due to school choice partnership | O100: https://www.southside.academy/admissions | P100: 2221 W. Raleigh Blvd. Rocky Mount, NC 27803 | Q100: 32037 | R100: 2021
...

Sheet Openings_summary_since_aug_2025
A1: Openings | B1: Type
A2: Total | B2: Catholic | C2: Episcopal | D2: Lutheran | E2: Christian | F2: Jewish | G2: Special needs | H2: Ind.
A3: =COUNTIF(All_openings!H2:H1033, ">=8/1/2025") -> 65 | B3: =COUNTIFS(All_openings!H2:H1033, ">=8/1/2025",All_openings!G2:G1033, "Roman Catholic") -> 11 | C3: =COUNTIFS(All_openings!H2:H1033, ">=8/1/2025",All_openings!G2:G1033, "Episcopal") -> 0 | D3: =COUNTIFS(All_openings!H2:H1033, ">=8/1/2025",All_openings!G2:G1033, "Lutheran") -> 1 | E3: =COUNTIFS(All_openings!H2:H1033, ">=8/1/2025",All_openings!G2:G1033, "Christian") -> 13 | F3: =COUNTIFS(All_openings!H2:H1033, ">=8/1/2025",All_openings!G2:G1033, "Jewish") -> 3 | G3: =COUNTIFS(All_openings!H2:H1033, ">=8/1/2025",All_openings!G2:G1033, "Special needs") -> 4 | H3: =COUNTIFS(All_openings!H2:H1033, ">=8/1/2025",All_openings!G2:G1033, "Independent") -> 30

Sheet Openings_by_month_since_aug_202
B1: Number of Announced Openings
A2: =IF(EDATE(DATE(2025,6,1), row(A2))<TODAY(), EDATE(DATE(2025,6,1), Row(A2)), "") -> 45870 | B2: =IF(A2="","",COUNTIFS(All_openings!$H$2:$H$1034, ">="& EDATE(DATE(2025,6,1), row(A2)),All_openings!$H$2:$H$1034, "<"& EDATE(DATE(2025,7,1), row(A2)))) -> 9
A3: =IF(EDATE(DATE(2025,6,1), row(A3))<TODAY(), EDATE(DATE(2025,6,1), Row(A3)), "") -> 45901 | B3: =IF(A3="","",COUNTIFS(All_openings!$H$2:$H$1034, ">="& EDATE(DATE(2025,6,1), row(A3)),All_openings!$H$2:$H$1034, "<"& EDATE(DATE(2025,7,1), row(A3)))) -> 4
A4: =IF(EDATE(DATE(2025,6,1), row(A4))<TODAY(), EDATE(DATE(2025,6,1), Row(A4)), "") -> 45931 | B4: =IF(A4="","",COUNTIFS(All_openings!$H$2:$H$1034, ">="& EDATE(DATE(2025,6,1), row(A4)),All_openings!$H$2:$H$1034, "<"& EDATE(DATE(2025,7,1), row(A4)))) -> 1
A5: =IF(EDATE(DATE(2025,6,1), row(A5))<TODAY(), EDATE(DATE(2025,6,1), Row(A5)), "") -> 45962 | B5: =IF(A5="","",COUNTIFS(All_openings!$H$2:$H$1034, ">="& EDATE(DATE(2025,6,1), row(A5)),All_openings!$H$2:$H$1034, "<"& EDATE(DATE(2025,7,1), row(A5)))) -> 4
A6: =IF(EDATE(DATE(2025,6,1), row(A6))<TODAY(), EDATE(DATE(2025,6,1), Row(A6)), "") -> 45992 | B6: =IF(A6="","",COUNTIFS(All_openings!$H$2:$H$1034, ">="& EDATE(DATE(2025,6,1), row(A6)),All_openings!$H$2:$H$1034, "<"& EDATE(DATE(2025,7,1), row(A6)))) -> 0
A7: =IF(EDATE(DATE(2025,6,1), row(A7))<TODAY(), EDATE(DATE(2025,6,1), Row(A7)), "") -> 46023 | B7: =IF(A7="","",COUNTIFS(All_openings!$H$2:$H$1034, ">="& EDATE(DATE(2025,6,1), row(A7)),All_openings!$H$2:$H$1034, "<"& EDATE(DATE(2025,7,1), row(A7)))) -> 6
A8: =IF(EDATE(DATE(2025,6,1), row(A8))<TODAY(), EDATE(DATE(2025,6,1), Row(A8)), "") -> 46054 | B8: =IF(A8="","",COUNTIFS(All_openings!$H$2:$H$1034, ">="& EDATE(DATE(2025,6,1), row(A8)),All_openings!$H$2:$H$1034, "<"& EDATE(DATE(2025,7,1), row(A8)))) -> 7
A9: =IF(EDATE(DATE(2025,6,1), row(A9))<TODAY(), EDATE(DATE(2025,6,1), Row(A9)), "") -> 46082 | B9: =IF(A9="","",COUNTIFS(All_openings!$H$2:$H$1034, ">="& EDATE(DATE(2025,6,1), row(A9)),All_openings!$H$2:$H$1034, "<"& EDATE(DATE(2025,7,1), row(A9)))) -> 3
A10: =IF(EDATE(DATE(2025,6,1), row(A10))<TODAY(), EDATE(DATE(2025,6,1), Row(A10)), "") -> 46113 | B10: =IF(A10="","",COUNTIFS(All_openings!$H$2:$H$1034, ">="& EDATE(DATE(2025,6,1), row(A10)),All_openings!$H$2:$H$1034, "<"& EDATE(DATE(2025,7,1), row(A10)))) -> 6
A11: =IF(EDATE(DATE(2025,6,1), row(A11))<TODAY(), EDATE(DATE(2025,6,1), Row(A11)), "") -> 46143 | B11: =IF(A11="","",COUNTIFS(All_openings!$H$2:$H$1034, ">="& EDATE(DATE(2025,6,1), row(A11)),All_openings!$H$2:$H$1034, "<"& EDATE(DATE(2025,7,1), row(A11)))) -> 10
A12: =IF(EDATE(DATE(2025,6,1), row(A12))<TODAY(), EDATE(DATE(2025,6,1), Row(A12)), "") -> 46174 | B12: =IF(A12="","",COUNTIFS(All_openings!$H$2:$H$1034, ">="& EDATE(DATE(2025,6,1), row(A12)),All_openings!$H$2:$H$1034, "<"& EDATE(DATE(2025,7,1), row(A12)))) -> 10
A13: =IF(EDATE(DATE(2025,6,1), row(A13))<TODAY(), EDATE(DATE(2025,6,1), Row(A13)), "") -> 46204 | B13: =IF(A13="","",COUNTIFS(All_openings!$H$2:$H$1034, ">="& EDATE(DATE(2025,6,1), row(A13)),All_openings!$H$2:$H$1034, "<"& EDATE(DATE(2025,7,1), row(A13)))) -> 5
A14: =IF(EDATE(DATE(2025,6,1), row(A14))<TODAY(), EDATE(DATE(2025,6,1), Row(A14)), "") | B14: =IF(A14="","",COUNTIFS(All_openings!$H$2:$H$1034, ">="& EDATE(DATE(2025,6,1), row(A14)),All_openings!$H$2:$H$1034, "<"& EDATE(DATE(2025,7,1), row(A14))))

Sheet cs_aug_2022
A1: Closures | B1: Type | I1: Total Enroll. | J1: Avg. Enroll. | K1: Avg. Tuition
B2: Catholic | C2: Episcopal | D2: Lutheran | E2: Christian | F2: Jewish | G2: Special needs | H2: Ind.
A3: =COUNTIF(All_closures!J2:J1005, ">=8/1/2022") -> 234 | B3: =COUNTIFS(All_closures!J2:J1005, ">=8/1/2022",All_closures!I2:I1005, "Roman Catholic") -> 178 | C3: =COUNTIFS(All_closures!J2:J1005, ">=8/1/2022",All_closures!I2:I1005, "Episcopal") -> 1 | D3: =COUNTIFS(All_closures!J2:J1005, ">=8/1/2022",All_closures!I2:I1005, "Lutheran") -> 1 | E3: =COUNTIFS(All_closures!J2:J1005, ">=8/1/2022",All_closures!I2:I1005, "Christian") -> 17 | F3: =COUNTIFS(All_closures!J2:J1005, ">=8/1/2022",All_closures!I2:I1005, "Jewish") -> 3 | G3: =COUNTIFS(All_closures!J2:J1005, ">=8/1/2022",All_closures!I2:I1005, "Special needs") -> 3 | H3: =COUNTIFS(All_closures!J2:J1005, ">=8/1/2022",All_closures!I2:I1005, "Independent") -> 30 | I3: =SUMIF(All_closures!J2:J1005, ">=8/1/2022", All_closures!K2:K1005) -> 33878 | J3: =SUMIF(All_closures!J2:J1005, ">=8/1/2022", All_closures!K2:K1005)/A3 -> 144.77778 | K3: =AVERAGEIF(All_closures!J2:J1005, ">=8/1/2022", All_closures!S2:S1005) -> 10036.167

Sheet cs_aug_2023
A1: Closures | B1: Type | I1: Total Enroll. | J1: Avg. Enroll. | K1: Avg. Tuition
B2: Catholic | C2: Episcopal | D2: Lutheran | E2: Christian | F2: Jewish | G2: Special needs | H2: Ind.
A3: =COUNTIFS(All_closures!J2:J1005, ">=8/1/2023", All_closures!J2:J1005, "<=7/31/2024") -> 60 | B3: =COUNTIFS(All_closures!J2:J1005, ">=8/1/2023",All_closures!J2:J1005, "<8/1/2024",All_closures!I2:I1005, "Roman Catholic") -> 41 | C3: =COUNTIFS(All_closures!J2:J1005, ">=8/1/2023", All_closures!J2:J1005, "<8/1/2024", All_closures!I2:I1005, "Episcopal") -> 0 | D3: =COUNTIFS(All_closures!J2:J1005, ">=8/1/2023", All_closures!J2:J1005, "<8/1/2024",All_closures!I2:I1005, "Lutheran") -> 0 | E3: =COUNTIFS(All_closures!J2:J1005, ">=8/1/2023", All_closures!J2:J1005, "<8/1/2024",All_closures!I2:I1005, "Christian") -> 8 | F3: =COUNTIFS(All_closures!J2:J1005, ">=8/1/2023", All_closures!J2:J1005, "<8/1/2024",All_closures!I2:I1005, "Jewish") -> 1 | G3: =COUNTIFS(All_closures!J2:J1005, ">=8/1/2023", All_closures!J2:J1005, "<8/1/2024",All_closures!I2:I1005, "Special needs") -> 1 | H3: =COUNTIFS(All_closures!J2:J1005, ">=8/1/2023", All_closures!J2:J1005, "<8/1/2024",All_closures!I2:I1005, "Independent") -> 9 | I3: =SUMIFS(All_closures!K2:K1005, All_closures!J2:J1005, ">=8/1/2023", All_closures!J2:J1005, "<=7/31/2024") -> 6572 | J3: =if(A3=0,"", SUMIFS(All_closures!K2:K1005, All_closures!J2:J1005, ">=8/1/2023", All_closures!J2:J1005, "<=7/31/2024")/A3) -> 109.53333 | K3: =if(A3=0,"",AVERAGEIFS(All_closures!S2:S1005, All_closures!J2:J1005, ">=8/1/2023", All_closures!J2:J1005, "<=7/31/2024")) -> 10835.535

Sheet cs_aug_2024
A1: Closures | B1: Type | I1: Total Enroll. | J1: Avg. Enroll. | K1: Avg. Tuition
B2: Catholic | C2: Episcopal | D2: Lutheran | E2: Christian | F2: Jewish | G2: Special needs | H2: Ind.
A3: =COUNTIF(All_closures!J2:J1005, ">=8/1/2024") -> 120 | B3: =COUNTIFS(All_closures!J2:J1005, ">=8/1/2024",All_closures!I2:I1005, "Roman Catholic") -> 92 | C3: =COUNTIFS(All_closures!J2:J1005, ">=8/1/2024",All_closures!I2:I1005, "Episcopal") -> 1 | D3: =COUNTIFS(All_closures!J2:J1005, ">=8/1/2024",All_closures!I2:I1005, "Lutheran") -> 1 | E3: =COUNTIFS(All_closures!J2:J1005, ">=8/1/2024",All_closures!I2:I1005, "Christian") -> 8 | F3: =COUNTIFS(All_closures!J2:J1005, ">=8/1/2024",All_closures!I2:I1005, "Jewish") -> 2 | G3: =COUNTIFS(All_closures!J2:J1005, ">=8/1/2024",All_closures!I2:I1005, "Special needs") -> 1 | H3: =COUNTIFS(All_closures!J2:J1005, ">=8/1/2024",All_closures!I2:I1005, "Independent") -> 14 | I3: =SUMIF(All_closures!J2:J1005, ">=8/1/2024", All_closures!K2:K1005) -> 17682 | J3: =if(A3=0,"", SUMIF(All_closures!J2:J1005, ">=8/1/2024", All_closures!K2:K1005)/A3) -> 147.35 | K3: =if(A3=0,"",AVERAGEIF(All_closures!J2:J1005, ">=8/1/2024", All_closures!S2:S1005)) -> 9637.8

Sheet All_closures
B1: Closures | C1: COVID? | D1: Merging with Other School Closure | E1: New School | F1: Town | G1: State | H1: Region | I1: Type | J1: Date Reported | K1: Enrollment | L1: Enrollment source | M1: Year founded | N1: Notes | O1: Preexisting financial problems? | P1: Link | Q1: % Students on Financial Aid | R1: Link2 | S1: Tuition | T1: Link3 | U1: % Black | V1: Enrolled Black | W1: % Hispanic | X1: Enrolled Hispanic | Y1: % Asian | Z1: Enrolled Asian | AA1: % White | AB1: Enrolled White | AC1: % Other | AD1: Enrolled Other | AE1: Link4 | AF1: Full Address | AG1: Estimated Tract Median Family Income | AH1: Data Year
A2: =ROW()-1 -> 1 | B2: Saint Anthony School | C2: x | F2: Winsted | G2: CT | H2: Northeast | I2: Roman Catholic | J2: 43908 | K2: 90 | L2: Media | M2: 1865 | O2: Yes | P2: https://www.registercitizen.com/news/article/Winsted-s-St-Anthony-School-closing-in-June-15138379.php | S2: 5200 | T2: http://www.stanthonyschool-winsted.org/wp-content/uploads/2019/03/FullSizeRender-2019-03-28T205251.691.jpg | U2: 0 | V2: =IF(U2<>"",K2*U2/100,"") -> 0 | W2: 0 | X2: =IF(W2<>"",K2*W2/100,"") -> 0 | Y2: 1.8 | Z2: =IF(Y2<>"",K2*Y2/100,"") -> 1.62 | AA2: 95.8 | AB2: =IF(AA2<>"",K2*AA2/100,"") -> 86.22 | AC2: 2.4 | AD2: =IF(AC2<>"",K2*AC2/100,"") -> 2.16 | AE2: https://www.niche.com/k12/st-anthony-school-winsted-ct/ | AF2: 55 Oak St, Winsted, CT 06098 | AG2: 59763 | AH2: 2020
A3: =ROW()-1 -> 2 | B3: Midreshet Shalhevet High School | C3: x | F3: Valley Stream | G3: NY | H3: Northeast | I3: Jewish | J3: 43922 | K3: 80 | L3: PSR | M3: 2007 | U3: 0 | V3: =IF(U3<>"",K3*U3/100,"") -> 0 | W3: 0 | X3: =IF(W3<>"",K3*W3/100,"") -> 0 | Y3: 0 | Z3: =IF(Y3<>"",K3*Y3/100,"") -> 0 | AA3: 100 | AB3: =IF(AA3<>"",K3*AA3/100,"") -> 80 | AC3: 0 | AD3: =IF(AC3<>"",K3*AC3/100,"") -> 0 | AE3: https://www.niche.com/k12/midreshet-shalhevet-shalhevet-high-school-for-girls-valley-stream-ny/students/ | AF3: 1000 Rosedale Rd, Valley Stream, NY 11581 | AG3: 136424 | AH3: 2020
A4: =ROW()-1 -> 3 | B4: Saint Martha | C4: x | F4: Enfield | G4: CT | H4: Northeast | I4: Roman Catholic | J4: 43929 | K4: 148 | L4: Media | M4: 1963 | N4: Parent group trying to save school | O4: Yes | P4: https://www.journalinquirer.com/towns/enfield/it-s-a-tragedy-for-everybody-st-martha-school-to-close-after-55-years-due/article_34e5607e-7f14-11ea-af3a-6f63e01e8aef.html | S4: 6303 | T4: https://www.stmarthaschool-ct.org/tuition | U4: 1.9 | V4: =IF(U4<>"",K4*U4/100,"") -> 2.812 | W4: 3.1 | X4: =IF(W4<>"",K4*W4/100,"") -> 4.588 | Y4: 6.2 | Z4: =IF(Y4<>"",K4*Y4/100,"") -> 9.176 | AA4: 85.7 | AB4: =IF(AA4<>"",K4*AA4/100,"") -> 126.836 | AC4: 3.1 | AD4: =IF(AC4<>"",K4*AC4/100,"") -> 4.588 | AE4: https://www.niche.com/k12/st-martha-school-enfield-ct/ | AF4: 214 Brainard Rd, Enfield, CT 06082 | AG4: 100538 | AH4: 2020
A5: =ROW()-1 -> 4 | B5: Oyster Point Academy | C5: x | F5: Hampton Roads | G5: VA | H5: South | I5: Special needs | J5: 43932 | K5: 28 | L5: PSR | U5: 82 | V5: =IF(U5<>"",K5*U5/100,"") -> 22.96 | W5: 4 | X5: =IF(W5<>"",K5*W5/100,"") -> 1.12 | Y5: 0 | Z5: =IF(Y5<>"",K5*Y5/100,"") -> 0 | AA5: 14 | AB5: =IF(AA5<>"",K5*AA5/100,"") -> 3.92 | AC5: 0 | AD5: =IF(AC5<>"",K5*AC5/100,"") -> 0 | AE5: https://high-schools.com/directory/va/cities/newport-news/oyster-point-academy/a1503976/ | AF5: 766 J Clyde Morris Blvd Newport News, VA 23601 | AG5: 72189 | AH5: 2020
A6: =ROW()-1 -> 5 | B6: Coyle and Cassidy H.S. & M.S. | C6: x | F6: Taunton | G6: MA | H6: Northeast | I6: Roman Catholic | J6: 43936 | K6: 258 | L6: Media | M6: 1911 | N6: Some dispute closure necessary or COVID-driven | O6: Yes | P6: https://www.tauntongazette.com/news/20200418/we-had-no-opportunity-to-save-that-school----coyle-cassidy-closure-in-taunton-draws-strong-reaction | S6: 10590 | T6: https://www.coylecassidy.com/tuition-rates-and-financial-aid/ | U6: 7.1 | V6: =IF(U6<>"",K6*U6/100,"") -> 18.318 | W6: 1.6 | X6: =IF(W6<>"",K6*W6/100,"") -> 4.128 | Y6: 2.6 | Z6: =IF(Y6<>"",K6*Y6/100,"") -> 6.708 | AA6: 88.3 | AB6: =IF(AA6<>"",K6*AA6/100,"") -> 227.814 | AC6: 0.4 | AD6: =IF(AC6<>"",K6*AC6/100,"") -> 1.032 | AE6: https://www.niche.com/k12/coyle--and--cassidy-high-school-taunton-ma/students/ | AF6: 2 Hamilton St, Taunton, MA 02780 | AG6: 63252 | AH6: 2020
A7: =ROW()-1 -> 6 | B7: Saint Margaret Primary | C7: x | F7: Buzzards Bay | G7: MA | H7: Northeast | I7: Roman Catholic | J7: 43936 | K7: 62 | L7: Media | M7: 1994 | O7: Yes | P7: http://www.smrsbb.org/wp-content/uploads/Two-School-Closures_April-14-2020.docx.pdf | Q7: 10 | R7: https://www.privateschoolreview.com/st-margaret-primary-school-profile | S7: 5825 | T7: http://www.smrsbb.org/wp-content/uploads/Enrollment-Information-2019-2020.pdf | U7: 5.3 | V7: =IF(U7<>"",K7*U7/100,"") -> 3.286 | W7: 4 | X7: =IF(W7<>"",K7*W7/100,"") -> 2.48 | Y7: 5.3 | Z7: =IF(Y7<>"",K7*Y7/100,"") -> 3.286 | AA7: 82.7 | AB7: =IF(AA7<>"",K7*AA7/100,"") -> 51.274 | AC7: 2.7 | AD7: =IF(AC7<>"",K7*AC7/100,"") -> 1.674 | AE7: https://www.niche.com/k12/st-margaret-primary-school-buzzards-bay-ma/ | AF7: 143 Main Street Buzzards Bay, MA 02532 | AG7: 122991 | AH7: 2020
A8: =ROW()-1 -> 7 | B8: Cape Trinity Elementary | C8: x | D8: Yes^ | E8: Yes | F8: Wildwood | G8: NJ | H8: Northeast | I8: Roman Catholic | J8: 43938 | K8: 200 | L8: Media | M8: 1929 | N8: Announced on 6/4/2020 that it will be merging with Wildwood Catholic HS | O8: Yes | P8: https://www.camdendiocese.org/five-catholic-schools-in-the-diocese-of-camden-to-close-at-end-of-school-year/ | S8: 5150 | T8: https://4.files.edl.io/e69b/10/01/19/152917-c2ef0243-ed72-4cbf-ab2f-7b1ae04c3954.pdf | U8: 1 | V8: =IF(U8<>"",K8*U8/100,"") -> 2 | W8: 3.5 | X8: =IF(W8<>"",K8*W8/100,"") -> 7 | Y8: 1.5 | Z8: =IF(Y8<>"",K8*Y8/100,"") -> 3 | AA8: 90 | AB8: =IF(AA8<>"",K8*AA8/100,"") -> 180 | AC8: 4 | AD8: =IF(AC8<>"",K8*AC8/100,"") -> 8 | AE8: https://www.niche.com/k12/cape-trinity-catholic-school-north-wildwood-nj/ | AF8: 1500 Central Ave, North Wildwood, NJ 08260 | AG8: 62205 | AH8: 2020
A9: =ROW()-1 -> 8 | B9: Wildwood Catholic H.S. | C9: x | D9: Yes | E9: Yes^ | F9: Wildwood | G9: NJ | H9: Northeast | I9: Roman Catholic | J9: 43938 | K9: 140 | L9: Media | M9: 1948 | N9: Announced on 6/4/2020 that it will be merging with Cape Trinity Elementary (counts as one net closure) | O9: Yes | P9: https://www.camdendiocese.org/five-catholic-schools-in-the-diocese-of-camden-to-close-at-end-of-school-year/ | S9: 9100 | T9: https://wildwoodcatholicacademy.org/financialaid | U9: 3 | V9: =IF(U9<>"",K9*U9/100,"") -> 4.2 | W9: 6 | X9: =IF(W9<>"",K9*W9/100,"") -> 8.4 | Y9: 6 | Z9: =IF(Y9<>"",K9*Y9/100,"") -> 8.4 | AA9: 81 | AB9: =IF(AA9<>"",K9*AA9/100,"") -> 113.4 | AC9: 2 | AD9: =IF(AC9<>"",K9*AC9/100,"") -> 2.8 | AE9: https://www.niche.com/k12/wildwood-catholic-high-school-north-wildwood-nj/students/ | AF9: 1500 Central Ave, North Wildwood, NJ 08260 | AG9: 62205 | AH9: 2020
A10: =ROW()-1 -> 9 | B10: Good Shepherd Regional Elementary | C10: x | F10: Collingswood | G10: NJ | H10: Northeast | I10: Roman Catholic | J10: 43938 | K10: 108 | L10: Media | O10: Yes | P10: https://www.camdendiocese.org/five-catholic-schools-in-the-diocese-of-camden-to-close-at-end-of-school-year/ | S10: 4525 | T10: https://www.gscregional.org/tuition-and-fees.html | U10: 9.1 | V10: =IF(U10<>"",K10*U10/100,"") -> 9.828 | W10: 3.3 | X10: =IF(W10<>"",K10*W10/100,"") -> 3.564 | Y10: 2.6 | Z10: =IF(Y10<>"",K10*Y10/100,"") -> 2.808 | AA10: 78.6 | AB10: =IF(AA10<>"",K10*AA10/100,"") -> 84.888 | AC10: 6.5 | AD10: =IF(AC10<>"",K10*AC10/100,"") -> 7.02 | AE10: https://www.niche.com/k12/good-shepherd-regional-school-collingswood-nj/ | AF10: 100 Lees Ave, Collingswood, NJ 08108 | AG10: 97207 | AH10: 2020
A11: =ROW()-1 -> 10 | B11: Saint Joseph Regional Elementary | C11: x | F11: Hammonton | G11: NJ | H11: Northeast | I11: Roman Catholic | J11: 43938 | K11: 94 | L11: Media | M11: 1922 | O11: Yes | P11: https://www.inquirer.com/education/school-closing-new-jersey-catholic-wildwood-catholic-good-shepherd-saint-joseph-20200417.html | Q11: 10 | R11: https://www.privateschoolreview.com/st-joseph-regional-elementary-school-profile | S11: 5375 | T11: https://www.stjosephprek8.org/tuition-and-financial-aid | U11: 5.5 | V11: =IF(U11<>"",K11*U11/100,"") -> 5.17 | W11: 5.5 | X11: =IF(W11<>"",K11*W11/100,"") -> 5.17 | Y11: 1.7 | Z11: =IF(Y11<>"",K11*Y11/100,"") -> 1.598 | AA11: 85.7 | AB11: =IF(AA11<>"",K11*AA11/100,"") -> 80.558 | AC11: 1.7 | AD11: =IF(AC11<>"",K11*AC11/100,"") -> 1.598 | AE11: https://www.niche.com/k12/st-joseph-regional-elementary-school-hammonton-nj/ | AF11: 40 Chestnut Ridge Rd, Montvale, NJ 07645 | AG11: 119663 | AH11: 2020
A12: =ROW()-1 -> 11 | B12: St. Joseph Catholic High School | F12: Hammonton | G12: NJ | H12: Northeast | I12: Roman Catholic | J12: 43938 | K12: 206 | L12: Media | P12: https://www.camdendiocese.org/five-catholic-schools-in-the-diocese-of-camden-to-close-at-end-of-school-year/ | AF12: 328 Vine Street Hammonton, New Jersey 08037 | AG12: 119663 | AH12: 2020
A13: =ROW()-1 -> 12 | B13: Saint Mary's | C13: x | F13: Lawton | G13: OK | H13: South | I13: Roman Catholic | J13: 43938 | K13: 135 | L13: Media | M13: 1907 | O13: Yes | P13: https://www.stmarys-ok.org/school-closing-information | S13: 4700 | T13: https://www.stmarys-ok.org/tuition-fees | U13: 12.2 | V13: =IF(U13<>"",K13*U13/100,"") -> 16.47 | W13: 26.8 | X13: =IF(W13<>"",K13*W13/100,"") -> 36.18 | Y13: 10.6 | Z13: =IF(Y13<>"",K13*Y13/100,"") -> 14.31 | AA13: 35.8 | AB13: =IF(AA13<>"",K13*AA13/100,"") -> 48.33 | AC13: 14.6 | AD13: =IF(AC13<>"",K13*AC13/100,"") -> 19.71 | AE13: https://www.niche.com/k12/st-marys-catholic-school-lawton-ok/ | AF13: 611 SW A Ave #3972, Lawton, OK 73501 | AG13: 48140 | AH13: 2020
A14: =ROW()-1 -> 13 | B14: Poughkeepsie Day School | C14: x | D14: No | F14: Poughkeepsie | G14: NY | H14: Northeast | I14: Independent | J14: 43942 | K14: 175 | L14: Media | M14: 1934 | N14: Plans to reopen in 2021-2022: https://hudsonvalleypost.com/famed-hudson-valley-school-announces-plans-to-reopen/ | O14: Yes | P14: https://www.poughkeepsiejournal.com/story/news/education/2020/04/21/coronavirus-poughkeepsie-day-school-announces-closure-june/2995029001/ | Q14: 42 | R14: https://www.privateschoolreview.com/poughkeepsie-day-school-profile | S14: 29213 | T14: https://poughkeepsieday.org/admissions/flexible-tuition/ | U14: 5.8 | V14: =IF(U14<>"",K14*U14/100,"") -> 10.15 | W14: 8.1 | X14: =IF(W14<>"",K14*W14/100,"") -> 14.175 | Y14: 2.3 | Z14: =IF(Y14<>"",K14*Y14/100,"") -> 4.025 | AA14: 72.7 | AB14: =IF(AA14<>"",K14*AA14/100,"") -> 127.225 | AC14: 11.1 | AD14: =IF(AC14<>"",K14*AC14/100,"") -> 19.425 | AE14: https://www.niche.com/k12/poughkeepsie-day-school-poughkeepsie-ny/students/ | AF14: 260 Boardman Rd, Poughkeepsie, NY 12603 | AG14: 140931 | AH14: 2020
A15: =ROW()-1 -> 14 | B15: Our Lady of Mt. Carmel | C15: x | F15: Houston | G15: TX | H15: South | I15: Roman Catholic | J15: 43943 | K15: 85 | L15: School | M15: 1954 | O15: Yes | P15: https://olmchou.org/a-letter-from-fr-cobos-concerning-the-closing-of-olmc/ | Q15: 100 | R15: School | S15: 3750 | T15: https://olmchou.org/wp-content/uploads/2020/01/2020-2021-Tuition-and-Fees.pdf | U15: 11.1 | V15: =IF(U15<>"",K15*U15/100,"") -> 9.435 | W15: 83.6 | X15: =IF(W15<>"",K15*W15/100,"") -> 71.06 | Y15: 2.3 | Z15: =IF(Y15<>"",K15*Y15/100,"") -> 1.955 | AA15: 2.3 | AB15: =IF(AA15<>"",K15*AA15/100,"") -> 1.955 | AC15: 0.6 | AD15: =IF(AC15<>"",K15*AC15/100,"") -> 0.51 | AE15: https://www.niche.com/k12/our-lady-of-mount-carmel-school-houston-tx/ | AF15: 6703 Whitefriars Dr, Houston, TX 77087 | AG15: 42928 | AH15: 2020
A16: =ROW()-1 -> 15 | B16: Queen of Peace | C16: x | F16: Houston | G16: TX | H16: South | I16: Roman Catholic | J16: 43943 | K16: 131 | L16: PSR | M16: 1942 | O16: Yes | P16: https://abc13.com/catholic-schools-closing-st-pius-v-our-lady-of-mount-carmel-queen-peace/6121113/ | S16: 3750 | T16: https://queenofpeacecatholicschool.org/wp-content/uploads/2019/12/2020-2021-Tuition-and-Fees-new.pdf | U16: 2 | V16: =IF(U16<>"",K16*U16/100,"") -> 2.62 | W16: 87 | X16: =IF(W16<>"",K16*W16/100,"") -> 113.97 | Y16: 7 | Z16: =IF(Y16<>"",K16*Y16/100,"") -> 9.17 | AA16: 6 | AB16: =IF(AA16<>"",K16*AA16/100,"") -> 7.86 | AC16: 1 | AD16: =IF(AC16<>"",K16*AC16/100,"") -> 1.31 | AE16: https://www.learncentralhouston.org/schools/view/queen-peace-catholic-school/ | AF16: 2320 Oakcliff St, Houston, TX 77023 | AG16: 57544 | AH16: 2020
A17: =ROW()-1 -> 16 | B17: Saint Francis of Assisi | C17: x | F17: Houston | G17: TX | H17: South | I17: Roman Catholic | J17: 43943 | K17: 162 | L17: PSR | O17: Yes | P17: https://abc13.com/catholic-schools-closing-st-pius-v-our-lady-of-mount-carmel-queen-peace/6121113/ | S17: 7000 | T17: https://sfoacs.org/admissions/tuition-fees/ | U17: 94.1 | V17: =IF(U17<>"",K17*U17/100,"") -> 152.442 | W17: 2.9 | X17: =IF(W17<>"",K17*W17/100,"") -> 4.698 | Y17: 2.9 | Z17: =IF(Y17<>"",K17*Y17/100,"") -> 4.698 | AA17: 0 | AB17: =IF(AA17<>"",K17*AA17/100,"") -> 0 | AC17: 0 | AD17: =IF(AC17<>"",K17*AC17/100,"") -> 0 | AE17: https://www.niche.com/k12/st-francis-of-assisi-school-houston-tx/ | AF17: 5100 Dabney St, Houston, TX 77026 | AG17: 31472 | AH17: 2020
A18: =ROW()-1 -> 17 | B18: Saint Pius V | C18: x | F18: Pasadena | G18: TX | H18: South | I18: Roman Catholic | J18: 43943 | K18: 60 | L18: PSR | M18: 1947 | O18: Yes | P18: https://abc13.com/catholic-schools-closing-st-pius-v-our-lady-of-mount-carmel-queen-peace/6121113/ | Q18: 95 | R18: https://www.privateschoolreview.com/st-pius-v-catholic-school-profile/77506 | S18: 3750 | T18: https://spvpasadena.org/admissions/tuition-assistance/ | U18: 2.2 | V18: =IF(U18<>"",K18*U18/100,"") -> 1.32 | W18: 91.1 | X18: =IF(W18<>"",K18*W18/100,"") -> 54.66 | Y18: 0 | Z18: =IF(Y18<>"",K18*Y18/100,"") -> 0 | AA18: 2.2 | AB18: =IF(AA18<>"",K18*AA18/100,"") -> 1.32 | AC18: 4.4 | AD18: =IF(AC18<>"",K18*AC18/100,"") -> 2.64 | AE18: https://www.niche.com/k12/st-pius-v-catholic-school-pasadena-tx/ | AF18: 812 Main St, Pasadena, TX 77506 | AG18: 36832 | AH18: 2020
A19: =ROW()-1 -> 18 | B19: Lawton Christian School | C19: x | F19: Lawton | G19: OK | H19: South | I19: Christian | J19: 43943 | K19: 38 | L19: Media | M19: 1976 | N19: Only discontinued grades 9-12 | O19: Yes | P19: https://www.kswo.com/2020/04/22/lcs-staff-shares-reasons-closing-secondary-school/ | S19: 6875 | T19: http://www.lcscrusaders.com/editoruploads/files/19-20_Tuition_Prices.pdf | U19: 30 | V19: =IF(U19<>"",K19*U19/100,"") -> 11.4 | W19: 7 | X19: =IF(W19<>"",K19*W19/100,"") -> 2.66 | Y19: 5 | Z19: =IF(Y19<>"",K19*Y19/100,"") -> 1.9 | AA19: 50 | AB19: =IF(AA19<>"",K19*AA19/100,"") -> 19 | AC19: 5 | AD19: =IF(AC19<>"",K19*AC19/100,"") -> 1.9 | AE19: https://www.niche.com/k12/lawton-christian-school-lawton-ok/students/ | AF19: 1 Crusader Dr, Lawton, OK 73505 | AG19: 97726 | AH19: 2020
A20: =ROW()-1 -> 19 | B20: Holy Family Consolidated | C20: x | F20: Berwick | G20: PA | H20: Northeast | I20: Roman Catholic | J20: 43949 | K20: 62 | L20: Media | O20: Yes | P20: https://www.wnep.com/article/news/local/columbia-county/holy-family-catholic-school-closing/523-8d93ac3b-bda6-43a4-b93c-f365009f1c5d | U20: 0 | V20: =IF(U20<>"",K20*U20/100,"") -> 0 | W20: 9.8 | X20: =IF(W20<>"",K20*W20/100,"") -> 6.076 | Y20: 2.2 | Z20: =IF(Y20<>"",K20*Y20/100,"") -> 1.364 | AA20: 88 | AB20: =IF(AA20<>"",K20*AA20/100,"") -> 54.56 | AC20: 0 | AD20: =IF(AC20<>"",K20*AC20/100,"") -> 0 | AE20: https://www.niche.com/k12/holy-family-consolidated-school-berwick-pa/ | AF20: 728 Washington St, Berwick, PA 18603 | AG20: 58004 | AH20: 2020
A21: =ROW()-1 -> 20 | B21: Lebanon Catholic | C21: x | F21: Lebanon | G21: PA | H21: Northeast | I21: Roman Catholic | J21: 43949 | K21: 350 | L21: Media | M21: 1859 | O21: Yes | P21: https://www.ldnews.com/story/news/2020/04/28/lebanon-catholic-school-close-end-school-year/3044484001/ | S21: 4310 | T21: http://www.lebanoncatholicschool.org/admissions/financial-assistance/ | U21: 3 | V21: =IF(U21<>"",K21*U21/100,"") -> 10.5 | W21: 8 | X21: =IF(W21<>"",K21*W21/100,"") -> 28 | Y21: 3 | Z21: =IF(Y21<>"",K21*Y21/100,"") -> 10.5 | AA21: 83 | AB21: =IF(AA21<>"",K21*AA21/100,"") -> 290.5 | AC21: 1 | AD21: =IF(AC21<>"",K21*AC21/100,"") -> 3.5 | AE21: https://www.niche.com/k12/lebanon-catholic-school-lebanon-pa/students/ | AF21: 1400 Chestnut St, Lebanon, PA 17042 | AG21: 56110 | AH21: 2020
A22: =ROW()-1 -> 21 | B22: Saint John the Baptist Catholic School | C22: x | F22: Napa | G22: CA | H22: West | I22: Roman Catholic | J22: 43949 | K22: 76 | L22: Media | M22: 1912 | O22: Yes | P22: https://napavalleyregister.com/news/local/citing-economics-napas-st-john-s-catholic-school-to-close/article_d565cd9b-adf5-527f-a471-55a89ccedc7f.html | U22: 0 | V22: =IF(U22<>"",K22*U22/100,"") -> 0 | W22: 55.1 | X22: =IF(W22<>"",K22*W22/100,"") -> 41.876 | Y22: 6.1 | Z22: =IF(Y22<>"",K22*Y22/100,"") -> 4.636 | AA22: 24.5 | AB22: =IF(AA22<>"",K22*AA22/100,"") -> 18.62 | AC22: 14.3 | AD22: =IF(AC22<>"",K22*AC22/100,"") -> 10.868 | AE22: https://www.niche.com/k12/st-john-the-baptist-catholic-school-napa-ca/ | AF22: 983 Napa St, Napa, CA 94559 | AG22: 82719 | AH22: 2020
A23: =ROW()-1 -> 22 | B23: All Saints | C23: x | D23: No | F23: Elsmere | G23: DE | H23: South | I23: Roman Catholic | J23: 43951 | K23: 210 | L23: Media | M23: 2011 | O23: Yes | P23: https://www.wdel.com/news/elsmeres-all-saints-catholic-school-closing-at-the-end-of-the-year-due-to-lack/article_e8e6965a-8b09-11ea-95a2-1bd670c2de35.html | Q23: 90 | R23: https://www.privateschoolreview.com/all-saints-catholic-school-profile/19805 | S23: 6470 | T23: https://www.privateschoolreview.com/all-saints-catholic-school-profile/19805 | U23: 4.3 | V23: =IF(U23<>"",K23*U23/100,"") -> 9.03 | W23: 10.4 | X23: =IF(W23<>"",K23*W23/100,"") -> 21.84 | Y23: 0.8 | Z23: =IF(Y23<>"",K23*Y23/100,"") -> 1.68 | AA23: 83.8 | AB23: =IF(AA23<>"",K23*AA23/100,"") -> 175.98 | AC23: 0.8 | AD23: =IF(AC23<>"",K23*AC23/100,"") -> 1.68 | AE23: https://www.niche.com/k12/all-saints-catholic-school-wilmington-de/ | AF23: 907 New Rd, Wilmington, DE 19805 | AG23: 61762 | AH23: 2020
A24: =ROW()-1 -> 23 | B24: Siena Catholic Academy | C24: x | F24: Brighton | G24: NY | H24: Northeast | I24: Roman Catholic | J24: 43951 | K24: 132 | L24: Media | M24: 1994 | O24: Yes | P24: https://catholiccourier.com/articles/enrollment-woes-intensified-by-pandemic-to-shutter-siena-academy | Q24: 32 | R24: https://www.niche.com/k12/siena-catholic-academy-rochester-ny/ | S24: 6600 | T24: https://www.sienacatholic.org/wp-content/uploads/Siena-2020-2021-Tuition-Rates-updated-11.06.19.pdf | U24: 8.3 | V24: =IF(U24<>"",K24*U24/100,"") -> 10.956 | W24: 0.9 | X24: =IF(W24<>"",K24*W24/100,"") -> 1.188 | Y24: 1.8 | Z24: =IF(Y24<>"",K24*Y24/100,"") -> 2.376 | AA24: 88.9 | AB24: =IF(AA24<>"",K24*AA24/100,"") -> 117.348 | AC24: 0 | AD24: =IF(AC24<>"",K24*AC24/100,"") -> 0 | AE24: https://www.niche.com/k12/siena-catholic-academy-rochester-ny/ | AF24: 2617 East Ave, Rochester, NY 14610 | AG24: 150106 | AH24: 2020
A25: =ROW()-1 -> 24 | B25: Saint Mark's Episcopal School | C25: x | F25: Upland | G25: CA | H25: West | I25: Episcopal | J25: 43951 | K25: 106 | L25: Media | M25: 1982 | N25: preschool may reopen during fall | O25: Yes | P25: https://www.dailybulletin.com/2020/05/16/after-38-years-st-marks-episcopal-school-in-upland-is-closing/ | Q25: 35 | R25: https://www.privateschoolreview.com/saint-mark-s-episcopal-school-profile | S25: 13613 | T25: https://www.stmarks-upland.org/admission/tuition-fees-and-financial-aid/ | U25: 6.6 | V25: =IF(U25<>"",K25*U25/100,"") -> 6.996 | W25: 14.9 | X25: =IF(W25<>"",K25*W25/100,"") -> 15.794 | Y25: 14.9 | Z25: =IF(Y25<>"",K25*Y25/100,"") -> 15.794 | AA25: 49.4 | AB25: =IF(AA25<>"",K25*AA25/100,"") -> 52.364 | AC25: 14.3 | AD25: =IF(AC25<>"",K25*AC25/100,"") -> 15.158 | AE25: https://www.niche.com/k12/st-marks-episcopal-school-upland-ca/ | AF25: 330 E 16th St, Upland, CA 91784 | AG25: 133266 | AH25: 2020
A26: =ROW()-1 -> 25 | B26: Saint Joseph Catholic Academy | C26: x | F26: Brookfield | G26: CT | H26: Northeast | I26: Roman Catholic | J26: 43955 | K26: 66 | L26: Media | M26: 1953 | O26: Yes | P26: https://www.ctinsider.com/local/newstimes/article/St-Joseph-Catholic-Academy-in-Brookfield-to-close-15245757.php | S26: 6500 | T26: https://www.sjsbrookfield.org/tuition-and-financial-aid | U26: 1.9 | V26: =IF(U26<>"",K26*U26/100,"") -> 1.254 | W26: 7.7 | X26: =IF(W26<>"",K26*W26/100,"") -> 5.082 | Y26: 1.9 | Z26: =IF(Y26<>"",K26*Y26/100,"") -> 1.254 | AA26: 74 | AB26: =IF(AA26<>"",K26*AA26/100,"") -> 48.84 | AC26: 14.4 | AD26: =IF(AC26<>"",K26*AC26/100,"") -> 9.504 | AE26: https://www.niche.com/k12/st-joseph-catholic-academy-brookfield-ct/ | AF26: 5 Obtuse Hill Rd, Brookfield, CT 06804 | AG26: 154705 | AH26: 2020
A27: =ROW()-1 -> 26 | B27: Institute of Notre Dame | C27: x | F27: Baltimore | G27: MD | H27: South | I27: Roman Catholic | J27: 43956 | K27: 273 | L27: PSR | M27: 1847 | O27: Yes | P27: https://www.baltimoresun.com/education/bs-md-institute-notre-dame-closing-20200505-iviuyq5k5zfo5ke3zqytgv3o4u-story.html | Q27: 90 | R27: https://www.baltimoresun.com/education/bs-md-institute-notre-dame-closing-20200505-iviuyq5k5zfo5ke3zqytgv3o4u-story.html | S27: 15070 | T27: https://www.indofmd.org/enrollment/tuition | U27: 37.5 | V27: =IF(U27<>"",K27*U27/100,"") -> 102.375 | W27: 4.8 | X27: =IF(W27<>"",K27*W27/100,"") -> 13.104 | Y27: 4.4 | Z27: =IF(Y27<>"",K27*Y27/100,"") -> 12.012 | AA27: 46.4 | AB27: =IF(AA27<>"",K27*AA27/100,"") -> 126.672 | AC27: 6.4 | AD27: =IF(AC27<>"",K27*AC27/100,"") -> 17.472 | AE27: https://www.niche.com/k12/institute-of-notre-dame-baltimore-md/students/ | AF27: 901 Aisquith St, Baltimore, MD 21202 | AG27: 32323 | AH27: 2020
A28: =ROW()-1 -> 27 | B28: Immaculate Conception School | C28: x | F28: Marlborough | G28: MA | H28: Northeast | I28: Roman Catholic | J28: 43956 | K28: 132 | L28: Media | M28: 1910 | O28: Yes | P28: https://www.thebostonpilot.com/article.asp?ID=187592 | S28: 7550 | T28: https://www.icschool.net/tuition | U28: 1.8 | V28: =IF(U28<>"",K28*U28/100,"") -> 2.376 | W28: 7 | X28: =IF(W28<>"",K28*W28/100,"") -> 9.24 | Y28: 5.3 | Z28: =IF(Y28<>"",K28*Y28/100,"") -> 6.996 | AA28: 80.7 | AB28: =IF(AA28<>"",K28*AA28/100,"") -> 106.524 | AC28: 5.3 | AD28: =IF(AC28<>"",K28*AC28/100,"") -> 6.996 | AE28: https://www.niche.com/k12/immaculate-conception-school-marlborough-ma/ | AF28: 25 Washington Ct, Marlborough, MA 01752 | AG28: 77992 | AH28: 2020
A29: =ROW()-1 -> 28 | B29: Saint James Catholic School | C29: x | F29: Belvidere | G29: IL | H29: Midwest | I29: Roman Catholic | J29: 43957 | K29: 36 | L29: Media | M29: 1910 | O29: Yes | P29: https://www.mystateline.com/news/local-news/belvideres-st-james-catholic-school-to-permanently-close/ | S29: 3850 | T29: http://www.stjamesbelvidere.org/st-james-school/wp-content/uploads/2018/01/St.-James-School-Enrollment-Packet.pdf | U29: 2 | V29: =IF(U29<>"",K29*U29/100,"") -> 0.72 | W29: 26.7 | X29: =IF(W29<>"",K29*W29/100,"") -> 9.612 | Y29: 0 | Z29: =IF(Y29<>"",K29*Y29/100,"") -> 0 | AA29: 56.4 | AB29: =IF(AA29<>"",K29*AA29/100,"") -> 20.304 | AC29: 14.9 | AD29: =IF(AC29<>"",K29*AC29/100,"") -> 5.364 | AE29: https://www.niche.com/k12/st-james-school-belvidere-il/ | AF29: 320 Logan Ave, Belvidere, IL 61008 | AG29: 62299 | AH29: 2020
A30: =ROW()-1 -> 29 | B30: Saint Barnabas Catholic School | C30: x | F30: Birmingham | G30: AL | H30: South | I30: Roman Catholic | J30: 43957 | K30: 100 | L30: Media | M30: 1958 | O30: Yes | P30: https://www.wbrc.com/2020/05/06/st-barnabas-catholic-school-will-cut-numerous-grade-levels-next-year-due-pandemic/ | Q30: 0.8 | R30: School | S30: 4520 | T30: School | U30: 84.3 | V30: =IF(U30<>"",K30*U30/100,"") -> 84.3 | W30: 7.8 | X30: =IF(W30<>"",K30*W30/100,"") -> 7.8 | Y30: 0 | Z30: =IF(Y30<>"",K30*Y30/100,"") -> 0 | AA30: 3.3 | AB30: =IF(AA30<>"",K30*AA30/100,"") -> 3.3 | AC30: 4.6 | AD30: =IF(AC30<>"",K30*AC30/100,"") -> 4.6 | AE30: https://www.niche.com/k12/st-barnabas-regional-school-birmingham-al/ | AF30: 7901 1st Ave N, Birmingham, AL 35206 | AG30: 22304 | AH30: 2020
A31: =ROW()-1 -> 30 | B31: Monsignor McHugh School | C31: x | F31: Cresco | G31: PA | H31: Northeast | I31: Roman Catholic | J31: 43957 | K31: 70 | L31: Media | M31: 1961 | O31: Yes | P31: https://www.dioceseofscranton.org/diocese-announces-closure-of-monsignor-mchugh-school/ | Q31: 28 | R31: https://www.niche.com/k12/monsignor-mchugh-school-cresco-pa/ | S31: 4400 | T31: https://d0bfdaa1-6434-431f-b6de-79a8afeb3498.filesusr.com/ugd/ee9872_a41708194dae4fc2945acc4773a4d87c.pdf | U31: 22.1 | V31: =IF(U31<>"",K31*U31/100,"") -> 15.47 | W31: 7.7 | X31: =IF(W31<>"",K31*W31/100,"") -> 5.39 | Y31: 2.9 | Z31: =IF(Y31<>"",K31*Y31/100,"") -> 2.03 | AA31: 54.8 | AB31: =IF(AA31<>"",K31*AA31/100,"") -> 38.36 | AC31: 12.5 | AD31: =IF(AC31<>"",K31*AC31/100,"") -> 8.75 | AE31: https://www.niche.com/k12/monsignor-mchugh-school-cresco-pa/ | AF31: 212 PA-390, Cresco, PA 18326 | AG31: 75058 | AH31: 2020
A32: =ROW()-1 -> 31 | B32: Cristo Rey Newark High School | C32: x | F32: Newark | G32: NJ | H32: Northeast | I32: Roman Catholic | J32: 43958 | K32: 279 | L32: PSR | M32: 2007 | O32: Yes | P32: https://dailyvoice.com/new-jersey/essex/schools/breaking-newark-archdiocese-permanently-closing-10-schools-in-three-counties/787685/ | Q32: 85 | R32: https://www.privateschoolreview.com/cristo-rey-newark-high-school-profile | S32: 2975 | T32: https://cristoreynewark.org/tuition-financial-aid-assistance/ | U32: 56.1 | V32: =IF(U32<>"",K32*U32/100,"") -> 156.519 | W32: 30.6 | X32: =IF(W32<>"",K32*W32/100,"") -> 85.374 | Y32: 1.1 | Z32: =IF(Y32<>"",K32*Y32/100,"") -> 3.069 | AA32: 1.1 | AB32: =IF(AA32<>"",K32*AA32/100,"") -> 3.069 | AC32: 11.1 | AD32: =IF(AC32<>"",K32*AC32/100,"") -> 30.969 | AE32: https://www.niche.com/k12/cristo-rey-newark-high-school-newark-nj/students/ | AF32: 239 Woodside Ave, Newark, NJ 07104 | AG32: 47451 | AH32: 2020
A33: =ROW()-1 -> 32 | B33: Incarnation Catholic School | C33: x | F33: Collierville | G33: TN | H33: South | I33: Roman Catholic | J33: 43958 | K33: 80 | L33: Media | M33: 2000 | O33: Yes | P33: https://www.wmcactionnews5.com/2020/05/08/incarnation-catholic-school-closing-due-covid-/ | S33: 6800 | T33: https://incarnationschool.edu/tuition-and-fees | U33: 2.4 | V33: =IF(U33<>"",K33*U33/100,"") -> 1.92 | W33: 8.9 | X33: =IF(W33<>"",K33*W33/100,"") -> 7.12 | Y33: 3 | Z33: =IF(Y33<>"",K33*Y33/100,"") -> 2.4 | AA33: 77.5 | AB33: =IF(AA33<>"",K33*AA33/100,"") -> 62 | AC33: 8.3 | AD33: =IF(AC33<>"",K33*AC33/100,"") -> 6.64 | AE33: https://www.niche.com/k12/incarnation-catholic-school-collierville-tn/ | AF33: 360 Bray Station Rd, Collierville, TN 38017 | AG33: 148888 | AH33: 2020
A34: =row()-1 -> 33 | B34: Academy of St. Therese of Lisieux | D34: No | F34: Cresskill | G34: NJ | H34: Northeast | I34: Roman Catholic | J34: 43958 | K34: 208 | L34: PSR | M34: 1957 | N34: Archdiocese unable to continue providing financial subsidy to the school; declining enrollment | O34: Yes | P34: https://www.northjersey.com/story/news/local/2020/05/29/cresskill-nj-st-therese-school-close-despite-efforts-save/5285659002/ | R34: https://www.privateschoolreview.com/academy-of-st-therese-of-lisiuex-profile | S34: 4380 (catholic), 5100 (non-catholic) | T34: https://scgstl.org/tuition-and-fees/ | U34: 5 | V34: =IF(U34<>"",K34*U34/100,"") -> 10.4 | W34: 2 | X34: =IF(W34<>"",K34*W34/100,"") -> 4.16 | Y34: 17 | Z34: =IF(Y34<>"",K34*Y34/100,"") -> 35.36 | AA34: 58 | AB34: =IF(AA34<>"",K34*AA34/100,"") -> 120.64 | AC34: 18 | AD34: =IF(AC34<>"",K34*AC34/100,"") -> 37.44 | AE34: https://www.greatschools.org/new-jersey/cresskill/2404-Academy-Of-St.-Therese/ | AF34: 220 Jefferson Ave, Cresskill, NJ 07626 | AG34: 150258 | AH34: 2020
A35: =row()-1 -> 34 | B35: St. Anne School | D35: No | F35: Fair Lawn | G35: NJ | H35: Northeast | I35: Roman Catholic | J35: 43958 | K35: 233 | L35: PSR | M35: 1950 | N35: shut down by the Archdiocese of Newark; financial problems exacerbated by pandemic | O35: Yes | P35: https://www.nj.com/union/2020/06/nj-catholic-school-saved-from-closure-by-donors-9-others-remain-on-shutdown-list.html | S35: 4275 | T35: https://www.privateschoolreview.com/st-anne-school-profile/07410 | U35: 9 | V35: =IF(U35<>"",K35*U35/100,"") -> 20.97 | W35: 28 | X35: =IF(W35<>"",K35*W35/100,"") -> 65.24 | Y35: 6 | Z35: =IF(Y35<>"",K35*Y35/100,"") -> 13.98 | AA35: 45 | AB35: =IF(AA35<>"",K35*AA35/100,"") -> 104.85 | AC35: 13 | AD35: =IF(AC35<>"",K35*AC35/100,"") -> 30.29 | AE35: https://www.greatschools.org/new-jersey/fair-lawn/2324-St-Anne-School/ | AF35: 1-30 Summit Ave, Fair Lawn, NJ 07410 | AG35: 123052 | AH35: 2020
A36: =row()-1 -> 35 | B36: Trinity Academy | D36: No | F36: Caldwell | G36: NJ | H36: Northeast | I36: Roman Catholic | J36: 43958 | K36: 111 | L36: Media | M36: 1991 | N36: shut down by the Archdiocese of Newark; declining enrollment | O36: Yes | P36: https://www.newjerseyhills.com/the_progress/news/update-archdiocese-to-close-trinity-academy-in-caldwell/article_96af397a-976f-5ab7-9d52-92c081226a3e.html | S36: 5,300 (member), 8,500 (non-member) | T36: http://www.schooltuitions.org/school/caldwell-nj-trinity_academy | U36: 1 | V36: =IF(U36<>"",K36*U36/100,"") -> 1.11 | W36: 4 | X36: =IF(W36<>"",K36*W36/100,"") -> 4.44 | Y36: 4 | Z36: =IF(Y36<>"",K36*Y36/100,"") -> 4.44 | AA36: 91 | AB36: =IF(AA36<>"",K36*AA36/100,"") -> 101.01 | AC36: 1 | AD36: =IF(AC36<>"",K36*AC36/100,"") -> 1.11 | AE36: https://www.greatschools.org/new-jersey/caldwell/2321-Trinity-Academy/ | AF36: 235 Bloomfield Ave, Caldwell, NJ 07006 | AG36: 128948 | AH36: 2020
A37: =row()-1 -> 36 | B37: Good Shepherd Academy | D37: No | F37: Irvington | G37: NJ | H37: Northeast | I37: Roman Catholic | J37: 43958 | K37: 187 | L37: PSR | M37: . | N37: shut down by the Archdiocese of Newark | O37: Yes | P37: https://patch.com/new-jersey/newarknj/archdiocese-closing-10-catholic-schools-new-jersey | U37: 84 | V37: =IF(U37<>"",K37*U37/100,"") -> 157.08 | W37: 5 | X37: =IF(W37<>"",K37*W37/100,"") -> 9.35 | Y37: 3 | Z37: =IF(Y37<>"",K37*Y37/100,"") -> 5.61 | AA37: 10 | AB37: =IF(AA37<>"",K37*AA37/100,"") -> 18.7 | AC37: 1 | AD37: =IF(AC37<>"",K37*AC37/100,"") -> 1.87 | AE37: https://elementaryschools.org/directory/nj/cities/irvington/good-shepherd-academy/a0902155/ | AF37: 285 Nesbit Terrace, Irvington, NJ 07111 | AG37: 56017 | AH37: 2020
A38: =row()-1 -> 37 | B38: Our Lady Help of Christians School | D38: No | F38: East Orange | G38: NJ | H38: Northeast | I38: Roman Catholic | J38: 43958 | K38: 171 | L38: Great Schools | M38: 1883 | N38: shut down by the Archdiocese of Newark; declining enrollment | O38: Yes | P38: https://www.greatschools.org/new-jersey/east-orange/2334-Our-Lady-Help-Christians-School/ | R38: https://www.linkedin.com/showcase/-saveolhc | U38: 94 | V38: =IF(U38<>"",K38*U38/100,"") -> 160.74 | W38: 4 | X38: =IF(W38<>"",K38*W38/100,"") -> 6.84 | Y38: 1 | Z38: =IF(Y38<>"",K38*Y38/100,"") -> 1.71 | AA38: 0 | AB38: =IF(AA38<>"",K38*AA38/100,"") -> 0 | AC38: 1 | AD38: =IF(AC38<>"",K38*AC38/100,"") -> 1.71 | AE38: https://www.greatschools.org/new-jersey/east-orange/2334-Our-Lady-Help-Christians-School/ | AF38: 23 N Clinton St, East Orange, NJ 07017 | AG38: 41270 | AH38: 2020
A39: =row()-1 -> 38 | B39: St. James the Apostle School | D39: No | F39: Springfield | G39: NJ | H39: Northeast | I39: Roman Catholic | J39: 43958 | K39: 178 | L39: PSR | M39: 1952 | N39: shut down by the Archdiocese of Newark | O39: Yes | P39: https://www.tapinto.net/towns/springfield/sections/religions-and-spirituality/articles/st-james-the-apostle-school-in-springfield-among-ten-being-consolidated-by-newark-archdiocese | R39: https://www.privateschoolreview.com/st-james-the-apostle-school-profile/07081 | U39: 19 | V39: =IF(U39<>"",K39*U39/100,"") -> 33.82 | W39: 12 | X39: =IF(W39<>"",K39*W39/100,"") -> 21.36 | Y39: 12 | Z39: =IF(Y39<>"",K39*Y39/100,"") -> 21.36 | AA39: 48 | AB39: =IF(AA39<>"",K39*AA39/100,"") -> 85.44 | AC39: 9 | AD39: =IF(AC39<>"",K39*AC39/100,"") -> 16.02 | AE39: https://www.greatschools.org/new-jersey/springfield-township/2436-St-James-The-Apostle-School/ | AF39: 41 S Springfield Ave, Springfield, NJ 07081 | AG39: 140362 | AH39: 2020
A40: =row()-1 -> 39 | B40: Holy Spirit School | D40: No | F40: Union | G40: NJ | H40: Northeast | I40: Roman Catholic | J40: 43958 | K40: 191 | L40: Great Schools | M40: 1965 | N40: shut down by the Archdiocese of Newark; declining enrollment | O40: Yes | P40: https://elementaryschools.org/directory/nj/cities/union/holy-spirit-school/00863486/ | R40: https://www.greatschools.org/new-jersey/union/2439-Holy-Spirit-School/ | T40: https://www.privateschoolreview.com/holy-spirit-school-profile/07083 | U40: 18 | V40: =IF(U40<>"",K40*U40/100,"") -> 34.38 | W40: 19 | X40: =IF(W40<>"",K40*W40/100,"") -> 36.29 | Y40: 12 | Z40: =IF(Y40<>"",K40*Y40/100,"") -> 22.92 | AA40: 27 | AB40: =IF(AA40<>"",K40*AA40/100,"") -> 51.57 | AC40: 24 | AD40: =IF(AC40<>"",K40*AC40/100,"") -> 45.84 | AE40: https://www.greatschools.org/new-jersey/union/2439-Holy-Spirit-School/ | AF40: 970 Suburban Rd, Union, NJ 07083 | AG40: 112736 | AH40: 2020
A41: =row()-1 -> 40 | B41: St. Genevieve School | D41: No | F41: Elizabeth | G41: NJ | H41: Northeast | I41: Roman Catholic | J41: 43958 | K41: 164 | L41: Great Schools | M41: 1926 | N41: shut down by the Archdiocese of Newark | O41: Yes | P41: https://www.greatschools.org/new-jersey/elizabeth/2409-St-Genevieve-School/ | S41: 10000 | T41: http://www.schooltuitions.org/school/elizabeth-nj-st_genevieve_school | U41: 32 | V41: =IF(U41<>"",K41*U41/100,"") -> 52.48 | W41: 32 | X41: =IF(W41<>"",K41*W41/100,"") -> 52.48 | Y41: 1 | Z41: =IF(Y41<>"",K41*Y41/100,"") -> 1.64 | AA41: 35 | AB41: =IF(AA41<>"",K41*AA41/100,"") -> 57.4 | AC41: 0 | AD41: =IF(AC41<>"",K41*AC41/100,"") -> 0 | AE41: https://www.greatschools.org/new-jersey/elizabeth/2409-St-Genevieve-School/ | AF41: 209 Princeton Rd, Elizabeth, NJ 07208 | AG41: 99949 | AH41: 2020
A42: =ROW()-1 -> 41 | B42: Junipero Serra School | C42: x | F42: Monterey | G42: CA | H42: West | I42: Roman Catholic | J42: 43959 | K42: 110 | L42: Media | M42: 1943 | O42: Yes | P42: https://kion546.com/news/2020/05/08/junipero-serra-school-to-close-permanently-after-this-school-year/ | Q42: 10 | R42: https://www.privateschoolreview.com/junipero-serra-school-profile | S42: 8000 | T42: http://stjuniperoserraschool.org/en/admissions/tuition-fees | U42: 0 | V42: =IF(U42<>"",K42*U42/100,"") -> 0 | W42: 17.6 | X42: =IF(W42<>"",K42*W42/100,"") -> 19.36 | Y42: 8.2 | Z42: =IF(Y42<>"",K42*Y42/100,"") -> 9.02 | AA42: 64.1 | AB42: =IF(AA42<>"",K42*AA42/100,"") -> 70.51 | AC42: 10.1 | AD42: =IF(AC42<>"",K42*AC42/100,"") -> 11.11 | AE42: https://www.niche.com/k12/junipero-serra-school-carmel-ca/ | AF42: 3090 Rio Road, Carmel, CA 93923 | AG42: 108740 | AH42: 2020
A43: =ROW()-1 -> 42 | B43: Saint Theresa of the Child Jesus | C43: x | F43: Hellertown | G43: PA | H43: Northeast | I43: Roman Catholic | J43: 43963 | K43: 81 | L43: Media | M43: 1940 | O43: Yes | P43: https://www.lehighvalleylive.com/news/2020/05/a-catholic-elementary-school-in-hellertown-will-close-for-good-after-80-years.html | Q43: 10 | R43: https://www.privateschoolreview.com/st-theresa-school-profile/18055 | S43: 4148 | T43: http://www.sttheresaotcj.org/tuition-and-fees | U43: 2.1 | V43: =IF(U43<>"",K43*U43/100,"") -> 1.701 | W43: 0 | X43: =IF(W43<>"",K43*W43/100,"") -> 0 | Y43: 0 | Z43: =IF(Y43<>"",K43*Y43/100,"") -> 0 | AA43: 96.5 | AB43: =IF(AA43<>"",K43*AA43/100,"") -> 78.165 | AC43: 1.4 | AD43: =IF(AC43<>"",K43*AC43/100,"") -> 1.134 | AE43: https://www.niche.com/k12/st-theresa-school-hellertown-pa/ | AF43: 300 Leonard St, Hellertown, PA 18055 | AG43: 71419 | AH43: 2020
A44: =ROW()-1 -> 43 | B44: Holy Family Catholic School | C44: x | F44: Hillcrest Heights | G44: MD | H44: South | I44: Roman Catholic | J44: 43964 | K44: 197 | L44: PSR | M44: 1957 | O44: Yes | P44: https://cathstan.org/news/local/holy-family-catholic-school-in-hillcrest-heights-to-close-at-end-of-school-year | S44: 7725 | T44: https://holyfamilymd.org/tuition-financial-aid | U44: 98.1 | V44: =IF(U44<>"",K44*U44/100,"") -> 193.257 | W44: 1.9 | X44: =IF(W44<>"",K44*W44/100,"") -> 3.743 | Y44: 0 | Z44: =IF(Y44<>"",K44*Y44/100,"") -> 0 | AA44: 0 | AB44: =IF(AA44<>"",K44*AA44/100,"") -> 0 | AC44: 0 | AD44: =IF(AC44<>"",K44*AC44/100,"") -> 0 | AE44: https://www.niche.com/k12/holy-family-catholic-school-hillcrest-heights-md/ | AF44: 2200 Callaway St, Hillcrest Heights, MD 20748 | AG44: 69261 | AH44: 2020
A45: =ROW()-1 -> 44 | B45: Most Holy Trinity Catholic School & Academy | C45: x | F45: Saint Louis | G45: MO | H45: Midwest | I45: Roman Catholic | J45: 43966 | K45: 102 | L45: PSR | O45: Yes | P45: https://www.stltoday.com/news/local/education/three-st-louis-area-catholic-grade-schools-to-close-after-budget-cuts-from-coronavirus-fallout/article_b6b92f10-d680-530c-845a-c899f315ecca.html | S45: 600 | T45: https://www.stltoday.com/news/local/education/more-non-catholic-students-are-enrolling-in-st-louis-area-catholic-schools/article_80f43f79-2f54-582c-8335-1af9bf1b07ef.html | U45: 93.2 | V45: =IF(U45<>"",K45*U45/100,"") -> 95.064 | W45: 0 | X45: =IF(W45<>"",K45*W45/100,"") -> 0 | Y45: 0 | Z45: =IF(Y45<>"",K45*Y45/100,"") -> 0 | AA45: 2.6 | AB45: =IF(AA45<>"",K45*AA45/100,"") -> 2.652 | AC45: 4.3 | AD45: =IF(AC45<>"",K45*AC45/100,"") -> 4.386 | AE45: https://www.niche.com/k12/holy-trinity-catholic-school-saint-louis-mo/ | AF45: 1435 Mallinckrodt St Saint Louis, MO 63107 | AG45: 31074 | AH45: 2020
A46: =ROW()-1 -> 45 | B46: Christ, Light of the Nations School | C46: x | F46: North County | G46: MO | H46: Midwest | I46: Roman Catholic | J46: 43966 | K46: 220 | L46: PSR | M46: 2005 | O46: Yes | P46: https://www.stltoday.com/news/local/education/three-st-louis-area-catholic-grade-schools-to-close-after-budget-cuts-from-coronavirus-fallout/article_b6b92f10-d680-530c-845a-c899f315ecca.html | U46: 71.5 | V46: =IF(U46<>"",K46*U46/100,"") -> 157.3 | W46: 1.1 | X46: =IF(W46<>"",K46*W46/100,"") -> 2.42 | Y46: 0 | Z46: =IF(Y46<>"",K46*Y46/100,"") -> 0 | AA46: 25.3 | AB46: =IF(AA46<>"",K46*AA46/100,"") -> 55.66 | AC46: 2.2 | AD46: =IF(AC46<>"",K46*AC46/100,"") -> 4.84 | AE46: https://www.niche.com/k12/christ-light-of-the-nations-catholic-school-saint-louis-mo/ | AF46: 1650 Redman Ave, St. Louis, MO 63138 | AG46: 51955 | AH46: 2020
A47: =ROW()-1 -> 46 | B47: Saint Joseph School | C47: x | F47: Manchester | G47: MO | H47: Midwest | I47: Roman Catholic | J47: 43966 | K47: 288 | L47: PSR | M47: 1960 | O47: Yes | P47: https://www.stltoday.com/news/local/education/three-st-louis-area-catholic-grade-schools-to-close-after-budget-cuts-from-coronavirus-fallout/article_b6b92f10-d680-530c-845a-c899f315ecca.html | S47: 5595 | T47: https://d2y1pz2y630308.cloudfront.net/709/documents/2019/2/K-8th_Grade_Registration_Packet_fro_FD_and_STJ_Website_for_2019-2020-1.pdf | U47: 1.2 | V47: =IF(U47<>"",K47*U47/100,"") -> 3.456 | W47: 2.8 | X47: =IF(W47<>"",K47*W47/100,"") -> 8.064 | Y47: 1.2 | Z47: =IF(Y47<>"",K47*Y47/100,"") -> 3.456 | AA47: 94.1 | AB47: =IF(AA47<>"",K47*AA47/100,"") -> 271.008 | AC47: 0.8 | AD47: =IF(AC47<>"",K47*AC47/100,"") -> 2.304 | AE47: https://www.niche.com/k12/st-joseph-elementary-school-manchester-mo/ | AF47: 555 St Josephs Ln, Ballwin, MO 63021 | AG47: 112708 | AH47: 2020
A48: =ROW()-1 -> 47 | B48: The Wilkes School at Grace and Saint Peter's | C48: x | F48: Baltimore | G48: MD | H48: South | I48: Episcopal | J48: 43967 | K48: 55 | L48: PSR | M48: 1946 | O48: Yes | P48: https://baltimore.cbslocal.com/2020/05/16/the-wilkes-school-at-grace-and-st-peters-closing-due-to-declining-enrollment/ | Q48: 30 | R48: http://wilkesschool.org/about/ | S48: 17410 | T48: http://wilkesschool.org/admissions/affording-wilkes/ | U48: 45.5 | V48: =IF(U48<>"",K48*U48/100,"") -> 25.025 | W48: 0 | X48: =IF(W48<>"",K48*W48/100,"") -> 0 | Y48: 0 | Z48: =IF(Y48<>"",K48*Y48/100,"") -> 0 | AA48: 45.5 | AB48: =IF(AA48<>"",K48*AA48/100,"") -> 25.025 | AC48: 9.1 | AD48: =IF(AC48<>"",K48*AC48/100,"") -> 5.005 | AE48: https://www.niche.com/k12/the-wilkes-school-at-grace-and-st-peters-baltimore-md/ | AF48: 707 Park Ave, Baltimore, MD 21201 | AG48: 113942 | AH48: 2020
A49: =ROW()-1 -> 48 | B49: Saint Mary's School | C49: x | F49: Pompton Lakes | G49: NJ | H49: Northeast | I49: Roman Catholic | J49: 43969 | K49: 164 | L49: Media | M49: 1952 | O49: Yes | P49: https://www.northjersey.com/story/news/passaic/pompton-lakes/2020/05/18/st-marys-school-pompton-lakes-close-amid-coronavirus-crisis/5216254002/ | S49: 5080 | T49: https://smspompton.org/about/tuition-fees/ | U49: 1.9 | V49: =IF(U49<>"",K49*U49/100,"") -> 3.116 | W49: 6.3 | X49: =IF(W49<>"",K49*W49/100,"") -> 10.332 | Y49: 9.2 | Z49: =IF(Y49<>"",K49*Y49/100,"") -> 15.088 | AA49: 78.7 | AB49: =IF(AA49<>"",K49*AA49/100,"") -> 129.068 | AC49: 3.4 | AD49: =IF(AC49<>"",K49*AC49/100,"") -> 5.576 | AE49: https://www.niche.com/k12/st-marys-school-pompton-lakes-nj/ | AF49: 19 Pompton Ave, Pompton Lakes, NJ 07442 | AG49: 111044 | AH49: 2020
A50: =ROW()-1 -> 49 | B50: Saint Peter School | C50: x | F50: South Beloit | G50: IL | H50: Midwest | I50: Roman Catholic | J50: 43971 | K50: 56 | L50: Media | M50: 1963 | O50: Yes | P50: https://www.beloitdailynews.com/news/local-news/saint-peters-school-in-south-beloit-to-close/article_ce9a8538-e96f-5411-a89c-dcc44f1c29d2.html | U50: 2.3 | V50: =IF(U50<>"",K50*U50/100,"") -> 1.288 | W50: 37.1 | X50: =IF(W50<>"",K50*W50/100,"") -> 20.776 | Y50: 0 | Z50: =IF(Y50<>"",K50*Y50/100,"") -> 0 | AA50: 57.3 | AB50: =IF(AA50<>"",K50*AA50/100,"") -> 32.088 | AC50: 3.4 | AD50: =IF(AC50<>"",K50*AC50/100,"") -> 1.904 | AE50: https://www.niche.com/k12/st-peter-catholic-school-south-beloit-il/ | AF50: 320 Elmwood Ave, South Beloit, IL 61080 | AG50: 91211 | AH50: 2020
A51: =ROW()-1 -> 50 | B51: White Mountain Waldorf School | C51: x | F51: Conway | G51: NH | H51: Northeast | I51: Independent | J51: 43971 | K51: 56 | L51: Media | M51: 1984 | O51: Yes | P51: https://www.conwaydailysun.com/business/local/white-mountain-waldorf-school-closing-after-35-years/article_99697104-a4e7-11ea-8c4f-ff536a6acf78.html | Q51: 50 | R51: https://www.privateschoolreview.com/white-mountain-waldorf-school-profile | S51: 11160 | T51: https://www.conwaydailysun.com/business/local/white-mountain-waldorf-school-closing-after-35-years/article_99697104-a4e7-11ea-8c4f-ff536a6acf78.html | U51: 1.8 | V51: =IF(U51<>"",K51*U51/100,"") -> 1.008 | W51: 0 | X51: =IF(W51<>"",K51*W51/100,"") -> 0 | Y51: 0 | Z51: =IF(Y51<>"",K51*Y51/100,"") -> 0 | AA51: 98.2 | AB51: =IF(AA51<>"",K51*AA51/100,"") -> 54.992 | AC51: 0 | AD51: =IF(AC51<>"",K51*AC51/100,"") -> 0 | AE51: https://www.niche.com/k12/white-mountain-waldorf-school-albany-nh/ | AF51: 1371 Nh Rt 16 Conway, NH 03818 | AG51: 72300 | AH51: 2020
A52: =ROW()-1 -> 51 | B52: Saint Louis School | C52: x | F52: Lowell | G52: MA | H52: Northeast | I52: Roman Catholic | J52: 43973 | K52: 200 | L52: Media | M52: 1907 | O52: Yes | P52: https://www.lowellsun.com/2020/05/22/after-over-a-century-of-education-st-louis-school-closing-in-lowell/ | S52: 4600 | T52: https://www.saintlouisschool.org/tuition-rates | U52: 19.6 | V52: =IF(U52<>"",K52*U52/100,"") -> 39.2 | W52: 7.4 | X52: =IF(W52<>"",K52*W52/100,"") -> 14.8 | Y52: 4.9 | Z52: =IF(Y52<>"",K52*Y52/100,"") -> 9.8 | AA52: 65 | AB52: =IF(AA52<>"",K52*AA52/100,"") -> 130 | AC52: 3.1 | AD52: =IF(AC52<>"",K52*AC52/100,"") -> 6.2 | AE52: https://www.niche.com/k12/st-louis-school-lowell-ma/ | AF52: 77 Boisvert St, Lowell, MA 01850 | AG52: 68072 | AH52: 2020
A53: =ROW()-1 -> 52 | B53: Holy Family Catholic School | C53: x | F53: Corpus Christi | G53: TX | H53: South | I53: Roman Catholic | J53: 43973 | K53: 113 | L53: PSR | M53: 1956 | O53: Yes | P53: https://www.caller.com/story/news/education/2020/05/27/holy-family-catholic-school-permanently-closing-corpus-christi/5265693002/ | S53: 3550 | T53: https://4.files.edl.io/8892/02/26/20/200411-1c7e6301-9637-4902-a073-a4a22b602970.pdf | U53: 0 | V53: =IF(U53<>"",K53*U53/100,"") -> 0 | W53: 100 | X53: =IF(W53<>"",K53*W53/100,"") -> 113 | Y53: 0 | Z53: =IF(Y53<>"",K53*Y53/100,"") -> 0 | AA53: 0 | AB53: =IF(AA53<>"",K53*AA53/100,"") -> 0 | AC53: 0 | AD53: =IF(AC53<>"",K53*AC53/100,"") -> 0 | AE53: https://www.niche.com/k12/holy-family-elementary-school-corpus-christi-tx/ | AF53: 2509 Nogales St, Corpus Christi, TX 78416 | AG53: 37356 | AH53: 2020
A54: =ROW()-1 -> 53 | B54: Saint Joseph Academy | C54: x | F54: Lakeland | G54: FL | H54: South | I54: Roman Catholic | J54: 43976 | K54: 185 | L54: Media | M54: 1938 | O54: Yes | P54: https://www.lkldnow.com/parents-launch-effort-to-save-historic-st-joseph-academy/ | R54: https://www.sjalakeland.org/tuition-assistance (tuition assistance link error) | S54: 7000 | T54: https://static1.squarespace.com/static/5cf7c57e54106a000186895d/t/5e53fb18a9679668e0695ba9/1582562072367/SJA+TUITION+AND+FEE+SCHEDULE+2020-2021.pdf | U54: 9.3 | V54: =IF(U54<>"",K54*U54/100,"") -> 17.205 | W54: 32.2 | X54: =IF(W54<>"",K54*W54/100,"") -> 59.57 | Y54: 4.4 | Z54: =IF(Y54<>"",K54*Y54/100,"") -> 8.14 | AA54: 48.3 | AB54: =IF(AA54<>"",K54*AA54/100,"") -> 89.355 | AC54: 5.9 | AD54: =IF(AC54<>"",K54*AC54/100,"") -> 10.915 | AE54: https://www.niche.com/k12/st-josephs-academy-lakeland-fl/ | AF54: 310 Frank Lloyd Wright Way, Lakeland, FL 33803 | AG54: 122533 | AH54: 2020
A55: =ROW()-1 -> 54 | B55: Immaculate Conception Cathedral School | C55: x | F55: Memphis | G55: TN | H55: South | I55: Roman Catholic | J55: 43977 | K55: 207 | L55: PSR | M55: 1921 | N55: 9-12 are discontinued, K-8 still open | O55: Yes | P55: https://www.localmemphis.com/article/news/education/local-cathedral-high-school-to-close-memphis-immaculate-conception/522-128f145b-9c82-42c9-8af7-847999fedfc3 | S55: 11300 | T55: http://www.myiccs.org/tuitionandfees | U55: 33.8 | V55: =IF(U55<>"",K55*U55/100,"") -> 69.966 | W55: 6.8 | X55: =IF(W55<>"",K55*W55/100,"") -> 14.076 | Y55: 4.4 | Z55: =IF(Y55<>"",K55*Y55/100,"") -> 9.108 | AA55: 48.3 | AB55: =IF(AA55<>"",K55*AA55/100,"") -> 99.981 | AC55: 6.8 | AD55: =IF(AC55<>"",K55*AC55/100,"") -> 14.076 | AE55: https://www.niche.com/k12/immaculate-conception-cathedral-school-memphis-tn/students/ | AF55: 1669 Central Ave, Memphis, TN 38104 | AG55: 120604 | AH55: 2020
A56: =ROW()-1 -> 55 | B56: The Rock Creek School | C56: x | F56: Superior | G56: CO | H56: West | I56: Independent | J56: 43978 | K56: 47 | L56: Media | M56: 2015 | N56: Kindergarden and summer program | P56: https://www.dailycamera.com/2020/05/27/private-kindergarten-summer-camp-program-closes-in-superior-because-of-coronavirus-impacts/ | V56: =IF(U56<>"",K56*U56/100,"") | X56: =IF(W56<>"",K56*W56/100,"") | Z56: =IF(Y56<>"",K56*Y56/100,"") | AB56: =IF(AA56<>"",K56*AA56/100,"") | AD56: =IF(AC56<>"",K56*AC56/100,"") | AF56: 2800 Rock Creek Cir, Superior, CO 80027 | AG56: 174469 | AH56: 2020
A57: =ROW()-1 -> 56 | B57: Quigley Catholic High School | C57: x | F57: Baden | G57: PA | H57: Northeast | I57: Roman Catholic | J57: 43980 | K57: 93 | L57: Media | M57: 1967 | O57: Yes | P57: https://www.wtae.com/article/catholic-diocese-of-pittsburgh-announces-closure-of-quigley-catholic-high-school/32714434 | S57: 9900 | T57: http://www.qchs.org/Tuition.html | U57: 2.3 | V57: =IF(U57<>"",K57*U57/100,"") -> 2.139 | W57: 2.3 | X57: =IF(W57<>"",K57*W57/100,"") -> 2.139 | Y57: 0 | Z57: =IF(Y57<>"",K57*Y57/100,"") -> 0 | AA57: 90.9 | AB57: =IF(AA57<>"",K57*AA57/100,"") -> 84.537 | AC57: 4.6 | AD57: =IF(AC57<>"",K57*AC57/100,"") -> 4.278 | AE57: https://www.niche.com/k12/quigley-catholic-high-school-baden-pa/ | AF57: 200 Quigley Dr, Baden, PA 15005 | AG57: 74226 | AH57: 2020
A58: =row()-1 -> 57 | B58: Weizmann Day School | D58: No | F58: Pasadena | G58: CA | H58: West | I58: Jewish | J58: 43981 | K58: 59 | L58: Great Schools | M58: 1983 | N58: low enrollment | O58: Yes | P58: http://www.jlifesgpv.com/weizmann-day-school/ | Q58: 40 | R58: https://www.privateschoolreview.com/chaim-weizmann-community-day-school-profile | S58: 18428 | T58: . | U58: 0 | V58: =IF(U58<>"",K58*U58/100,"") -> 0 | W58: 19 | X58: =IF(W58<>"",K58*W58/100,"") -> 11.21 | Y58: 5 | Z58: =IF(Y58<>"",K58*Y58/100,"") -> 2.95 | AA58: 76 | AB58: =IF(AA58<>"",K58*AA58/100,"") -> 44.84 | AC58: 0 | AD58: =IF(AC58<>"",K58*AC58/100,"") -> 0 | AE58: https://www.greatschools.org/california/pasadena/9620-Weizmann-Day-School/ | AF58: 1434 N Altadena Dr, Pasadena, CA 91107 | AG58: 119142 | AH58: 2020
A59: =ROW()-1 -> 58 | B59: St. Jerome School | C59: x | F59: Weymouth | G59: MA | H59: Northeast | I59: Roman Catholic | J59: 43983 | K59: 110 | L59: Media | M59: 1957 | O59: Yes | P59: https://weymouth.wickedlocal.com/news/20200601/st-jerome-elementary-school-in-north-weymouth-to-close-permanently | S59: 6000 | T59: https://7bfd6bca-f746-47e0-9499-7a09a71ce653.filesusr.com/ugd/e10742_439b57e4640e42a2a74d8973facd8888.pdf | U59: 7.1 | V59: =IF(U59<>"",K59*U59/100,"") -> 7.81 | W59: 5.9 | X59: =IF(W59<>"",K59*W59/100,"") -> 6.49 | Y59: 5.9 | Z59: =IF(Y59<>"",K59*Y59/100,"") -> 6.49 | AA59: 78.8 | AB59: =IF(AA59<>"",K59*AA59/100,"") -> 86.68 | AC59: 2.9 | AD59: =IF(AC59<>"",K59*AC59/100,"") -> 3.19 | AE59: https://www.niche.com/k12/st-jerome-elementary-school-weymouth-ma/ | AF59: 598 Bridge St, Weymouth, MA 02191 | AG59: 112358 | AH59: 2020
A60: =ROW()-1 -> 59 | B60: Good Shepherd Catholic School | C60: x | F60: Camp Hill | G60: PA | H60: Northeast | I60: Roman Catholic | J60: 43983 | K60: 82 | L60: Media | M60: 1951 | N60: Pre-K and K still open | O60: Yes | P60: https://www.abc27.com/news/local/carlisle-west-shore/good-shepherd-catholic-school-to-suspend-operations/ | S60: 4825 | T60: https://www.gsschpa.org/tuition/ | U60: 13.6 | V60: =IF(U60<>"",K60*U60/100,"") -> 11.152 | W60: 48.7 | X60: =IF(W60<>"",K60*W60/100,"") -> 39.934 | Y60: 0 | Z60: =IF(Y60<>"",K60*Y60/100,"") -> 0 | AA60: 36 | AB60: =IF(AA60<>"",K60*AA60/100,"") -> 29.52 | AC60: 1.7 | AD60: =IF(AC60<>"",K60*AC60/100,"") -> 1.394 | AE60: https://www.niche.com/k12/good-shepherd-elementary-school-camp-hill-pa/ | AF60: 3400 Market St, Camp Hill, PA 17011 | AG60: 120284 | AH60: 2020
A61: =row()-1 -> 60 | B61: St. John Paul II Stem Academy | D61: No | F61: Burbank | G61: CA | H61: West | I61: Roman Catholic | J61: 43983 | K61: 275 | L61: PSR | M61: 2019 | P61: https://lacatholics.org/archive-info/ | S61: 9350 | T61: https://www.privateschoolreview.com/st-john-paul-ii-stem-academy-profile | V61: =IF(U61<>"",K61*U61/100,"") | X61: =IF(W61<>"",K61*W61/100,"") | Z61: =IF(Y61<>"",K61*Y61/100,"") | AB61: =IF(AA61<>"",K61*AA61/100,"") | AD61: =IF(AC61<>"",K61*AC61/100,"") | AF61: 465 E. Olive Ave, Burbank, CA, 91501 | AG61: 80987 | AH61: 2020
A62: =ROW()-1 -> 61 | B62: Seashore School | C62: x | F62: Long Branch | G62: NJ | H62: Northeast | I62: Independent | J62: 43985 | K62: 100 | L62: Media | M62: 1974 | O62: Yes | P62: https://www.app.com/story/news/education/in-our-schools/2020/06/03/long-branchs-seashore-school-close-good-camp-remain-open/3123862001/ | S62: 13850 | T62: https://www.privateschoolreview.com/the-seashore-school-profile | U62: 10.1 | V62: =IF(U62<>"",K62*U62/100,"") -> 10.1 | W62: 5 | X62: =IF(W62<>"",K62*W62/100,"") -> 5 | Y62: 2.5 | Z62: =IF(Y62<>"",K62*Y62/100,"") -> 2.5 | AA62: 82.4 | AB62: =IF(AA62<>"",K62*AA62/100,"") -> 82.4 | AC62: 0 | AD62: =IF(AC62<>"",K62*AC62/100,"") -> 0 | AE62: https://www.niche.com/k12/seashore-school-long-branch-nj/ | AF62: 345 Second Ave Long Branch, NJ 07740 | AG62: 49286 | AH62: 2020
A63: =ROW()-1 -> 62 | B63: St Francis of Assisi School | C63: x | F63: Braintree | G63: MA | H63: Northeast | I63: Roman Catholic | J63: 43985 | K63: 280 | L63: PSR | M63: 1959 | O63: Yes | P63: https://braintree.wickedlocal.com/news/20200603/archdiocese-plans-to-permanently-close-braintree-catholic-school | S63: 6303 | T63: http://www.sfab.org/sfabschool/admissions/tuition/ | U63: 14.6 | V63: =IF(U63<>"",K63*U63/100,"") -> 40.88 | W63: 6.9 | X63: =IF(W63<>"",K63*W63/100,"") -> 19.32 | Y63: 19.2 | Z63: =IF(Y63<>"",K63*Y63/100,"") -> 53.76 | AA63: 45.7 | AB63: =IF(AA63<>"",K63*AA63/100,"") -> 127.96 | AC63: 13.7 | AD63: =IF(AC63<>"",K63*AC63/100,"") -> 38.36 | AE63: https://www.niche.com/k12/st-francis-of-assisi-school-braintree-ma/ | AF63: 850 Washington St, Braintree, MA 02184 | AG63: 129904 | AH63: 2020
A64: =ROW()-1 -> 63 | B64: St. Stephen School | C64: x | F64: Worcester | G64: MA | H64: Northeast | I64: Roman Catholic | J64: 43987 | K64: 112 | L64: Media | M64: 1924 | O64: Yes | P64: https://www.telegram.com/news/20200605/diocese-announces-closure-of-st-stephen-school | Q64: 20 | R64: https://www.telegram.com/news/20200605/diocese-announces-closure-of-st-stephen-school | S64: 5400 | T64: https://www.telegram.com/news/20200605/diocese-announces-closure-of-st-stephen-school | U64: 22.6 | V64: =IF(U64<>"",K64*U64/100,"") -> 25.312 | W64: 12.3 | X64: =IF(W64<>"",K64*W64/100,"") -> 13.776 | Y64: 6.9 | Z64: =IF(Y64<>"",K64*Y64/100,"") -> 7.728 | AA64: 54.1 | AB64: =IF(AA64<>"",K64*AA64/100,"") -> 60.592 | AC64: 4.1 | AD64: =IF(AC64<>"",K64*AC64/100,"") -> 4.592 | AE64: https://www.niche.com/k12/st-stephen-elementary-school-worcester-ma/ | AF64: 355 Grafton St, Worcester, MA 01604 | AG64: 44924 | AH64: 2020
A65: =ROW()-1 -> 64 | B65: St. Rose School | C65: x | F65: Chelsea | G65: MA | H65: Northeast | I65: Roman Catholic | J65: 43987 | K65: 130 | L65: Media | M65: 1871 | O65: Yes | P65: https://www.thebostonpilot.com/article.asp?ID=187792 | S65: 2650 | T65: http://strosechelsea.com/aboutus/tuition.html | U65: 8.9 | V65: =IF(U65<>"",K65*U65/100,"") -> 11.57 | W65: 65.4 | X65: =IF(W65<>"",K65*W65/100,"") -> 85.02 | Y65: 16.8 | Z65: =IF(Y65<>"",K65*Y65/100,"") -> 21.84 | AA65: 7.8 | AB65: =IF(AA65<>"",K65*AA65/100,"") -> 10.14 | AC65: 1.1 | AD65: =IF(AC65<>"",K65*AC65/100,"") -> 1.43 | AE65: https://www.niche.com/k12/st-rose-school-chelsea-ma/ | AF65: 580 Broadway, Chelsea, MA 02150 | AG65: 54098 | AH65: 2020
A66: =ROW()-1 -> 65 | B66: The Palmer School for Boys and Girls | C66: x | F66: Walnut Creek | G66: CA | H66: West | I66: Independent | J66: 43989 | K66: 385 | L66: Media | M66: 1939 | O66: No | P66: https://patch.com/california/walnutcreek/walnut-creek-school-closes-abruptly-due-coronavirus | S66: 14134 | T66: https://web.archive.org/web/20190914063225/https://www.palmerschool.org/admissions/tuition-and-fees/ | U66: 6 | V66: =IF(U66<>"",K66*U66/100,"") -> 23.1 | W66: 5.2 | X66: =IF(W66<>"",K66*W66/100,"") -> 20.02 | Y66: 16.8 | Z66: =IF(Y66<>"",K66*Y66/100,"") -> 64.68 | AA66: 53.6 | AB66: =IF(AA66<>"",K66*AA66/100,"") -> 206.36 | AC66: 18.4 | AD66: =IF(AC66<>"",K66*AC66/100,"") -> 70.84 | AE66: https://www.niche.com/k12/palmer-school-walnut-creek-ca/ | AF66: 2740 Jones Rd, Walnut Creek, CA 94597 | AG66: 148332 | AH66: 2020
A67: =ROW()-1 -> 66 | B67: Saint Francis | C67: x | F67: Pikeville | G67: KY | H67: South | I67: Roman Catholic | J67: 43990 | K67: 43 | L67: PSR | M67: 1954 | S67: 4000 | T67: https://cdlex.org/tuition-information | U67: 0 | V67: =IF(U67<>"",K67*U67/100,"") -> 0 | W67: 15.8 | X67: =IF(W67<>"",K67*W67/100,"") -> 6.794 | Y67: 5.3 | Z67: =IF(Y67<>"",K67*Y67/100,"") -> 2.279 | AA67: 68.4 | AB67: =IF(AA67<>"",K67*AA67/100,"") -> 29.412 | AC67: 10.5 | AD67: =IF(AC67<>"",K67*AC67/100,"") -> 4.515 | AE67: https://www.niche.com/k12/st-francis-of-assisi-school-pikeville-ky/ | AF67: 147 Bryan St, Pikeville, KY 41501 | AG67: 68577 | AH67: 2020
A68: =ROW()-1 -> 67 | B68: St. Mary's School | C68: x | F68: Worcester | G68: MA | H68: Northeast | I68: Roman Catholic | J68: 43990 | K68: 196 | L68: Media | M68: 1915 | O68: Yes | P68: https://www.milforddailynews.com/news/20200609/heartbroken-families-lament-closing-of-st-marys-schools-in-worcester-catholic-schools-are-working-to-place-st-marys-students | S68: 5926 | T68: http://stmarysworcester.org/tuition/ | U68: 10 | V68: =IF(U68<>"",K68*U68/100,"") -> 19.6 | W68: 3 | X68: =IF(W68<>"",K68*W68/100,"") -> 5.88 | Y68: 0 | Z68: =IF(Y68<>"",K68*Y68/100,"") -> 0 | AA68: 85 | AB68: =IF(AA68<>"",K68*AA68/100,"") -> 166.6 | AC68: 0 | AD68: =IF(AC68<>"",K68*AC68/100,"") -> 0 | AE68: https://www.niche.com/k12/st-marys-junior-senior-high-school-worcester-ma/students/ | AF68: 50 Richland St, Worcester, MA 01610 | AG68: 41560 | AH68: 2020
A69: =ROW()-1 -> 68 | B69: The Paragon School | C69: x | F69: Orlando | G69: FL | H69: South | I69: Special needs | J69: 43992 | K69: 106 | L69: Media | M69: 2007 | O69: No | P69: https://www.redefinedonline.org/2020/06/pandemic-forces-closure-of-florida-private-school-for-students-with-autism/ | S69: 20500 | T69: https://www.paragonschool.org/admissions/tuition-fees | U69: 7.8 | V69: =IF(U69<>"",K69*U69/100,"") -> 8.268 | W69: 18.8 | X69: =IF(W69<>"",K69*W69/100,"") -> 19.928 | Y69: 6.3 | Z69: =IF(Y69<>"",K69*Y69/100,"") -> 6.678 | AA69: 54.7 | AB69: =IF(AA69<>"",K69*AA69/100,"") -> 57.982 | AC69: 12.5 | AD69: =IF(AC69<>"",K69*AC69/100,"") -> 13.25 | AE69: https://www.niche.com/k12/the-paragon-school-orlando-fl/ | AF69: 4710 Adanson Street, Orlando, FL 32804 | AG69: 77430 | AH69: 2020
A70: =ROW()-1 -> 69 | B70: Sacred Heart School | C70: x | F70: Bath | G70: PA | H70: Northeast | I70: Roman Catholic | J70: 43992 | K70: 60 | L70: Media | M70: 1925 | O70: Yes | P70: https://www.mcall.com/coronavirus/mc-nws-coronavirus-bath-bally-catholic-schools-closing-20200610-2jk7yhhf7rgknn5lbkhloh62qe-story.html | S70: 3500 | T70: https://www.sacred-heart-school.com/tuition-fees/ | U70: 0 | V70: =IF(U70<>"",K70*U70/100,"") -> 0 | W70: 2.6 | X70: =IF(W70<>"",K70*W70/100,"") -> 1.56 | Y70: 1.6 | Z70: =IF(Y70<>"",K70*Y70/100,"") -> 0.96 | AA70: 93.8 | AB70: =IF(AA70<>"",K70*AA70/100,"") -> 56.28 | AC70: 2.1 | AD70: =IF(AC70<>"",K70*AC70/100,"") -> 1.26 | AE70: https://www.niche.com/k12/st-francis-academy-bally-pa/ | AF70: 115 Washington St, Bath, PA 18014 | AG70: 58764 | AH70: 2020
A71: =ROW()-1 -> 70 | B71: St. Francis Academy | C71: x | F71: Bally | G71: PA | H71: Northeast | I71: Roman Catholic | J71: 43992 | K71: 75 | L71: Media | M71: 1743 | N71: Pre-K and K programs continuing | O71: Yes | P71: https://www.mcall.com/coronavirus/mc-nws-coronavirus-bath-bally-catholic-schools-closing-20200610-2jk7yhhf7rgknn5lbkhloh62qe-story.html | S71: 3595 | T71: https://d2y1pz2y630308.cloudfront.net/22567/documents/2019/9/SFA%20Tuition%20FACTS%20-%202019-2020-1.pdf | U71: 1.9 | V71: =IF(U71<>"",K71*U71/100,"") -> 1.425 | W71: 0 | X71: =IF(W71<>"",K71*W71/100,"") -> 0 | Y71: 0 | Z71: =IF(Y71<>"",K71*Y71/100,"") -> 0 | AA71: 98.1 | AB71: =IF(AA71<>"",K71*AA71/100,"") -> 73.575 | AC71: 0 | AD71: =IF(AC71<>"",K71*AC71/100,"") -> 0 | AE71: https://www.niche.com/k12/sacred-heart-of-jesus-parish-school-bath-pa/ | AF71: 668 Pine St, Bally, PA 19503 | AG71: 83764 | AH71: 2020
A72: =ROW()-1 -> 71 | B72: St. Patrick School | C72: x | F72: Canonsburg | G72: PA | H72: Northeast | I72: Roman Catholic | J72: 43994 | K72: 106 | L72: Media | M72: 1954 | O72: Yes | P72: https://observer-reporter.com/news/localnews/st-patrick-school-in-canonsburg-is-closing/article_a9dcd79a-ace6-11ea-89a8-4744a4305ddf.html | S72: 4000 | T72: https://saintpatsschool.org/tuition-financial-assistance | U72: 3 | V72: =IF(U72<>"",K72*U72/100,"") -> 3.18 | W72: 3.6 | X72: =IF(W72<>"",K72*W72/100,"") -> 3.816 | Y72: 0 | Z72: =IF(Y72<>"",K72*Y72/100,"") -> 0 | AA72: 92.3 | AB72: =IF(AA72<>"",K72*AA72/100,"") -> 97.838 | AC72: 1.2 | AD72: =IF(AC72<>"",K72*AC72/100,"") -> 1.272 | AE72: https://www.niche.com/k12/st-patrick-school-canonsburg-pa/ | AF72: 200 Murdock St, Canonsburg, PA 15317 | AG72: 64935 | AH72: 2020
A73: =ROW()-1 -> 72 | B73: Our Lady of the Most Blessed Sacrament School | C73: x | F73: Natrona Heights | G73: PA | H73: Northeast | I73: Roman Catholic | J73: 43994 | K73: 85 | L73: Media | M73: 1954 | O73: Yes | P73: https://triblive.com/local/valley-news-dispatch/blessed-sacrament-school-in-natrona-heights-to-be-closed-by-pittsburgh-diocese/ | U73: 1.5 | V73: =IF(U73<>"",K73*U73/100,"") -> 1.275 | W73: 0.5 | X73: =IF(W73<>"",K73*W73/100,"") -> 0.425 | Y73: 1 | Z73: =IF(Y73<>"",K73*Y73/100,"") -> 0.85 | AA73: 96.6 | AB73: =IF(AA73<>"",K73*AA73/100,"") -> 82.11 | AC73: 0.5 | AD73: =IF(AC73<>"",K73*AC73/100,"") -> 0.425 | AE73: https://www.niche.com/k12/our-lady-of-the-most-blessed-sacrament-school-natrona-heights-pa/ | AF73: 800 Montana Ave, Natrona Heights, PA 15065 | AG73: 39109 | AH73: 2020
A74: =ROW()-1 -> 73 | B74: Saint John the Baptist Catholic School | C74: x | F74: Honolulu | G74: HI | H74: West | I74: Roman Catholic | J74: 43994 | K74: 55 | L74: Media | M74: 1959 | O74: Yes | P74: https://www.asumag.com/facilities-management/article/21134419/catholic-school-in-honolulu-is-closing-after-60-years | S74: 6290 | T74: https://www.hais.us/Customized/Uploads/ByDate/2019/July_2019/July_31st_2019/19-20%20Tuition%20Report50601.pdf | U74: 0.6 | V74: =IF(U74<>"",K74*U74/100,"") -> 0.33 | W74: 0.6 | X74: =IF(W74<>"",K74*W74/100,"") -> 0.33 | Y74: 89.9 | Z74: =IF(Y74<>"",K74*Y74/100,"") -> 49.445 | AA74: 2.5 | AB74: =IF(AA74<>"",K74*AA74/100,"") -> 1.375 | AC74: 6.3 | AD74: =IF(AC74<>"",K74*AC74/100,"") -> 3.465 | AE74: https://www.niche.com/k12/st-john-the-baptist-catholic-school-honolulu-hi/ | AF74: 2340 Omilo Ln, Honolulu, HI 96819 | AG74: 70521 | AH74: 2020
A75: =ROW()-1 -> 74 | B75: Saint Joseph Elementary School | C75: x | D75: no | F75: Verona | G75: PA | H75: Northeast | I75: Roman Catholic | J75: 43994 | K75: 135 | L75: NCES | M75: 1898 | N75: Merging with Saint John the Baptist School | O75: Yes | P75: https://pittsburgh.cbslocal.com/2020/06/12/diocese-of-pittsburgh-announces-closure-of-two-elementary-schools-merger-of-two-elementary-schools/ | S75: 4385 | T75: https://stjoeschool.opvcatholic.org/tuition | U75: 1.3 | V75: =IF(U75<>"",K75*U75/100,"") -> 1.755 | W75: 1.3 | X75: =IF(W75<>"",K75*W75/100,"") -> 1.755 | Y75: 2.6 | Z75: =IF(Y75<>"",K75*Y75/100,"") -> 3.51 | AA75: 91 | AB75: =IF(AA75<>"",K75*AA75/100,"") -> 122.85 | AC75: 3.9 | AD75: =IF(AC75<>"",K75*AC75/100,"") -> 5.265 | AE75: https://www.niche.com/k12/st-joseph-school---verona-verona-pa/ | AF75: 825 2nd St, Verona, PA 15147 | AG75: 61100 | AH75: 2020
A76: =ROW()-1 -> 75 | B76: Holy Family Catholic School | C76: x | F76: Moss Bluff | G76: LA | H76: South | I76: Roman Catholic | J76: 43995 | K76: 89 | L76: Media | O76: Yes | P76: https://www.americanpress.com/news/holy-family-school-in-moss-bluff-closing/article_a2003458-8be5-581b-bf9a-3103afd7275e.html | S76: 5046 | T76: https://d2y1pz2y630308.cloudfront.net/21711/documents/2019/2/Registration%20Fee%202019-2020-1.pdf | U76: 8 | V76: =IF(U76<>"",K76*U76/100,"") -> 7.12 | W76: 1.6 | X76: =IF(W76<>"",K76*W76/100,"") -> 1.424 | Y76: 0.8 | Z76: =IF(Y76<>"",K76*Y76/100,"") -> 0.712 | AA76: 85.6 | AB76: =IF(AA76<>"",K76*AA76/100,"") -> 76.184 | AC76: 4 | AD76: =IF(AC76<>"",K76*AC76/100,"") -> 3.56 | AE76: https://www.niche.com/k12/st-theodore-holy-family-catholic-school-lake-charles-la/ | AF76: 785 Sam Houston Jones Pkwy, Lake Charles, LA 70611 | AG76: 84337 | AH76: 2020
A77: =ROW()-1 -> 76 | B77: Middleburg Academy | C77: x | F77: Middleburg | G77: VA | H77: South | I77: Independent | J77: 43999 | K77: 130 | L77: PSR | M77: 1965 | O77: Yes | P77: https://www.loudountimes.com/news/middleburg-academy-to-close-its-doors/article_d323aa1a-b09d-11ea-8d1c-87e10516c30a.html | S77: 25985 | T77: http://www.middleburgacademy.org/affordability-tuition | U77: 15.4 | V77: =IF(U77<>"",K77*U77/100,"") -> 20.02 | W77: 3.8 | X77: =IF(W77<>"",K77*W77/100,"") -> 4.94 | Y77: 15.4 | Z77: =IF(Y77<>"",K77*Y77/100,"") -> 20.02 | AA77: 61.5 | AB77: =IF(AA77<>"",K77*AA77/100,"") -> 79.95 | AC77: 3.8 | AD77: =IF(AC77<>"",K77*AC77/100,"") -> 4.94 | AE77: https://www.niche.com/k12/middleburg-academy-middleburg-va/students/ | AF77: 35321 Notre Dame Ln, Middleburg, VA 20117 | AG77: 166109 | AH77: 2020
A78: =ROW()-1 -> 77 | B78: Blessed Sacrament School | C78: x | F78: Midland | G78: MI | H78: Midwest | I78: Roman Catholic | J78: 44000 | K78: 60 | L78: Media | M78: 1955 | O78: Yes | P78: https://www.ourmidland.com/news/article/Blessed-Sacrament-School-closes-after-65-15347571.php | S78: 0 | T78: https://www.ourmidland.com/news/article/Blessed-Sacrament-School-closes-after-65-15347571.php | U78: 0 | V78: =IF(U78<>"",K78*U78/100,"") -> 0 | W78: 2.9 | X78: =IF(W78<>"",K78*W78/100,"") -> 1.74 | Y78: 1 | Z78: =IF(Y78<>"",K78*Y78/100,"") -> 0.6 | AA78: 95.1 | AB78: =IF(AA78<>"",K78*AA78/100,"") -> 57.06 | AC78: 1 | AD78: =IF(AC78<>"",K78*AC78/100,"") -> 0.6 | AE78: https://www.niche.com/k12/blessed-sacrament-elementary-school-midland-mi/ | AF78: 3109 Swede Ave, Midland, MI 48642 | AG78: 91982 | AH78: 2020
A79: =ROW()-1 -> 78 | B79: Holy Family Regional School | C79: x | F79: Commack | G79: NY | H79: Northeast | I79: Roman Catholic | J79: 44001 | K79: 139 | L79: Media | O79: Yes | P79: https://www.newsday.com/long-island/religion/catholic-schools-closures-long-island-coronavirus-covid19-1.45896546 | S79: 6108 | T79: https://holyfamilyregional.com/tuition | U79: 7 | V79: =IF(U79<>"",K79*U79/100,"") -> 9.73 | W79: 9.4 | X79: =IF(W79<>"",K79*W79/100,"") -> 13.066 | Y79: 1.9 | Z79: =IF(Y79<>"",K79*Y79/100,"") -> 2.641 | AA79: 80.3 | AB79: =IF(AA79<>"",K79*AA79/100,"") -> 111.617 | AC79: 1.4 | AD79: =IF(AC79<>"",K79*AC79/100,"") -> 1.946 | AE79: https://www.niche.com/k12/holy-family-regional-school-commack-ny/ | AF79: 2 Indian Head Rd, Commack, NY 11725 | AG79: 175075 | AH79: 2020
A80: =ROW()-1 -> 79 | B80: Our Lady of Wisdom Regional School | C80: x | F80: Port Jefferson | G80: NY | H80: Northeast | I80: Roman Catholic | J80: 44001 | K80: 66 | L80: Media | M80: 1938 | O80: Yes | P80: https://www.newsday.com/long-island/religion/catholic-schools-closures-long-island-coronavirus-covid19-1.45896546 | S80: 5846 | T80: https://olowregional.org/tuition-and-financial-aid | U80: 3.7 | V80: =IF(U80<>"",K80*U80/100,"") -> 2.442 | W80: 9.3 | X80: =IF(W80<>"",K80*W80/100,"") -> 6.138 | Y80: 3.7 | Z80: =IF(Y80<>"",K80*Y80/100,"") -> 2.442 | AA80: 79.6 | AB80: =IF(AA80<>"",K80*AA80/100,"") -> 52.536 | AC80: 3.8 | AD80: =IF(AC80<>"",K80*AC80/100,"") -> 2.508 | AE80: https://www.niche.com/k12/our-lady-of-wisdom-regional-school-port-jefferson-ny/ | AF80: 114-116 Myrtle Ave, Port Jefferson, NY 11777 | AG80: 158415 | AH80: 2020
A81: =ROW()-1 -> 80 | B81: Saint Peter of Alcantara Elementary School | C81: x | F81: Port Washington | G81: NY | H81: Northeast | I81: Roman Catholic | J81: 44001 | K81: 99 | L81: Media | M81: 1925 | O81: Yes | P81: https://www.newsday.com/long-island/religion/catholic-schools-closures-long-island-coronavirus-covid19-1.45896546 | U81: 1.1 | V81: =IF(U81<>"",K81*U81/100,"") -> 1.089 | W81: 0 | X81: =IF(W81<>"",K81*W81/100,"") -> 0 | Y81: 6.8 | Z81: =IF(Y81<>"",K81*Y81/100,"") -> 6.732 | AA81: 90 | AB81: =IF(AA81<>"",K81*AA81/100,"") -> 89.1 | AC81: 2.1 | AD81: =IF(AC81<>"",K81*AC81/100,"") -> 2.079 | AE81: https://www.niche.com/k12/st-peter-of-alcantara-school-port-washington-ny/ | AF81: 1321 Port Washington Blvd, Port Washington, NY 11050 | AG81: 214359 | AH81: 2020
A82: =ROW()-1 -> 81 | B82: Our Lady of Perpetual Help | C82: x | F82: Ewa Beach | G82: HI | H82: West | I82: Roman Catholic | J82: 44006 | K82: 150 | L82: Media | M82: 1967 | O82: Yes | P82: https://www.hawaiicatholicherald.com/2020/06/24/covid-stress-closes-kalihi-and-ewa-beach-catholic-schools/ | S82: 6600 | T82: https://www.hawaiicatholicherald.com/2020/06/24/covid-stress-closes-kalihi-and-ewa-beach-catholic-schools/ | U82: 0 | V82: =IF(U82<>"",K82*U82/100,"") -> 0 | W82: 4.6 | X82: =IF(W82<>"",K82*W82/100,"") -> 6.9 | Y82: 48.6 | Z82: =IF(Y82<>"",K82*Y82/100,"") -> 72.9 | AA82: 11 | AB82: =IF(AA82<>"",K82*AA82/100,"") -> 16.5 | AC82: 35.9 | AD82: =IF(AC82<>"",K82*AC82/100,"") -> 53.85 | AE82: https://www.niche.com/k12/our-lady-of-perpetual-help-school-ewa-beach-hi/ | AF82: 91-1010 N Rd, Ewa Beach, HI 96706 | AG82: 89388 | AH82: 2020
A83: =ROW()-1 -> 82 | B83: The Jefferson School and Residential Center | C83: x | F83: Frederick | G83: MD | H83: South | I83: Special needs | J83: 44006 | K83: 82 | L83: PSR | N83: Faced legal problems from sexual abuse in addition to financial. Special education and mental health school for 12-18 year olds | O83: Yes | P83: https://www.bizjournals.com/baltimore/news/2020/06/25/sheppard-pratt-to-close-jefferson-school-maryland.html | U83: 36 | V83: =IF(U83<>"",K83*U83/100,"") -> 29.52 | W83: 8 | X83: =IF(W83<>"",K83*W83/100,"") -> 6.56 | Y83: 1 | Z83: =IF(Y83<>"",K83*Y83/100,"") -> 0.82 | AA83: 50 | AB83: =IF(AA83<>"",K83*AA83/100,"") -> 41 | AC83: 5 | AD83: =IF(AC83<>"",K83*AC83/100,"") -> 4.1 | AE83: https://www.greatschools.org/maryland/jefferson/1862-The-Jefferson-School/ | AF83: 2940 Point of Rocks Rd, Jefferson, MD 21755 | AG83: 123492 | AH83: 2020
A84: =ROW()-1 -> 83 | B84: Sacred Heart School | C84: x | F84: Oxford | G84: PA | H84: Northeast | I84: Roman Catholic | J84: 44011 | K84: 52 | L84: Media | M84: 2002 | O84: Yes | P84: https://catholicphilly.com/2020/06/news/local-news/two-chester-county-catholic-schools-wont-reopen-in-fall/ | S84: 4950 | T84: https://shsoxford.us/tuition | U84: 1.3 | V84: =IF(U84<>"",K84*U84/100,"") -> 0.676 | W84: 8.8 | X84: =IF(W84<>"",K84*W84/100,"") -> 4.576 | Y84: 0 | Z84: =IF(Y84<>"",K84*Y84/100,"") -> 0 | AA84: 90 | AB84: =IF(AA84<>"",K84*AA84/100,"") -> 46.8 | AC84: 0 | AD84: =IF(AC84<>"",K84*AC84/100,"") -> 0 | AE84: https://www.niche.com/k12/sacred-heart-school-oxford-pa/ | AF84: 205 Church Rd, Oxford, PA 19363 | AG84: 85987 | AH84: 2020
A85: =ROW()-1 -> 84 | B85: St Thomas Aquinas School | C85: x | F85: Derry | G85: NH | H85: Northeast | I85: Roman Catholic | J85: 44013 | K85: 71 | L85: Media | M85: 1954 | O85: Yes | P85: https://www.eagletribune.com/news/new_hampshire/st-thomas-aquinas-school-in-derry-to-close-for-good/article_2a9527f9-298a-5a67-a49b-f9e1c2a8c9bb.html | S85: 5370 | T85: https://www.staderry.com/copy-of-tuition | U85: 0.6 | V85: =IF(U85<>"",K85*U85/100,"") -> 0.426 | W85: 0.6 | X85: =IF(W85<>"",K85*W85/100,"") -> 0.426 | Y85: 0 | Z85: =IF(Y85<>"",K85*Y85/100,"") -> 0 | AA85: 94.7 | AB85: =IF(AA85<>"",K85*AA85/100,"") -> 67.237 | AC85: 4.1 | AD85: =IF(AC85<>"",K85*AC85/100,"") -> 2.911 | AE85: https://www.niche.com/k12/st-thomas-aquinas-school-derry-nh/ | AF85: 3 Moody St, Derry, NH 03038 | AG85: 64109 | AH85: 2020
A86: =ROW()-1 -> 85 | B86: St. Cornelius Catholic School | C86: x | D86: no | F86: Richmond | G86: CA | H86: West | I86: Roman Catholic | J86: 44018 | K86: 140 | L86: Media | M86: 1948 | O86: Yes | P86: https://richmondstandard.com/richmond/2020/07/07/diocese-to-close-72-year-old-catholic-school-in-richmond/ | S86: 5885 | T86: https://www.privateschoolreview.com/st-cornelius-school-profile | U86: 6 | V86: =IF(U86<>"",K86*U86/100,"") -> 8.4 | W86: 91 | X86: =IF(W86<>"",K86*W86/100,"") -> 127.4 | Y86: 1 | Z86: =IF(Y86<>"",K86*Y86/100,"") -> 1.4 | AA86: 0 | AB86: =IF(AA86<>"",K86*AA86/100,"") -> 0 | AC86: 2 | AD86: =IF(AC86<>"",K86*AC86/100,"") -> 2.8 | AE86: https://www.greatschools.org/california/richmond/8242-St.-Cornelius-Elementary-School/ | AF86: 201 28th St, Richmond, CA 94804 | AG86: 58754 | AH86: 2020
A87: =ROW()-1 -> 86 | B87: All Saints School | C87: x | D87: no | F87: Los Angeles | G87: CA | H87: West | I87: Roman Catholic | J87: 44018 | K87: 116 | L87: PSR | M87: 1948 | O87: Yes | P87: http://www.allsaintsla.com/ministries/all-saints-school | U87: 0 | V87: =IF(U87<>"",K87*U87/100,"") -> 0 | W87: 100 | X87: =IF(W87<>"",K87*W87/100,"") -> 116 | Y87: 0 | Z87: =IF(Y87<>"",K87*Y87/100,"") -> 0 | AA87: 0 | AB87: =IF(AA87<>"",K87*AA87/100,"") -> 0 | AC87: 0 | AD87: =IF(AC87<>"",K87*AC87/100,"") -> 0 | AE87: https://www.niche.com/k12/all-saints-catholic-school-los-angeles-ca/ | AF87: 3420 Portola Ave, Los Angeles, CA 90032 | AG87: 46194 | AH87: 2020
A88: =ROW()-1 -> 87 | B88: Corpus Christi School | C88: x | F88: Manhattan | G88: NY | H88: Northeast | I88: Roman Catholic | J88: 44021 | K88: 175 | L88: School Website | O88: Yes | P88: https://wcbs880.radio.com/articles/news/ny-archdiocese-closing-20-catholic-schools | S88: 7000 | T88: https://ccschoolnyc.org/documents/2020/1/11086-Corpus%20Christi%20NYC%20Tuition%20and%20Fees%20Rate%20Sheet.pdf | U88: 15.8 | V88: =IF(U88<>"",K88*U88/100,"") -> 27.65 | W88: 48.9 | X88: =IF(W88<>"",K88*W88/100,"") -> 85.575 | Y88: 3.6 | Z88: =IF(Y88<>"",K88*Y88/100,"") -> 6.3 | AA88: 19.4 | AB88: =IF(AA88<>"",K88*AA88/100,"") -> 33.95 | AC88: 12.2 | AD88: =IF(AC88<>"",K88*AC88/100,"") -> 21.35 | AE88: https://www.niche.com/k12/corpus-christi-school-new-york-ny/ | AF88: 533 W 121st St, New York, NY 10027 | AG88: 64966 | AH88: 2020
A89: =ROW()-1 -> 88 | B89: Divine Mercy School | C89: x | F89: New Windsor | G89: NY | H89: Northeast | I89: Roman Catholic | J89: 44021 | K89: 135 | L89: School Website | M89: 1954 | O89: Yes | P89: https://wcbs880.radio.com/articles/news/ny-archdiocese-closing-20-catholic-schools | S89: 5200 | T89: https://divinemercynewwindsor.org/documents/2020/1/11118-Divine%20Mercy%20Tuition%20and%20Fees%20Rate%20Sheet%20with%20English%20and%20Spanish%20sheets.pdf | U89: 4.4 | V89: =IF(U89<>"",K89*U89/100,"") -> 5.94 | W89: 59 | X89: =IF(W89<>"",K89*W89/100,"") -> 79.65 | Y89: 6.3 | Z89: =IF(Y89<>"",K89*Y89/100,"") -> 8.505 | AA89: 30.2 | AB89: =IF(AA89<>"",K89*AA89/100,"") -> 40.77 | AC89: 0 | AD89: =IF(AC89<>"",K89*AC89/100,"") -> 0 | AE89: https://www.niche.com/k12/divine-mercy-catholic-academy-ozone-park-ny/ | AF89: 148 Windsor Hwy, New Windsor, NY 12553 | AG89: 130942 | AH89: 2020
A90: =ROW()-1 -> 89 | B90: Holy Family School | C90: x | F90: New Rochelle | G90: NY | H90: Northeast | I90: Roman Catholic | J90: 44021 | K90: 136 | L90: School Website | M90: 1921 | O90: Yes | P90: https://wcbs880.radio.com/articles/news/ny-archdiocese-closing-20-catholic-schools | S90: 6275 | T90: https://holyfamilynewrochelle.org/tuition-and-fees | V90: =IF(U90<>"",K90*U90/100,"") | X90: =IF(W90<>"",K90*W90/100,"") | Z90: =IF(Y90<>"",K90*Y90/100,"") | AB90: =IF(AA90<>"",K90*AA90/100,"") | AD90: =IF(AC90<>"",K90*AC90/100,"") | AE90: https://www.greatschools.org/new-york/new-rochelle/4458-Holy-Family-School/ | AF90: 100 Mt Joy Pl, New Rochelle, NY 10801 | AG90: 157211 | AH90: 2020
A91: =ROW()-1 -> 90 | B91: Nativity of Our Blessed Lady School | C91: x | F91: The Bronx | G91: NY | H91: Northeast | I91: Roman Catholic | J91: 44021 | K91: 200 | L91: School Website | M91: 1954 | O91: Yes | P91: https://wcbs880.radio.com/articles/news/ny-archdiocese-closing-20-catholic-schools | S91: 6130 | T91: https://nativityofourblessedlady.org/tuition-fees | U91: 81.1 | V91: =IF(U91<>"",K91*U91/100,"") -> 162.2 | W91: 14.6 | X91: =IF(W91<>"",K91*W91/100,"") -> 29.2 | Y91: 0 | Z91: =IF(Y91<>"",K91*Y91/100,"") -> 0 | AA91: 0.6 | AB91: =IF(AA91<>"",K91*AA91/100,"") -> 1.2 | AC91: 3.7 | AD91: =IF(AC91<>"",K91*AC91/100,"") -> 7.4 | AE91: https://www.niche.com/k12/nativity-of-our-blessed-lady-school-bronx-ny/ | AF91: 1531 E 233rd St, The Bronx, NY 10466 | AG91: 95043 | AH91: 2020
A92: =ROW()-1 -> 91 | B92: Our Lady of Mt. Carmel-St. Benedicta School | C92: x | F92: Staten Island | G92: NY | H92: Northeast | I92: Roman Catholic | J92: 44021 | K92: 174 | L92: PSR | M92: 1959 | O92: Yes | P92: https://wcbs880.radio.com/articles/news/ny-archdiocese-closing-20-catholic-schools | S92: 5650 | T92: https://olmcsb.org/tuition-amp-fees | U92: 27.9 | V92: =IF(U92<>"",K92*U92/100,"") -> 48.546 | W92: 70.1 | X92: =IF(W92<>"",K92*W92/100,"") -> 121.974 | Y92: 1.3 | Z92: =IF(Y92<>"",K92*Y92/100,"") -> 2.262 | AA92: 0.7 | AB92: =IF(AA92<>"",K92*AA92/100,"") -> 1.218 | AC92: 0 | AD92: =IF(AC92<>"",K92*AC92/100,"") -> 0 | AE92: https://www.niche.com/k12/our-lady-of-mt-carmel-st-benedicta-school-staten-island-ny/ | AF92: 285 Clove Rd, Staten Island, NY 10310 | AG92: 69154 | AH92: 2020
A93: =ROW()-1 -> 92 | B93: Our Lady of Perpetual Help School | C93: x | F93: Pelham | G93: NY | H93: Northeast | I93: Roman Catholic | J93: 44021 | K93: 189 | L93: PSR | M93: 1958 | O93: Yes | P93: https://wcbs880.radio.com/articles/news/ny-archdiocese-closing-20-catholic-schools | S93: 6200 | T93: https://www.olphpelham.com/files/OLPH_PS_Handbook_17-18.pdf | U93: 40.1 | V93: =IF(U93<>"",K93*U93/100,"") -> 75.789 | W93: 17.2 | X93: =IF(W93<>"",K93*W93/100,"") -> 32.508 | Y93: 5.1 | Z93: =IF(Y93<>"",K93*Y93/100,"") -> 9.639 | AA93: 26.8 | AB93: =IF(AA93<>"",K93*AA93/100,"") -> 50.652 | AC93: 10.8 | AD93: =IF(AC93<>"",K93*AC93/100,"") -> 20.412 | AE93: https://www.niche.com/k12/our-lady-of-perpetual-help-school-pelham-ny/ | AF93: 575 Fowler Ave, Pelham, NY 10803 | AG93: 246619 | AH93: 2020
A94: =ROW()-1 -> 93 | B94: Our Lady of Pompeii School | C94: x | F94: Manhattan | G94: NY | H94: Northeast | I94: Roman Catholic | J94: 44021 | K94: 130 | L94: School Website | M94: 1930 | O94: Yes | P94: https://wcbs880.radio.com/articles/news/ny-archdiocese-closing-20-catholic-schools | S94: 8100 | T94: https://ourladyofpompeii.nyc/tuition-amp-fees | U94: 8 | V94: =IF(U94<>"",K94*U94/100,"") -> 10.4 | W94: 14.2 | X94: =IF(W94<>"",K94*W94/100,"") -> 18.46 | Y94: 7.4 | Z94: =IF(Y94<>"",K94*Y94/100,"") -> 9.62 | AA94: 64.8 | AB94: =IF(AA94<>"",K94*AA94/100,"") -> 84.24 | AC94: 5.6 | AD94: =IF(AC94<>"",K94*AC94/100,"") -> 7.28 | AE94: https://www.niche.com/k12/our-lady-of-pompeii-school-new-york-ny/ | AF94: 240 Bleecker St, New York, NY 10014 | AG94: 231469 | AH94: 2020
A95: =ROW()-1 -> 94 | B95: Our Lady of the Assumption School | C95: x | F95: The Bronx | G95: NY | H95: Northeast | I95: Roman Catholic | J95: 44021 | K95: 240 | L95: School Website | O95: Yes | P95: https://wcbs880.radio.com/articles/news/ny-archdiocese-closing-20-catholic-schools | S95: 6285 | T95: https://olassumptionbronx.org/tuition-amp-fees | U95: 3.7 | V95: =IF(U95<>"",K95*U95/100,"") -> 8.88 | W95: 41.6 | X95: =IF(W95<>"",K95*W95/100,"") -> 99.84 | Y95: 2.8 | Z95: =IF(Y95<>"",K95*Y95/100,"") -> 6.72 | AA95: 33.6 | AB95: =IF(AA95<>"",K95*AA95/100,"") -> 80.64 | AC95: 18.3 | AD95: =IF(AC95<>"",K95*AC95/100,"") -> 43.92 | AE95: https://www.niche.com/k12/our-lady-of-the-assumption-school-bronx-ny/ | AF95: 1617 Parkview Ave, The Bronx, NY 10461 | AG95: 51100 | AH95: 2020
A96: =ROW()-1 -> 95 | B96: Sacred Heart School | C96: x | F96: Suffern | G96: NY | H96: Northeast | I96: Roman Catholic | J96: 44021 | K96: 269 | L96: School Website | M96: 1911 | O96: Yes | P96: https://wcbs880.radio.com/articles/news/ny-archdiocese-closing-20-catholic-schools | S96: 6350 | T96: https://sacredheartschoolsuffern.com/tuition-amp-fees | U96: 39.1 | V96: =IF(U96<>"",K96*U96/100,"") -> 105.179 | W96: 16.7 | X96: =IF(W96<>"",K96*W96/100,"") -> 44.923 | Y96: 9.3 | Z96: =IF(Y96<>"",K96*Y96/100,"") -> 25.017 | AA96: 32.6 | AB96: =IF(AA96<>"",K96*AA96/100,"") -> 87.694 | AC96: 2.3 | AD96: =IF(AC96<>"",K96*AC96/100,"") -> 6.187 | AE96: https://www.niche.com/k12/sacred-heart-school-suffern-ny/ | AF96: 60 Washington Ave, Suffern, NY 10901 | AG96: 123215 | AH96: 2020
A97: =ROW()-1 -> 96 | B97: St. Ann School | C97: x | F97: Yonkers | G97: NY | H97: Northeast | I97: Roman Catholic | J97: 44021 | K97: 191 | L97: PSR | O97: Yes | P97: https://wcbs880.radio.com/articles/news/ny-archdiocese-closing-20-catholic-schools | S97: 6500 | T97: https://stannschoolyonkers.org/tuition-amp-fees | U97: 2.5 | V97: =IF(U97<>"",K97*U97/100,"") -> 4.775 | W97: 11.7 | X97: =IF(W97<>"",K97*W97/100,"") -> 22.347 | Y97: 3.1 | Z97: =IF(Y97<>"",K97*Y97/100,"") -> 5.921 | AA97: 74.9 | AB97: =IF(AA97<>"",K97*AA97/100,"") -> 143.059 | AC97: 8 | AD97: =IF(AC97<>"",K97*AC97/100,"") -> 15.28 | AE97: https://www.niche.com/k12/st-ann-school-yonkers-ny/ | AF97: 40 Brewster Ave, Yonkers, NY 10701 | AG97: 88884 | AH97: 2020
A98: =ROW()-1 -> 97 | B98: St. Elizabeth Ann Seton School | C98: x | F98: Shrub Oak | G98: NY | H98: Northeast | I98: Roman Catholic | J98: 44021 | K98: 150 | L98: School Website | M98: 1966 | O98: Yes | P98: https://wcbs880.radio.com/articles/news/ny-archdiocese-closing-20-catholic-schools | S98: 6900 | T98: https://seasschool.com/tuition-and-fees | U98: 3.6 | V98: =IF(U98<>"",K98*U98/100,"") -> 5.4 | W98: 6.8 | X98: =IF(W98<>"",K98*W98/100,"") -> 10.2 | Y98: 3.2 | Z98: =IF(Y98<>"",K98*Y98/100,"") -> 4.8 | AA98: 80.5 | AB98: =IF(AA98<>"",K98*AA98/100,"") -> 120.75 | AC98: 6 | AD98: =IF(AC98<>"",K98*AC98/100,"") -> 9 | AE98: https://www.niche.com/k12/st-elizabeth-ann-seton-school-shrub-oak-ny/ | AF98: 1375 E Main St, Shrub Oak, NY 10588 | AG98: 147052 | AH98: 2020
A99: =ROW()-1 -> 98 | B99: St. John’s School, Kingsbridge | C99: x | F99: The Bronx | G99: NY | H99: Northeast | I99: Roman Catholic | J99: 44021 | K99: 262 | L99: School Website | M99: 1910 | O99: Yes | P99: https://wcbs880.radio.com/articles/news/ny-archdiocese-closing-20-catholic-schools | S99: 6110 | T99: https://stjohnschoolbronx.org/tuition-and-fees | U99: 9.2 | V99: =IF(U99<>"",K99*U99/100,"") -> 24.104 | W99: 67.2 | X99: =IF(W99<>"",K99*W99/100,"") -> 176.064 | Y99: 6.3 | Z99: =IF(Y99<>"",K99*Y99/100,"") -> 16.506 | AA99: 11.5 | AB99: =IF(AA99<>"",K99*AA99/100,"") -> 30.13 | AC99: 5.8 | AD99: =IF(AC99<>"",K99*AC99/100,"") -> 15.196 | AE99: https://www.niche.com/k12/st-john-school-bronx-ny/ | AF99: 3143 Kingsbridge Ave, The Bronx, NY 10463 | AG99: 66512 | AH99: 2020
A100: =ROW()-1 -> 99 | B100: St. Joseph-St. Thomas School | C100: x | F100: Staten Island | G100: NY | H100: Northeast | I100: Roman Catholic | J100: 44021 | K100: 169 | L100: School Website | M100: 1966 | O100: Yes | P100: https://wcbs880.radio.com/articles/news/ny-archdiocese-closing-20-catholic-schools | S100: 5975 | T100: https://sjstschoolsi.org/tuition-amp-fees | U100: 0 | V100: =IF(U100<>"",K100*U100/100,"") -> 0 | W100: 4.7 | X100: =IF(W100<>"",K100*W100/100,"") -> 7.943 | Y100: 0.9 | Z100: =IF(Y100<>"",K100*Y100/100,"") -> 1.521 | AA100: 93.9 | AB100: =IF(AA100<>"",K100*AA100/100,"") -> 158.691 | AC100: 0.5 | AD100: =IF(AC100<>"",K100*AC100/100,"") -> 0.845 | AE100: https://www.niche.com/k12/ss-joseph--and--thomas-school-staten-island-ny/ | AF100: 50 Maguire Ave, Staten Island, NY 10309 | AG100: 127322 | AH100: 2020
...

Sheet Closures_summary_since_aug_2025
A1: Closures | B1: Type | I1: Total Enroll. | J1: Avg. Enroll. | K1: Avg. Tuition
B2: Catholic | C2: Episcopal | D2: Lutheran | E2: Christian | F2: Jewish | G2: Special needs | H2: Ind.
A3: =COUNTIF(All_closures!J2:J1005, ">=8/1/2025") -> 68 | B3: =COUNTIFS(All_closures!J2:J1005, ">=8/1/2025",All_closures!I2:I1005, "Roman Catholic") -> 50 | C3: =COUNTIFS(All_closures!J2:J1005, ">=8/1/2025",All_closures!I2:I1005, "Episcopal") -> 1 | D3: =COUNTIFS(All_closures!J2:J1005, ">=8/1/2025",All_closures!I2:I1005, "Lutheran") -> 0 | E3: =COUNTIFS(All_closures!J2:J1005, ">=8/1/2025",All_closures!I2:I1005, "Christian") -> 4 | F3: =COUNTIFS(All_closures!J2:J1005, ">=8/1/2025",All_closures!I2:I1005, "Jewish") -> 2 | G3: =COUNTIFS(All_closures!J2:J1005, ">=8/1/2025",All_closures!I2:I1005, "Special needs") -> 0 | H3: =COUNTIFS(All_closures!J2:J1005, ">=8/1/2025",All_closures!I2:I1005, "Independent") -> 11 | I3: =SUMIF(All_closures!J2:J1005, ">=8/1/2025", All_closures!K2:K1005) -> 8618 | J3: =if(A3=0,"", SUMIF(All_closures!J2:J1005, ">=8/1/2025", All_closures!K2:K1005)/A3) -> 126.73529 | K3: =if(A3=0,"",AVERAGEIF(All_closures!J2:J1005, ">=8/1/2025", All_closures!S2:S1005)) -> 11743.729

Sheet Closures_by_month_since_aug_202
B1: Number of Announced Closures
A2: =IF(EDATE(DATE(2025,6,1), row(A2))<TODAY(), EDATE(DATE(2025,6,1), Row(A2)), "") -> 45870 | B2: =IF(A2="","",COUNTIFS(All_closures!$J$2:$J$1005, ">="& EDATE(DATE(2025,6,1), row(B2)),All_closures!$J$2:$J$1005, "<"& EDATE(DATE(2025,7,1), row(B2)))) -> 0
A3: =IF(EDATE(DATE(2025,6,1), row(A3))<TODAY(), EDATE(DATE(2025,6,1), Row(A3)), "") -> 45901 | B3: =IF(A3="","",COUNTIFS(All_closures!$J$2:$J$1005, ">="& EDATE(DATE(2025,6,1), row(B3)),All_closures!$J$2:$J$1005, "<"& EDATE(DATE(2025,7,1), row(B3)))) -> 2
A4: =IF(EDATE(DATE(2025,6,1), row(A4))<TODAY(), EDATE(DATE(2025,6,1), Row(A4)), "") -> 45931 | B4: =IF(A4="","",COUNTIFS(All_closures!$J$2:$J$1005, ">="& EDATE(DATE(2025,6,1), row(B4)),All_closures!$J$2:$J$1005, "<"& EDATE(DATE(2025,7,1), row(B4)))) -> 2
A5: =IF(EDATE(DATE(2025,6,1), row(A5))<TODAY(), EDATE(DATE(2025,6,1), Row(A5)), "") -> 45962 | B5: =IF(A5="","",COUNTIFS(All_closures!$J$2:$J$1005, ">="& EDATE(DATE(2025,6,1), row(B5)),All_closures!$J$2:$J$1005, "<"& EDATE(DATE(2025,7,1), row(B5)))) -> 2
A6: =IF(EDATE(DATE(2025,6,1), row(A6))<TODAY(), EDATE(DATE(2025,6,1), Row(A6)), "") -> 45992 | B6: =IF(A6="","",COUNTIFS(All_closures!$J$2:$J$1005, ">="& EDATE(DATE(2025,6,1), row(B6)),All_closures!$J$2:$J$1005, "<"& EDATE(DATE(2025,7,1), row(B6)))) -> 2
A7: =IF(EDATE(DATE(2025,6,1), row(A7))<TODAY(), EDATE(DATE(2025,6,1), Row(A7)), "") -> 46023 | B7: =IF(A7="","",COUNTIFS(All_closures!$J$2:$J$1005, ">="& EDATE(DATE(2025,6,1), row(B7)),All_closures!$J$2:$J$1005, "<"& EDATE(DATE(2025,7,1), row(B7)))) -> 11
A8: =IF(EDATE(DATE(2025,6,1), row(A8))<TODAY(), EDATE(DATE(2025,6,1), Row(A8)), "") -> 46054 | B8: =IF(A8="","",COUNTIFS(All_closures!$J$2:$J$1005, ">="& EDATE(DATE(2025,6,1), row(B8)),All_closures!$J$2:$J$1005, "<"& EDATE(DATE(2025,7,1), row(B8)))) -> 12
A9: =IF(EDATE(DATE(2025,6,1), row(A9))<TODAY(), EDATE(DATE(2025,6,1), Row(A9)), "") -> 46082 | B9: =IF(A9="","",COUNTIFS(All_closures!$J$2:$J$1005, ">="& EDATE(DATE(2025,6,1), row(B9)),All_closures!$J$2:$J$1005, "<"& EDATE(DATE(2025,7,1), row(B9)))) -> 13
A10: =IF(EDATE(DATE(2025,6,1), row(A10))<TODAY(), EDATE(DATE(2025,6,1), Row(A10)), "") -> 46113 | B10: =IF(A10="","",COUNTIFS(All_closures!$J$2:$J$1005, ">="& EDATE(DATE(2025,6,1), row(B10)),All_closures!$J$2:$J$1005, "<"& EDATE(DATE(2025,7,1), row(B10)))) -> 1
A11: =IF(EDATE(DATE(2025,6,1), row(A11))<TODAY(), EDATE(DATE(2025,6,1), Row(A11)), "") -> 46143 | B11: =IF(A11="","",COUNTIFS(All_closures!$J$2:$J$1005, ">="& EDATE(DATE(2025,6,1), row(B11)),All_closures!$J$2:$J$1005, "<"& EDATE(DATE(2025,7,1), row(B11)))) -> 6
A12: =IF(EDATE(DATE(2025,6,1), row(A12))<TODAY(), EDATE(DATE(2025,6,1), Row(A12)), "") -> 46174 | B12: =IF(A12="","",COUNTIFS(All_closures!$J$2:$J$1005, ">="& EDATE(DATE(2025,6,1), row(B12)),All_closures!$J$2:$J$1005, "<"& EDATE(DATE(2025,7,1), row(B12)))) -> 13
A13: =IF(EDATE(DATE(2025,6,1), row(A13))<TODAY(), EDATE(DATE(2025,6,1), Row(A13)), "") -> 46204 | B13: =IF(A13="","",COUNTIFS(All_closures!$J$2:$J$1005, ">="& EDATE(DATE(2025,6,1), row(B13)),All_closures!$J$2:$J$1005, "<"& EDATE(DATE(2025,7,1), row(B13)))) -> 4
A59: =IF(EDATE(DATE(2023,6,1), row(A59))<TODAY(), EDATE(DATE(2023,6,1), Row(A59)), "") | B59: =IF(A59="","",COUNTIFS(All_closures!$J$2:$J$1005, ">="& EDATE(DATE(2023,6,1), row(B59)),All_closures!$J$2:$J$1005, "<"& EDATE(DATE(2023,7,1), row(B59))))
A60: =IF(EDATE(DATE(2023,6,1), row(A60))<TODAY(), EDATE(DATE(2023,6,1), Row(A60)), "") | B60: =IF(A60="","",COUNTIFS(All_closures!$J$2:$J$1005, ">="& EDATE(DATE(2023,6,1), row(B60)),All_closures!$J$2:$J$1005, "<"& EDATE(DATE(2023,7,1), row(B60))))
A61: =IF(EDATE(DATE(2023,6,1), row(A61))<TODAY(), EDATE(DATE(2023,6,1), Row(A61)), "") | B61: =IF(A61="","",COUNTIFS(All_closures!$J$2:$J$1005, ">="& EDATE(DATE(2023,6,1), row(B61)),All_closures!$J$2:$J$1005, "<"& EDATE(DATE(2023,7,1), row(B61))))

Sheet Closure_demographics_since_aug_
A2: White | B2: =SUMIF(All_closures!J2:J1005, ">=8/1/2025", All_closures!AB2:AB1005)/SUMIFS(All_closures!K2:K1005, All_closures!J2:J1005, ">=8/1/2025",All_closures!AA2:AA1005,"<>")*100 -> 34.217188
A3: Black | B3: =SUMIF(All_closures!J2:J1005, ">=8/1/2025", All_closures!V2:V1005)/SUMIFS(All_closures!K2:K1005, All_closures!J2:J1005, ">=8/1/2025",All_closures!U2:U1005,"<>")*100 -> 19.687336
A4: Hispanic | B4: =SUMIF(All_closures!J2:J1005, ">=8/1/2025", All_closures!X2:X1005)/SUMIFS(All_closures!K2:K1005, All_closures!J2:J1005, ">=8/1/2025",All_closures!W2:W1005,"<>")*100 -> 25.32558
A5: Asian | B5: =SUMIF(All_closures!J2:J1005, ">=8/1/2025", All_closures!Z2:Z1005)/SUMIFS(All_closures!K2:K1005, All_closures!J2:J1005, ">=8/1/2025",All_closures!Y2:Y1005,"<>")*100 -> 7.0354551
A6: Other | B6: =SUMIF(All_closures!J2:J1005, ">=8/1/2025", All_closures!AD2:AD1005)/SUMIFS(All_closures!K2:K1005, All_closures!J2:J1005, ">=8/1/2025",All_closures!AC2:AC1005,"<>")*100 -> 14.208043

Sheet cd_aug_2022
A2: White | B2: =SUMIF(All_closures!J2:J1005, ">=8/1/2022", All_closures!AB2:AB1005)/SUMIFS(All_closures!K2:K1005, All_closures!J2:J1005, ">=8/1/2022",All_closures!AA2:AA1005,"<>")*100 -> 37.741708
A3: Black | B3: =SUMIF(All_closures!J2:J1005, ">=8/1/2022", All_closures!V2:V1005)/SUMIFS(All_closures!K2:K1005, All_closures!J2:J1005, ">=8/1/2022",All_closures!U2:U1005,"<>")*100 -> 18.226107
A4: Hispanic | B4: =SUMIF(All_closures!J2:J1005, ">=8/1/2022", All_closures!X2:X1005)/SUMIFS(All_closures!K2:K1005, All_closures!J2:J1005, ">=8/1/2022",All_closures!W2:W1005,"<>")*100 -> 27.396031
A5: Asian | B5: =SUMIF(All_closures!J2:J1005, ">=8/1/2022", All_closures!Z2:Z1005)/SUMIFS(All_closures!K2:K1005, All_closures!J2:J1005, ">=8/1/2022",All_closures!Y2:Y1005,"<>")*100 -> 6.6029696
A6: Other | B6: =SUMIF(All_closures!J2:J1005, ">=8/1/2022", All_closures!AD2:AD1005)/SUMIFS(All_closures!K2:K1005, All_closures!J2:J1005, ">=8/1/2022",All_closures!AC2:AC1005,"<>")*100 -> 11.943724

Sheet cd_aug_2023
A2: White | B2: =SUMIF(All_closures!J2:J1005, ">=8/1/2023", All_closures!AB2:AB1005)/SUMIFS(All_closures!K2:K1005, All_closures!J2:J1005, ">=8/1/2023",All_closures!AA2:AA1005,"<>")*100 -> 39.380734
A3: Black | B3: =SUMIF(All_closures!J2:J1005, ">=8/1/2023", All_closures!V2:V1005)/SUMIFS(All_closures!K2:K1005, All_closures!J2:J1005, ">=8/1/2023",All_closures!U2:U1005,"<>")*100 -> 16.951307
A4: Hispanic | B4: =SUMIF(All_closures!J2:J1005, ">=8/1/2023", All_closures!X2:X1005)/SUMIFS(All_closures!K2:K1005, All_closures!J2:J1005, ">=8/1/2023",All_closures!W2:W1005,"<>")*100 -> 25.620096
A5: Asian | B5: =SUMIF(All_closures!J2:J1005, ">=8/1/2023", All_closures!Z2:Z1005)/SUMIFS(All_closures!K2:K1005, All_closures!J2:J1005, ">=8/1/2023",All_closures!Y2:Y1005,"<>")*100 -> 6.0575131
A6: Other | B6: =SUMIF(All_closures!J2:J1005, ">=8/1/2023", All_closures!AD2:AD1005)/SUMIFS(All_closures!K2:K1005, All_closures!J2:J1005, ">=8/1/2023",All_closures!AC2:AC1005,"<>")*100 -> 14.009621

Sheet cd_aug_2024
A2: White | B2: =SUMIF(All_closures!J2:J1005, ">=8/1/2024", All_closures!AB2:AB1005)/SUMIFS(All_closures!K2:K1005, All_closures!J2:J1005, ">=8/1/2024",All_closures!AA2:AA1005,"<>")*100 -> 35.429837
A3: Black | B3: =SUMIF(All_closures!J2:J1005, ">=8/1/2024", All_closures!V2:V1005)/SUMIFS(All_closures!K2:K1005, All_closures!J2:J1005, ">=8/1/2024",All_closures!U2:U1005,"<>")*100 -> 17.248469
A4: Hispanic | B4: =SUMIF(All_closures!J2:J1005, ">=8/1/2024", All_closures!X2:X1005)/SUMIFS(All_closures!K2:K1005, All_closures!J2:J1005, ">=8/1/2024",All_closures!W2:W1005,"<>")*100 -> 28.30703
A5: Asian | B5: =SUMIF(All_closures!J2:J1005, ">=8/1/2024", All_closures!Z2:Z1005)/SUMIFS(All_closures!K2:K1005, All_closures!J2:J1005, ">=8/1/2024",All_closures!Y2:Y1005,"<>")*100 -> 5.9887362
A6: Other | B6: =SUMIF(All_closures!J2:J1005, ">=8/1/2024", All_closures!AD2:AD1005)/SUMIFS(All_closures!K2:K1005, All_closures!J2:J1005, ">=8/1/2024",All_closures!AC2:AC1005,"<>")*100 -> 14.261352

Sheet Transfer_cost_to_public_schools
A1: =SUMIF(All_closures!J2:J1005, ">=8/1/2025", All_closures!K2:K1005)*18614 -> 160415452

Sheet Average_enrollment_loss
A1: =Closures_summary_since_aug_2025!J3 -> 126.73529

Sheet Net_school_gain_loss
A1: =Openings_summary_since_aug_2025!A3- Closures_summary_since_aug_2025!A3 -> -3

Sheet AnnualTransfer_cost_to_public_s
A2: =SUMIF(All_closures!J2:J1005, ">=8/1/2023", All_closures!K2:K1005)*18614 -> 451463956 | B2: 2023-24
A3: =SUMIF(All_closures!J2:J1006, ">=8/1/2024", All_closures!K2:K1006)*18614 -> 329132748 | B3: 2024-25
A4: =SUMIF(All_closures!J3:J1007, ">=8/1/2025", All_closures!K3:K1007)*18614 -> 160415452 | B4: 2025-26

Sheet Annual Net_school_gain_loss
A1: =opbm_aug_2022!C13-cbm_aug_2022!C13 -> -5 | B1: 2022-23
A2: =os_aug_2023!A3- cs_aug_2023!A3 -> -9 | B2: 2023–24
A3: =os_aug_2024!A3- cs_aug_2024!A3 -> -11 | B3: 2024-25
A4: =Openings_summary_since_aug_2025!A3- Closures_summary_since_aug_2025!A3 -> -3 | B4: 2024-25

Sheet opbm_aug_2023
B1: Number of Announced Openings
A2: =IF(EDATE(DATE(2023,6,1), row(A2))<TODAY(), EDATE(DATE(2023,6,1), Row(A2)), "") -> 45139 | B2: =IF(A2="","",COUNTIFS(All_openings!$H$2:$H$1034, ">="& EDATE(DATE(2023,6,1), row(A2)),All_openings!$H$2:$H$1034, "<"& EDATE(DATE(2023,7,1), row(A2)))) -> 6
A3: =IF(EDATE(DATE(2023,6,1), row(A3))<TODAY(), EDATE(DATE(2023,6,1), Row(A3)), "") -> 45170 | B3: =IF(A3="","",COUNTIFS(All_openings!$H$2:$H$1034, ">="& EDATE(DATE(2023,6,1), row(A3)),All_openings!$H$2:$H$1034, "<"& EDATE(DATE(2023,7,1), row(A3)))) -> 1
A4: =IF(EDATE(DATE(2023,6,1), row(A4))<TODAY(), EDATE(DATE(2023,6,1), Row(A4)), "") -> 45200 | B4: =IF(A4="","",COUNTIFS(All_openings!$H$2:$H$1034, ">="& EDATE(DATE(2023,6,1), row(A4)),All_openings!$H$2:$H$1034, "<"& EDATE(DATE(2023,7,1), row(A4)))) -> 5
A5: =IF(EDATE(DATE(2023,6,1), row(A5))<TODAY(), EDATE(DATE(2023,6,1), Row(A5)), "") -> 45231 | B5: =IF(A5="","",COUNTIFS(All_openings!$H$2:$H$1034, ">="& EDATE(DATE(2023,6,1), row(A5)),All_openings!$H$2:$H$1034, "<"& EDATE(DATE(2023,7,1), row(A5)))) -> 3
A6: =IF(EDATE(DATE(2023,6,1), row(A6))<TODAY(), EDATE(DATE(2023,6,1), Row(A6)), "") -> 45261 | B6: =IF(A6="","",COUNTIFS(All_openings!$H$2:$H$1034, ">="& EDATE(DATE(2023,6,1), row(A6)),All_openings!$H$2:$H$1034, "<"& EDATE(DATE(2023,7,1), row(A6)))) -> 0
A7: =IF(EDATE(DATE(2023,6,1), row(A7))<TODAY(), EDATE(DATE(2023,6,1), Row(A7)), "") -> 45292 | B7: =IF(A7="","",COUNTIFS(All_openings!$H$2:$H$1034, ">="& EDATE(DATE(2023,6,1), row(A7)),All_openings!$H$2:$H$1034, "<"& EDATE(DATE(2023,7,1), row(A7)))) -> 6
A8: =IF(EDATE(DATE(2023,6,1), row(A8))<TODAY(), EDATE(DATE(2023,6,1), Row(A8)), "") -> 45323 | B8: =IF(A8="","",COUNTIFS(All_openings!$H$2:$H$1034, ">="& EDATE(DATE(2023,6,1), row(A8)),All_openings!$H$2:$H$1034, "<"& EDATE(DATE(2023,7,1), row(A8)))) -> 4
A9: =IF(EDATE(DATE(2023,6,1), row(A9))<TODAY(), EDATE(DATE(2023,6,1), Row(A9)), "") -> 45352 | B9: =IF(A9="","",COUNTIFS(All_openings!$H$2:$H$1034, ">="& EDATE(DATE(2023,6,1), row(A9)),All_openings!$H$2:$H$1034, "<"& EDATE(DATE(2023,7,1), row(A9)))) -> 2
A10: =IF(EDATE(DATE(2023,6,1), row(A10))<TODAY(), EDATE(DATE(2023,6,1), Row(A10)), "") -> 45383 | B10: =IF(A10="","",COUNTIFS(All_openings!$H$2:$H$1034, ">="& EDATE(DATE(2023,6,1), row(A10)),All_openings!$H$2:$H$1034, "<"& EDATE(DATE(2023,7,1), row(A10)))) -> 5
A11: =IF(EDATE(DATE(2023,6,1), row(A11))<TODAY(), EDATE(DATE(2023,6,1), Row(A11)), "") -> 45413 | B11: =IF(A11="","",COUNTIFS(All_openings!$H$2:$H$1034, ">="& EDATE(DATE(2023,6,1), row(A11)),All_openings!$H$2:$H$1034, "<"& EDATE(DATE(2023,7,1), row(A11)))) -> 9
A12: =IF(EDATE(DATE(2023,6,1), row(A12))<TODAY(), EDATE(DATE(2023,6,1), Row(A12)), "") -> 45444 | B12: =IF(A12="","",COUNTIFS(All_openings!$H$2:$H$1034, ">="& EDATE(DATE(2023,6,1), row(A12)),All_openings!$H$2:$H$1034, "<"& EDATE(DATE(2023,7,1), row(A12)))) -> 2
A13: =IF(EDATE(DATE(2023,6,1), row(A13))<TODAY(), EDATE(DATE(2023,6,1), Row(A13)), "") -> 45474 | B13: =IF(A13="","",COUNTIFS(All_openings!$H$2:$H$1034, ">="& EDATE(DATE(2023,6,1), row(A13)),All_openings!$H$2:$H$1034, "<"& EDATE(DATE(2023,7,1), row(A13)))) -> 8
A43: =IF(EDATE(DATE(2022,6,1), row(A43))<TODAY(), EDATE(DATE(2022,6,1), Row(A43)), "") -> 46023 | B43: =IF(A43="","",COUNTIFS(All_openings!$H$2:$H$1034, ">="& EDATE(DATE(2023,6,1), row(A43)),All_openings!$H$2:$H$1034, "<"& EDATE(DATE(2023,7,1), row(A43)))) -> 0
A44: =IF(EDATE(DATE(2022,6,1), row(A44))<TODAY(), EDATE(DATE(2022,6,1), Row(A44)), "") -> 46054 | B44: =IF(A44="","",COUNTIFS(All_openings!$H$2:$H$1034, ">="& EDATE(DATE(2023,6,1), row(A44)),All_openings!$H$2:$H$1034, "<"& EDATE(DATE(2023,7,1), row(A44)))) -> 0
A45: =IF(EDATE(DATE(2022,6,1), row(A45))<TODAY(), EDATE(DATE(2022,6,1), Row(A45)), "") -> 46082 | B45: =IF(A45="","",COUNTIFS(All_openings!$H$2:$H$1034, ">="& EDATE(DATE(2023,6,1), row(A45)),All_openings!$H$2:$H$1034, "<"& EDATE(DATE(2023,7,1), row(A45)))) -> 0
A46: =IF(EDATE(DATE(2022,6,1), row(A46))<TODAY(), EDATE(DATE(2022,6,1), Row(A46)), "") -> 46113 | B46: =IF(A46="","",COUNTIFS(All_openings!$H$2:$H$1034, ">="& EDATE(DATE(2023,6,1), row(A46)),All_openings!$H$2:$H$1034, "<"& EDATE(DATE(2023,7,1), row(A46)))) -> 0
A47: =IF(EDATE(DATE(2022,6,1), row(A47))<TODAY(), EDATE(DATE(2022,6,1), Row(A47)), "") -> 46143 | B47: =IF(A47="","",COUNTIFS(All_openings!$H$2:$H$1034, ">="& EDATE(DATE(2023,6,1), row(A47)),All_openings!$H$2:$H$1034, "<"& EDATE(DATE(2023,7,1), row(A47)))) -> 0
A48: =IF(EDATE(DATE(2022,6,1), row(A48))<TODAY(), EDATE(DATE(2022,6,1), Row(A48)), "") -> 46174 | B48: =IF(A48="","",COUNTIFS(All_openings!$H$2:$H$1034, ">="& EDATE(DATE(2023,6,1), row(A48)),All_openings!$H$2:$H$1034, "<"& EDATE(DATE(2023,7,1), row(A48)))) -> 0
A49: =IF(EDATE(DATE(2022,6,1), row(A49))<TODAY(), EDATE(DATE(2022,6,1), Row(A49)), "") -> 46204 | B49: =IF(A49="","",COUNTIFS(All_openings!$H$2:$H$1034, ">="& EDATE(DATE(2022,6,1), row(A49)),All_openings!$H$2:$H$1034, "<"& EDATE(DATE(2022,7,1), row(A49)))) -> 5
A50: =IF(EDATE(DATE(2022,6,1), row(A50))<TODAY(), EDATE(DATE(2022,6,1), Row(A50)), "") | B50: =IF(A50="","",COUNTIFS(All_openings!$H$2:$H$1034, ">="& EDATE(DATE(2022,6,1), row(A50)),All_openings!$H$2:$H$1034, "<"& EDATE(DATE(2022,7,1), row(A50))))

Sheet opbm_aug_2022
B1: Number of Announced Openings
A2: =IF(EDATE(DATE(2022,6,1), row(A2))<TODAY(), EDATE(DATE(2022,6,1), Row(A2)), "") -> 44774 | B2: =IF(A2="","",COUNTIFS(All_openings!$H$2:$H$1034, ">="& EDATE(DATE(2022,6,1), row(A2)),All_openings!$H$2:$H$1034, "<"& EDATE(DATE(2022,7,1), row(A2)))) -> 11
A3: =IF(EDATE(DATE(2022,6,1), row(A3))<TODAY(), EDATE(DATE(2022,6,1), Row(A3)), "") -> 44805 | B3: =IF(A3="","",COUNTIFS(All_openings!$H$2:$H$1034, ">="& EDATE(DATE(2022,6,1), row(A3)),All_openings!$H$2:$H$1034, "<"& EDATE(DATE(2022,7,1), row(A3)))) -> 1
A4: =IF(EDATE(DATE(2022,6,1), row(A4))<TODAY(), EDATE(DATE(2022,6,1), Row(A4)), "") -> 44835 | B4: =IF(A4="","",COUNTIFS(All_openings!$H$2:$H$1034, ">="& EDATE(DATE(2022,6,1), row(A4)),All_openings!$H$2:$H$1034, "<"& EDATE(DATE(2022,7,1), row(A4)))) -> 2
A5: =IF(EDATE(DATE(2022,6,1), row(A5))<TODAY(), EDATE(DATE(2022,6,1), Row(A5)), "") -> 44866 | B5: =IF(A5="","",COUNTIFS(All_openings!$H$2:$H$1034, ">="& EDATE(DATE(2022,6,1), row(A5)),All_openings!$H$2:$H$1034, "<"& EDATE(DATE(2022,7,1), row(A5)))) -> 2
A6: =IF(EDATE(DATE(2022,6,1), row(A6))<TODAY(), EDATE(DATE(2022,6,1), Row(A6)), "") -> 44896 | B6: =IF(A6="","",COUNTIFS(All_openings!$H$2:$H$1034, ">="& EDATE(DATE(2022,6,1), row(A6)),All_openings!$H$2:$H$1034, "<"& EDATE(DATE(2022,7,1), row(A6)))) -> 0
A7: =IF(EDATE(DATE(2022,6,1), row(A7))<TODAY(), EDATE(DATE(2022,6,1), Row(A7)), "") -> 44927 | B7: =IF(A7="","",COUNTIFS(All_openings!$H$2:$H$1034, ">="& EDATE(DATE(2022,6,1), row(A7)),All_openings!$H$2:$H$1034, "<"& EDATE(DATE(2022,7,1), row(A7)))) -> 2
A8: =IF(EDATE(DATE(2022,6,1), row(A8))<TODAY(), EDATE(DATE(2022,6,1), Row(A8)), "") -> 44958 | B8: =IF(A8="","",COUNTIFS(All_openings!$H$2:$H$1034, ">="& EDATE(DATE(2022,6,1), row(A8)),All_openings!$H$2:$H$1034, "<"& EDATE(DATE(2022,7,1), row(A8)))) -> 4
A9: =IF(EDATE(DATE(2022,6,1), row(A9))<TODAY(), EDATE(DATE(2022,6,1), Row(A9)), "") -> 44986 | B9: =IF(A9="","",COUNTIFS(All_openings!$H$2:$H$1034, ">="& EDATE(DATE(2022,6,1), row(A9)),All_openings!$H$2:$H$1034, "<"& EDATE(DATE(2022,7,1), row(A9)))) -> 4
A10: =IF(EDATE(DATE(2022,6,1), row(A10))<TODAY(), EDATE(DATE(2022,6,1), Row(A10)), "") -> 45017 | B10: =IF(A10="","",COUNTIFS(All_openings!$H$2:$H$1034, ">="& EDATE(DATE(2022,6,1), row(A10)),All_openings!$H$2:$H$1034, "<"& EDATE(DATE(2022,7,1), row(A10)))) -> 7
A11: =IF(EDATE(DATE(2022,6,1), row(A11))<TODAY(), EDATE(DATE(2022,6,1), Row(A11)), "") -> 45047 | B11: =IF(A11="","",COUNTIFS(All_openings!$H$2:$H$1034, ">="& EDATE(DATE(2022,6,1), row(A11)),All_openings!$H$2:$H$1034, "<"& EDATE(DATE(2022,7,1), row(A11)))) -> 3
A12: =IF(EDATE(DATE(2022,6,1), row(A12))<TODAY(), EDATE(DATE(2022,6,1), Row(A12)), "") -> 45078 | B12: =IF(A12="","",COUNTIFS(All_openings!$H$2:$H$1034, ">="& EDATE(DATE(2022,6,1), row(A12)),All_openings!$H$2:$H$1034, "<"& EDATE(DATE(2022,7,1), row(A12)))) -> 5
A13: =IF(EDATE(DATE(2022,6,1), row(A13))<TODAY(), EDATE(DATE(2022,6,1), Row(A13)), "") -> 45108 | B13: =IF(A13="","",COUNTIFS(All_openings!$H$2:$H$1034, ">="& EDATE(DATE(2022,6,1), row(A13)),All_openings!$H$2:$H$1034, "<"& EDATE(DATE(2022,7,1), row(A13)))) -> 8 | C13: =SUM(B2:B13) -> 49
A14: =IF(EDATE(DATE(2022,6,1), row(A14))<TODAY(), EDATE(DATE(2022,6,1), Row(A14)), "") -> 45139 | B14: =IF(A14="","",COUNTIFS(All_openings!$H$2:$H$1034, ">="& EDATE(DATE(2022,6,1), row(A14)),All_openings!$H$2:$H$1034, "<"& EDATE(DATE(2022,7,1), row(A14)))) -> 6
A15: =IF(EDATE(DATE(2022,6,1), row(A15))<TODAY(), EDATE(DATE(2022,6,1), Row(A15)), "") -> 45170 | B15: =IF(A15="","",COUNTIFS(All_openings!$H$2:$H$1034, ">="& EDATE(DATE(2022,6,1), row(A15)),All_openings!$H$2:$H$1034, "<"& EDATE(DATE(2022,7,1), row(A15)))) -> 1
A16: =IF(EDATE(DATE(2022,6,1), row(A16))<TODAY(), EDATE(DATE(2022,6,1), Row(A16)), "") -> 45200 | B16: =IF(A16="","",COUNTIFS(All_openings!$H$2:$H$1034, ">="& EDATE(DATE(2022,6,1), row(A16)),All_openings!$H$2:$H$1034, "<"& EDATE(DATE(2022,7,1), row(A16)))) -> 5
A17: =IF(EDATE(DATE(2022,6,1), row(A17))<TODAY(), EDATE(DATE(2022,6,1), Row(A17)), "") -> 45231 | B17: =IF(A17="","",COUNTIFS(All_openings!$H$2:$H$1034, ">="& EDATE(DATE(2022,6,1), row(A17)),All_openings!$H$2:$H$1034, "<"& EDATE(DATE(2022,7,1), row(A17)))) -> 3
A18: =IF(EDATE(DATE(2022,6,1), row(A18))<TODAY(), EDATE(DATE(2022,6,1), Row(A18)), "") -> 45261 | B18: =IF(A18="","",COUNTIFS(All_openings!$H$2:$H$1034, ">="& EDATE(DATE(2022,6,1), row(A18)),All_openings!$H$2:$H$1034, "<"& EDATE(DATE(2022,7,1), row(A18)))) -> 0
A19: =IF(EDATE(DATE(2022,6,1), row(A19))<TODAY(), EDATE(DATE(2022,6,1), Row(A19)), "") -> 45292 | B19: =IF(A19="","",COUNTIFS(All_openings!$H$2:$H$1034, ">="& EDATE(DATE(2022,6,1), row(A19)),All_openings!$H$2:$H$1034, "<"& EDATE(DATE(2022,7,1), row(A19)))) -> 6
A20: =IF(EDATE(DATE(2022,6,1), row(A20))<TODAY(), EDATE(DATE(2022,6,1), Row(A20)), "") -> 45323 | B20: =IF(A20="","",COUNTIFS(All_openings!$H$2:$H$1034, ">="& EDATE(DATE(2022,6,1), row(A20)),All_openings!$H$2:$H$1034, "<"& EDATE(DATE(2022,7,1), row(A20)))) -> 4
A21: =IF(EDATE(DATE(2022,6,1), row(A21))<TODAY(), EDATE(DATE(2022,6,1), Row(A21)), "") -> 45352 | B21: =IF(A21="","",COUNTIFS(All_openings!$H$2:$H$1034, ">="& EDATE(DATE(2022,6,1), row(A21)),All_openings!$H$2:$H$1034, "<"& EDATE(DATE(2022,7,1), row(A21)))) -> 2
A22: =IF(EDATE(DATE(2022,6,1), row(A22))<TODAY(), EDATE(DATE(2022,6,1), Row(A22)), "") -> 45383 | B22: =IF(A22="","",COUNTIFS(All_openings!$H$2:$H$1034, ">="& EDATE(DATE(2022,6,1), row(A22)),All_openings!$H$2:$H$1034, "<"& EDATE(DATE(2022,7,1), row(A22)))) -> 5
A23: =IF(EDATE(DATE(2022,6,1), row(A23))<TODAY(), EDATE(DATE(2022,6,1), Row(A23)), "") -> 45413 | B23: =IF(A23="","",COUNTIFS(All_openings!$H$2:$H$1034, ">="& EDATE(DATE(2022,6,1), row(A23)),All_openings!$H$2:$H$1034, "<"& EDATE(DATE(2022,7,1), row(A23)))) -> 9
A24: =IF(EDATE(DATE(2022,6,1), row(A24))<TODAY(), EDATE(DATE(2022,6,1), Row(A24)), "") -> 45444 | B24: =IF(A24="","",COUNTIFS(All_openings!$H$2:$H$1034, ">="& EDATE(DATE(2022,6,1), row(A24)),All_openings!$H$2:$H$1034, "<"& EDATE(DATE(2022,7,1), row(A24)))) -> 2
A25: =IF(EDATE(DATE(2022,6,1), row(A25))<TODAY(), EDATE(DATE(2022,6,1), Row(A25)), "") -> 45474 | B25: =IF(A25="","",COUNTIFS(All_openings!$H$2:$H$1034, ">="& EDATE(DATE(2022,6,1), row(A25)),All_openings!$H$2:$H$1034, "<"& EDATE(DATE(2022,7,1), row(A25)))) -> 8 | C25: =SUM(B14:B25) -> 51
A26: =IF(EDATE(DATE(2022,6,1), row(A26))<TODAY(), EDATE(DATE(2022,6,1), Row(A26)), "") -> 45505 | B26: =IF(A26="","",COUNTIFS(All_openings!$H$2:$H$1034, ">="& EDATE(DATE(2022,6,1), row(A26)),All_openings!$H$2:$H$1034, "<"& EDATE(DATE(2022,7,1), row(A26)))) -> 9
A27: =IF(EDATE(DATE(2022,6,1), row(A27))<TODAY(), EDATE(DATE(2022,6,1), Row(A27)), "") -> 45536 | B27: =IF(A27="","",COUNTIFS(All_openings!$H$2:$H$1034, ">="& EDATE(DATE(2022,6,1), row(A27)),All_openings!$H$2:$H$1034, "<"& EDATE(DATE(2022,7,1), row(A27)))) -> 2
A28: =IF(EDATE(DATE(2022,6,1), row(A28))<TODAY(), EDATE(DATE(2022,6,1), Row(A28)), "") -> 45566 | B28: =IF(A28="","",COUNTIFS(All_openings!$H$2:$H$1034, ">="& EDATE(DATE(2022,6,1), row(A28)),All_openings!$H$2:$H$1034, "<"& EDATE(DATE(2022,7,1), row(A28)))) -> 2
A29: =IF(EDATE(DATE(2022,6,1), row(A29))<TODAY(), EDATE(DATE(2022,6,1), Row(A29)), "") -> 45597 | B29: =IF(A29="","",COUNTIFS(All_openings!$H$2:$H$1034, ">="& EDATE(DATE(2022,6,1), row(A29)),All_openings!$H$2:$H$1034, "<"& EDATE(DATE(2022,7,1), row(A29)))) -> 0
A30: =IF(EDATE(DATE(2022,6,1), row(A30))<TODAY(), EDATE(DATE(2022,6,1), Row(A30)), "") -> 45627 | B30: =IF(A30="","",COUNTIFS(All_openings!$H$2:$H$1034, ">="& EDATE(DATE(2022,6,1), row(A30)),All_openings!$H$2:$H$1034, "<"& EDATE(DATE(2022,7,1), row(A30)))) -> 3
A31: =IF(EDATE(DATE(2022,6,1), row(A31))<TODAY(), EDATE(DATE(2022,6,1), Row(A31)), "") -> 45658 | B31: =IF(A31="","",COUNTIFS(All_openings!$H$2:$H$1034, ">="& EDATE(DATE(2022,6,1), row(A31)),All_openings!$H$2:$H$1034, "<"& EDATE(DATE(2022,7,1), row(A31)))) -> 2
A32: =IF(EDATE(DATE(2022,6,1), row(A32))<TODAY(), EDATE(DATE(2022,6,1), Row(A32)), "") -> 45689 | B32: =IF(A32="","",COUNTIFS(All_openings!$H$2:$H$1034, ">="& EDATE(DATE(2022,6,1), row(A32)),All_openings!$H$2:$H$1034, "<"& EDATE(DATE(2022,7,1), row(A32)))) -> 3
A33: =IF(EDATE(DATE(2022,6,1), row(A33))<TODAY(), EDATE(DATE(2022,6,1), Row(A33)), "") -> 45717 | B33: =IF(A33="","",COUNTIFS(All_openings!$H$2:$H$1034, ">="& EDATE(DATE(2022,6,1), row(A33)),All_openings!$H$2:$H$1034, "<"& EDATE(DATE(2022,7,1), row(A33)))) -> 1
A34: =IF(EDATE(DATE(2022,6,1), row(A34))<TODAY(), EDATE(DATE(2022,6,1), Row(A34)), "") -> 45748 | B34: =IF(A34="","",COUNTIFS(All_openings!$H$2:$H$1034, ">="& EDATE(DATE(2022,6,1), row(A34)),All_openings!$H$2:$H$1034, "<"& EDATE(DATE(2022,7,1), row(A34)))) -> 0
A35: =IF(EDATE(DATE(2022,6,1), row(A35))<TODAY(), EDATE(DATE(2022,6,1), Row(A35)), "") -> 45778 | B35: =IF(A35="","",COUNTIFS(All_openings!$H$2:$H$1034, ">="& EDATE(DATE(2022,6,1), row(A35)),All_openings!$H$2:$H$1034, "<"& EDATE(DATE(2022,7,1), row(A35)))) -> 4
A36: =IF(EDATE(DATE(2022,6,1), row(A36))<TODAY(), EDATE(DATE(2022,6,1), Row(A36)), "") -> 45809 | B36: =IF(A36="","",COUNTIFS(All_openings!$H$2:$H$1034, ">="& EDATE(DATE(2022,6,1), row(A36)),All_openings!$H$2:$H$1034, "<"& EDATE(DATE(2022,7,1), row(A36)))) -> 8
A37: =IF(EDATE(DATE(2022,6,1), row(A37))<TODAY(), EDATE(DATE(2022,6,1), Row(A37)), "") -> 45839 | B37: =IF(A37="","",COUNTIFS(All_openings!$H$2:$H$1034, ">="& EDATE(DATE(2022,6,1), row(A37)),All_openings!$H$2:$H$1034, "<"& EDATE(DATE(2022,7,1), row(A37)))) -> 10
... A50: =IF(EDATE(DATE(2022,6,1), row(A50))<TODAY(), EDATE(DATE(2022,6,1), Row(A50)), "") | B50: =IF(A50="","",COUNTIFS(All_openings!$H$2:$H$1034, ">="& EDATE(DATE(2022,6,1), row(A50)),All_openings!$H$2:$H$1034, "<"& EDATE(DATE(2022,7,1), row(A50))))

Sheet opbm_aug_2024
B1: Number of Announced Openings
A2: =IF(EDATE(DATE(2024,6,1), row(A2))<TODAY(), EDATE(DATE(2024,6,1), Row(A2)), "") -> 45505 | B2: =IF(A2="","",COUNTIFS(All_openings!$H$2:$H$1034, ">="& EDATE(DATE(2024,6,1), row(A2)),All_openings!$H$2:$H$1034, "<"& EDATE(DATE(2024,7,1), row(A2)))) -> 9
A3: =IF(EDATE(DATE(2024,6,1), row(A3))<TODAY(), EDATE(DATE(2024,6,1), Row(A3)), "") -> 45536 | B3: =IF(A3="","",COUNTIFS(All_openings!$H$2:$H$1034, ">="& EDATE(DATE(2024,6,1), row(A3)),All_openings!$H$2:$H$1034, "<"& EDATE(DATE(2024,7,1), row(A3)))) -> 2
A4: =IF(EDATE(DATE(2024,6,1), row(A4))<TODAY(), EDATE(DATE(2024,6,1), Row(A4)), "") -> 45566 | B4: =IF(A4="","",COUNTIFS(All_openings!$H$2:$H$1034, ">="& EDATE(DATE(2024,6,1), row(A4)),All_openings!$H$2:$H$1034, "<"& EDATE(DATE(2024,7,1), row(A4)))) -> 2
A5: =IF(EDATE(DATE(2024,6,1), row(A5))<TODAY(), EDATE(DATE(2024,6,1), Row(A5)), "") -> 45597 | B5: =IF(A5="","",COUNTIFS(All_openings!$H$2:$H$1034, ">="& EDATE(DATE(2024,6,1), row(A5)),All_openings!$H$2:$H$1034, "<"& EDATE(DATE(2024,7,1), row(A5)))) -> 0
A6: =IF(EDATE(DATE(2024,6,1), row(A6))<TODAY(), EDATE(DATE(2024,6,1), Row(A6)), "") -> 45627 | B6: =IF(A6="","",COUNTIFS(All_openings!$H$2:$H$1034, ">="& EDATE(DATE(2024,6,1), row(A6)),All_openings!$H$2:$H$1034, "<"& EDATE(DATE(2024,7,1), row(A6)))) -> 3
A7: =IF(EDATE(DATE(2024,6,1), row(A7))<TODAY(), EDATE(DATE(2024,6,1), Row(A7)), "") -> 45658 | B7: =IF(A7="","",COUNTIFS(All_openings!$H$2:$H$1034, ">="& EDATE(DATE(2024,6,1), row(A7)),All_openings!$H$2:$H$1034, "<"& EDATE(DATE(2024,7,1), row(A7)))) -> 2
A8: =IF(EDATE(DATE(2024,6,1), row(A8))<TODAY(), EDATE(DATE(2024,6,1), Row(A8)), "") -> 45689 | B8: =IF(A8="","",COUNTIFS(All_openings!$H$2:$H$1034, ">="& EDATE(DATE(2024,6,1), row(A8)),All_openings!$H$2:$H$1034, "<"& EDATE(DATE(2024,7,1), row(A8)))) -> 3
A9: =IF(EDATE(DATE(2024,6,1), row(A9))<TODAY(), EDATE(DATE(2024,6,1), Row(A9)), "") -> 45717 | B9: =IF(A9="","",COUNTIFS(All_openings!$H$2:$H$1034, ">="& EDATE(DATE(2024,6,1), row(A9)),All_openings!$H$2:$H$1034, "<"& EDATE(DATE(2024,7,1), row(A9)))) -> 1
A10: =IF(EDATE(DATE(2024,6,1), row(A10))<TODAY(), EDATE(DATE(2024,6,1), Row(A10)), "") -> 45748 | B10: =IF(A10="","",COUNTIFS(All_openings!$H$2:$H$1034, ">="& EDATE(DATE(2024,6,1), row(A10)),All_openings!$H$2:$H$1034, "<"& EDATE(DATE(2024,7,1), row(A10)))) -> 0
A11: =IF(EDATE(DATE(2024,6,1), row(A11))<TODAY(), EDATE(DATE(2024,6,1), Row(A11)), "") -> 45778 | B11: =IF(A11="","",COUNTIFS(All_openings!$H$2:$H$1034, ">="& EDATE(DATE(2024,6,1), row(A11)),All_openings!$H$2:$H$1034, "<"& EDATE(DATE(2024,7,1), row(A11)))) -> 4
A12: =IF(EDATE(DATE(2024,6,1), row(A12))<TODAY(), EDATE(DATE(2024,6,1), Row(A12)), "") -> 45809 | B12: =IF(A12="","",COUNTIFS(All_openings!$H$2:$H$1034, ">="& EDATE(DATE(2024,6,1), row(A12)),All_openings!$H$2:$H$1034, "<"& EDATE(DATE(2024,7,1), row(A12)))) -> 8
A13: =IF(EDATE(DATE(2024,6,1), row(A13))<TODAY(), EDATE(DATE(2024,6,1), Row(A13)), "") -> 45839 | B13: =IF(A13="","",COUNTIFS(All_openings!$H$2:$H$1034, ">="& EDATE(DATE(2024,6,1), row(A13)),All_openings!$H$2:$H$1034, "<"& EDATE(DATE(2024,7,1), row(A13)))) -> 10
A14: =IF(EDATE(DATE(2024,6,1), row(A14))<TODAY(), EDATE(DATE(2024,6,1), Row(A14)), "") -> 45870 | B14: =IF(A14="","",COUNTIFS(All_openings!$H$2:$H$1034, ">="& EDATE(DATE(2024,6,1), row(A14)),All_openings!$H$2:$H$1034, "<"& EDATE(DATE(2024,7,1), row(A14)))) -> 9
B15: =IF(A15="","",COUNTIFS(All_openings!$H$2:$H$1034, ">="& EDATE(DATE(2024,6,1), row(A15)),All_openings!$H$2:$H$1034, "<"& EDATE(DATE(2024,7,1), row(A15))))

Sheet os_aug_2023
A1: Openings | B1: Type
A2: Total | B2: Catholic | C2: Episcopal | D2: Lutheran | E2: Christian | F2: Jewish | G2: Special needs | H2: Ind.
A3: =COUNTIFS(All_openings!H2:H1033, ">=8/1/2023", All_openings!H2:H1033, "<=7/31/2024") -> 51 | B3: =COUNTIFS(All_openings!H2:H1033, ">=8/1/2023", All_openings!H2:H1033, "<=7/31/2024", All_openings!G2:G1033, "Roman Catholic") -> 13 | C3: =COUNTIFS(All_openings!H2:H1033, ">=8/1/2023", All_openings!H2:H1033, "<=7/31/2024",All_openings!G2:G1033, "Episcopal") -> 0 | D3: =COUNTIFS(All_openings!H2:H1033, ">=8/1/2023", All_openings!H2:H1033, "<=7/31/2024",All_openings!G2:G1033, "Lutheran") -> 0 | E3: =COUNTIFS(All_openings!H2:H1033, ">=8/1/2023", All_openings!H2:H1033, "<=7/31/2024",All_openings!G2:G1033, "Christian") -> 23 | F3: =COUNTIFS(All_openings!H2:H1033, ">=8/1/2023", All_openings!H2:H1033, "<=7/31/2024",All_openings!G2:G1033, "Jewish") -> 0 | G3: =COUNTIFS(All_openings!H2:H1033, ">=8/1/2023", All_openings!H2:H1033, "<=7/31/2024",All_openings!G2:G1033, "Special needs") -> 0 | H3: =COUNTIFS(All_openings!H2:H1033, ">=8/1/2023", All_openings!H2:H1033, "<=7/31/2024",All_openings!G2:G1033, "Independent") -> 15

Sheet os_aug_2024
A1: Openings | B1: Type
A2: Total | B2: Catholic | C2: Episcopal | D2: Lutheran | E2: Christian | F2: Jewish | G2: Special needs | H2: Ind.
A3: =COUNTIF(All_openings!H2:H1033, ">=8/1/2024") -> 109 | B3: =COUNTIFS(All_openings!H2:H1033, ">=8/1/2024",All_openings!G2:G1033, "Roman Catholic") -> 20 | C3: =COUNTIFS(All_openings!H2:H1033, ">=8/1/2024",All_openings!G2:G1033, "Episcopal") -> 0 | D3: =COUNTIFS(All_openings!H2:H1033, ">=8/1/2024",All_openings!G2:G1033, "Lutheran") -> 2 | E3: =COUNTIFS(All_openings!H2:H1033, ">=8/1/2024",All_openings!G2:G1033, "Christian") -> 24 | F3: =COUNTIFS(All_openings!H2:H1033, ">=8/1/2024",All_openings!G2:G1033, "Jewish") -> 5 | G3: =COUNTIFS(All_openings!H2:H1033, ">=8/1/2024",All_openings!G2:G1033, "Special needs") -> 7 | H3: =COUNTIFS(All_openings!H2:H1033, ">=8/1/2024",All_openings!G2:G1033, "Independent") -> 47

Sheet Links
